Workbook
Name A_ALL_000050.SZ: #REF!
Name A_ALL_000413.SZ: #REF!
Name A_ALL_000725.SZ: #REF!
Name A_ALL_002371.SZ: #REF!
Name A_ALL_002415.SZ: #REF!
Name A_ALL_002415.SZ_: #REF!
Name A_ALL_002456.SZ: #REF!
Name A_ALL_002876.SZ: #REF!
Name A_ALL_2018.HK: #REF!
Name A_ALL_2303.TW: #REF!
Name A_ALL_4966.TWO: #REF!
Name A_ALL_600584.SS: #REF!
Name A_ALL_600699.SS: #REF!
Name A_ALL_603986.SS: #REF!
Name A_ALL_6415.TW: #REF!
Name A_ALL_KEYWORDS_TYPE_Breakdown_EQTY_200008919: #REF!
Name A_ALL_KEYWORDS_TYPE_ScalarContributed_EQTY_200006786: #REF!,#REF!,#REF!,#REF!
Name A_ALL_KEYWORDS_TYPE_ScalarContributed_EQTY_200008919: #REF!,#REF!
Name A_ALL_KEYWORDS_TYPE_ScalarContributed_EQTY_200011172: #REF!,#REF!
Name A_ALL_KEYWORDS_TYPE_ScalarContributed_EQTY_200012735: #REF!,#REF!
Name A_ALL_KEYWORDS_TYPE_ScalarContributed_EQTY_200012909: #REF!,#REF!
Name A_ALL_KEYWORDS_TYPE_ScalarContributed_EQTY_200012913: #REF!,#REF!
Name A_ALL_KEYWORDS_TYPE_ScalarContributed_EQTY_200016087: #REF!,#REF!
Name A_ALL_KEYWORDS_TYPE_ScalarContributed_EQTY_200019558: #REF!,#REF!
Name A_ALL_KEYWORDS_TYPE_ScalarContributed_EQTY_200019559: #REF!,#REF!
Name A_ALL_KEYWORDS_TYPE_ScalarContributed_EQTY_200019876: #REF!,#REF!,#REF!
Name A_ALL_KEYWORDS_TYPE_ScalarContributed_ISSR_208002015: #REF!,#REF!
Name A_ALL_KEYWORDS_TYPE_ScalarContributed_ISSR_208007067: #REF!,#REF!
Name A_ALL_KEYWORDS_TYPE_ScalarContributed_ISSR_208010212: #REF!,#REF!
Name A_ALL_KEYWORDS_TYPE_ScalarContributed_ISSR_208015000: #REF!,#REF!
Name A_ALL_KEYWORDS_TYPE_ScalarContributed_ISSR_208019081: #REF!,#REF!
Name A_ALL_KEYWORDS_TYPE_ScalarContributed_ISSR_208019322: #REF!,#REF!
Name A_ALL_KEYWORDS_TYPE_ScalarContributed_ISSR_208021173: #REF!,#REF!
Name A_ALL_KEYWORDS_TYPE_ScalarContributed_ISSR_208021175: #REF!,#REF!
Name A_ALL_KEYWORDS_TYPE_Vector_EQTY_200006785: #REF!,#REF!,#REF!,#REF!,#REF!
Name A_ALL_KEYWORDS_TYPE_Vector_EQTY_200006786: #REF!,#REF!,#REF!,#REF!,#REF!,#REF!
Name A_ALL_KEYWORDS_TYPE_Vector_EQTY_200008918: #REF!,#REF!,#REF!,#REF!,#REF!
Name A_ALL_KEYWORDS_TYPE_Vector_EQTY_200011172: #REF!,#REF!,#REF!,#REF!,#REF!
Name A_ALL_KEYWORDS_TYPE_Vector_EQTY_200012735: #REF!,#REF!,#REF!,#REF!,#REF!
Name A_ALL_KEYWORDS_TYPE_Vector_EQTY_200012909: #REF!,#REF!,#REF!,#REF!,#REF!
Name A_ALL_KEYWORDS_TYPE_Vector_EQTY_200012913: #REF!,#REF!,#REF!,#REF!,#REF!
Name A_ALL_KEYWORDS_TYPE_Vector_EQTY_200013283: #REF!,#REF!,#REF!,#REF!,#REF!
Name A_ALL_KEYWORDS_TYPE_Vector_EQTY_200016087: #REF!,#REF!,#REF!,#REF!,#REF!
Name A_ALL_KEYWORDS_TYPE_Vector_EQTY_200017468: #REF!,#REF!,#REF!,#REF!,#REF!
Name A_ALL_KEYWORDS_TYPE_Vector_EQTY_200018245: #REF!,#REF!,#REF!,#REF!,#REF!
Name A_ALL_KEYWORDS_TYPE_Vector_EQTY_200020142: #REF!,#REF!,#REF!,#REF!,#REF!
Name A_ALL_KEYWORDS_TYPE_Vector_EQTY_200020296: #REF!,#REF!,#REF!,#REF!,#REF!
Name A_ALL_KEYWORDS_TYPE_Vector_EQTY_200021697: #REF!,#REF!,#REF!,#REF!,#REF!
Name A_ALL_KEYWORDS_TYPE_Vector_EQTY_200021698: #REF!,#REF!,#REF!,#REF!,#REF!
Name A_ALL_KEYWORDS_TYPE_Vector_ISSR_208002015: #REF!,#REF!,#REF!,#REF!,#REF!,#REF!,#REF!,#REF!,#REF!,#REF!,#REF!,#REF!,#REF!
Name A_ALL_KEYWORDS_TYPE_Vector_ISSR_208006410: #REF!,#REF!,#REF!,#REF!,#REF!,#REF!,#REF!,#REF!,#REF!,#REF!,#REF!
Name A_ALL_KEYWORDS_TYPE_Vector_ISSR_208007067: #REF!,#REF!,#REF!,#REF!,#REF!,#REF!,#REF!,#REF!,#REF!,#REF!,#REF!,#REF!,#REF!
Name A_ALL_KEYWORDS_TYPE_Vector_ISSR_208008548: #REF!,#REF!,#REF!,#REF!,#REF!,#REF!,#REF!,#REF!,#REF!,#REF!,#REF!,#REF!,#REF!,#REF!,#REF!,#REF!
Name A_ALL_KEYWORDS_TYPE_Vector_ISSR_208009698: #REF!,#REF!,#REF!,#REF!,#REF!,#REF!,#REF!,#REF!,#REF!,#REF!,#REF!,#REF!,#REF!,#REF!
Name A_ALL_KEYWORDS_TYPE_Vector_ISSR_208009912: #REF!,#REF!,#REF!,#REF!,#REF!,#REF!,#REF!,#REF!,#REF!,#REF!,#REF!,#REF!,#REF!,#REF!,#REF!
Name A_ALL_KEYWORDS_TYPE_Vector_ISSR_208009916: #REF!,#REF!,#REF!,#REF!,#REF!,#REF!,#REF!,#REF!,#REF!,#REF!,#REF!,#REF!,#REF!,#REF!
Name A_ALL_KEYWORDS_TYPE_Vector_ISSR_208010212: #REF!,#REF!,#REF!,#REF!,#REF!,#REF!,#REF!,#REF!,#REF!,#REF!,#REF!,#REF!,#REF!,#REF!
Name A_ALL_KEYWORDS_TYPE_Vector_ISSR_208011603: #REF!,#REF!,#REF!,#REF!,#REF!,#REF!,#REF!,#REF!,#REF!,#REF!,#REF!
Name A_ALL_KEYWORDS_TYPE_Vector_ISSR_208013035: #REF!,#REF!,#REF!,#REF!,#REF!,#REF!,#REF!,#REF!,#REF!,#REF!,#REF!,#REF!,#REF!,#REF!,#REF!
Name A_ALL_KEYWORDS_TYPE_Vector_ISSR_208013036: #REF!,#REF!,#REF!,#REF!,#REF!,#REF!,#REF!,#REF!,#REF!,#REF!,#REF!

Sheet Model
A2: Innolight (300308.SZ)
A3: In Rmb millions | W3: 2014 | X3: 2014 | Y3: 2014 | Z3: 2014 | AA3: =W3+1 -> 2015 | AB3: =X3+1 -> 2015 | AC3: =Y3+1 -> 2015 | AD3: =Z3+1 -> 2015 | AE3: =AA3+1 -> 2016 | AF3: =AB3+1 -> 2016 | AG3: =AC3+1 -> 2016 | AH3: =AD3+1 -> 2016 | ... BZ3: =BV3+1 -> 2027
C4: 2009 | D4: 2010 | E4: 2011 | F4: 2012 | G4: 2013 | H4: 2014 | I4: 2015 | J4: 2016 | K4: 2017 | L4: =K4+1 -> 2018 | M4: =L4+1 -> 2019 | N4: =M4+1 -> 2020 | O4: =N4+1 -> 2021 | P4: =O4+1 -> 2022 | Q4: =P4+1 -> 2023 | R4: =Q4+1 -> 2024 | S4: =R4+1 -> 2025 | ... U4: =T4+1 -> 2027 | W4: 1Q14 | X4: 2Q14 | Y4: 3Q14 | Z4: 4Q14 | AA4: 1Q15 | AB4: 2Q15 | AC4: 3Q15 | AD4: 4Q15 | AE4: 1Q16 | AF4: 2Q16 | AG4: 3Q16 | AH4: 4Q16 | AI4: 1Q17 | AJ4: 2Q17 | AK4: 3Q17 | AL4: 4Q17 | AM4: 1Q18 | AN4: 2Q18 | AO4: 3Q18 | AP4: 4Q18 | AQ4: 1Q19 | AR4: 2Q19 | AS4: 3Q19 | AT4: 4Q19 | AU4: 1Q20 | AV4: 2Q20 | AW4: 3Q20 | AX4: 4Q20 | AY4: 1Q21 | AZ4: 2Q21 | BA4: 3Q21 | BB4: 4Q21 | BC4: 1Q22 | BD4: 2Q22 | BE4: 3Q22 | BF4: 4Q22 | BG4: 1Q23 | BH4: 2Q23 | BI4: 3Q23 | BJ4: 4Q23 | BK4: 1Q24 | BL4: 2Q24 | BM4: 3Q24 | BN4: 4Q24 | BO4: 1Q25 | BP4: 2Q25 | BQ4: 3Q25 | BR4: 4Q25 | BS4: 1Q26 | BT4: 2Q26 | BU4: 3Q26 | BV4: 4Q26 | BW4: 1Q27 | BX4: 2Q27 | BY4: 3Q27 | BZ4: 4Q27
B5: Income statements | C5: =C4 -> 2009 | D5: =D4 -> 2010 | E5: =E4 -> 2011 | F5: =F4 -> 2012 | G5: =G4 -> 2013 | H5: =H4 -> 2014 | I5: =I4 -> 2015 | J5: =J4 -> 2016 | ... U5: =U4 -> 2027 | W5: =W4 -> 1Q14 | X5: =X4 -> 2Q14 | Y5: =Y4 -> 3Q14 | Z5: =Z4 -> 4Q14 | AA5: =AA4 -> 1Q15 | AB5: =AB4 -> 2Q15 | AC5: =AC4 -> 3Q15 | AD5: =AD4 -> 4Q15 | ... BZ5: =BZ4 -> 4Q27
B7: Total sales/revenues | C7: 90.373718 | D7: 123.54713 | E7: 162.07917 | F7: 116.65963 | G7: 90.52615 | H7: 118.74621 | I7: 121.40994 | J7: 131.62038 | K7: 2357.0835 | L7: 5156.3142 | M7: 4757.677 | N7: 7049.5901 | O7: 7695.4048 | P7: =SUMIF($W$3:$BR$3,P$4,$W7:$BR7) -> 9641.7948 | Q7: =SUMIF($W$3:$BR$3,Q$4,$W7:$BR7) -> 10717.984 | R7: =SUMIF($W$3:$BR$3,R$4,$W7:$BR7) -> 23862.16 | S7: =SUMIF($W$3:$BR$3,S$4,$W7:$BR7) -> 35041.957 | T7: =SUMIF($W$3:$BZ$3,T$4,$W7:$BZ7) -> 50582.612 | U7: =SUMIF($W$3:$BZ$3,U$4,$W7:$BZ7) -> 61409.384 | W7: 38.360696 | X7: 19.824628 | Y7: 21.886566 | Z7: 38.674316 | AA7: 19.18802 | AB7: 23.88869 | AC7: 26.209578 | AD7: 52.123649 | AE7: 10.325244 | AF7: 46.362725 | AG7: 25.951711 | AH7: 48.980704 | AI7: 14.564576 | AJ7: 56.023104 | AK7: 1068.8855 | AL7: 1217.6103 | AM7: 1398.5982 | AN7: 1426.9623 | AO7: 1377.2606 | AP7: 953.49315 | AQ7: 875.64684 | AR7: 1159.5558 | AS7: 1248.7111 | AT7: 1473.7632 | AU7: 1326.0904 | AV7: 1918.5856 | AW7: 1960.1096 | AX7: 1844.8045 | AY7: 1471.7584 | AZ7: 1826.094 | BA7: 2024.2344 | BB7: 2373.318 | BC7: 2088.6226 | BD7: 2142.4212 | BE7: 2633.9444 | BF7: 2776.8065 | BG7: 1837.1632 | BH7: 2166.818 | BI7: 3026.3091 | BJ7: 3687.6941 | BK7: 4842.5469 | BL7: 5956.0473 | BM7: 6514.0076 | BN7: 6549.5579 | BO7: 6674.1765 | BP7: 8114.8984 | BQ7: =Assumption!P12 -> 9544.9328 | BR7: =Assumption!Q12 -> 10707.949 | BS7: =Assumption!R12 -> 10818.019 | BT7: =Assumption!S12 -> 12058.533 | BU7: =Assumption!T12 -> 13278.777 | BV7: =Assumption!U12 -> 14427.284 | BW7: =Assumption!V12 -> 13381.138 | BX7: =Assumption!W12 -> 15125.613 | ... BZ7: =Assumption!Y12 -> 16752.354
B8: COGS | C8: 45.395267 | D8: 60.78985 | E8: 80.740715 | F8: 59.862063 | G8: 53.85313 | H8: 80.199978 | I8: 88.449923 | J8: 91.398229 | K8: 1725.5088 | L8: 3749.9692 | M8: 3467.7751 | N8: 5256.9582 | O8: 5727.3999 | P8: =SUMIF($W$3:$BR$3,P$4,$W8:$BR8) -> 6815.5917 | Q8: =SUMIF($W$3:$BR$3,Q$4,$W8:$BR8) -> 7181.8774 | R8: =SUMIF($W$3:$BR$3,R$4,$W8:$BR8) -> 15795.567 | S8: =SUMIF($W$3:$BR$3,S$4,$W8:$BR8) -> 20461.892 | T8: =SUMIF($W$3:$BZ$3,T$4,$W8:$BZ8) -> 27736.865 | U8: =SUMIF($W$3:$BZ$3,U$4,$W8:$BZ8) -> 33440.372 | W8: 25.231973 | X8: 13.893568 | Y8: 15.721471 | Z8: 25.352966 | AA8: 16.14646 | AB8: 14.791145 | AC8: 19.536104 | AD8: 37.976214 | AE8: 6.930456 | AF8: 33.933494 | AG8: 18.631501 | AH8: 31.902778 | AI8: 9.9617218 | AJ8: 36.66104 | AK8: 781.51313 | AL8: 897.37294 | AM8: 1058.9192 | AN8: 1056.9059 | AO8: 992.99302 | AP8: 641.151 | AQ8: 629.53872 | AR8: 826.71743 | AS8: 898.30543 | AT8: 1113.2135 | AU8: 995.31096 | AV8: 1428.5533 | AW8: 1482.6544 | AX8: 1350.4395 | AY8: 1102.2124 | AZ8: 1390.9275 | BA8: 1527.9706 | BB8: 1706.2893 | BC8: 1539.71 | BD8: 1558.047 | BE8: 1850.7677 | BF8: 1867.067 | BG8: 1294.2925 | BH8: 1492.9706 | BI8: 2011.1547 | BJ8: 2383.4596 | BK8: 3256.1729 | BL8: 3964.601 | BM8: 4323.0185 | BN8: 4251.7742 | BO8: 4224.6871 | BP8: 4748.2798 | BQ8: =(BQ7-BQ12) -> 5453.9066 | BR8: =(BR7-BR12) -> 6035.0181 | BS8: =(BS7-BS12) -> 6021.4456 | BT8: =(BT7-BT12) -> 6689.9262 | BU8: =(BU7-BU12) -> 7235.995 | BV8: =(BV7-BV12) -> 7789.4979 | BW8: =(BW7-BW12) -> 7398.0969 | BX8: =(BX7-BX12) -> 8331.0321 | ... BZ8: =(BZ7-BZ12) -> 8945.2654
B9: Others | BA9: 0 | BB9: 0 | BC9: 0 | BD9: 0 | BE9: 0 | BF9: 0 | BG9: 0 | BH9: 0 | BI9: 0 | BJ9: 0 | BK9: 0 | BL9: 0 | BM9: 0 | BN9: 0 | BO9: 0 | BP9: 0 | BQ9: 0 | BR9: 0 | BS9: 0 | BT9: 0 | BU9: 0 | BV9: 0 | BW9: 0 | BX9: 0 | BY9: 0 | BZ9: 0
B10: Total COGS | C10: =C8+C9 -> 45.395267 | D10: =D8+D9 -> 60.78985 | E10: =E8+E9 -> 80.740715 | F10: =F8+F9 -> 59.862063 | G10: =G8+G9 -> 53.85313 | H10: =H8+H9 -> 80.199978 | I10: =I8+I9 -> 88.449923 | J10: =J8+J9 -> 91.398229 | ... U10: =U8+U9 -> 33440.372 | W10: =W8+W9 -> 25.231973 | X10: =X8+X9 -> 13.893568 | Y10: =Y8+Y9 -> 15.721471 | Z10: =Z8+Z9 -> 25.352966 | AA10: =AA8+AA9 -> 16.14646 | AB10: =AB8+AB9 -> 14.791145 | AC10: =AC8+AC9 -> 19.536104 | AD10: =AD8+AD9 -> 37.976214 | ... BZ10: =BZ8+BZ9 -> 8945.2654
B12: Gross profit | C12: =+C7-C10 -> 44.978451 | D12: =+D7-D10 -> 62.757275 | E12: =+E7-E10 -> 81.338459 | F12: =+F7-F10 -> 56.797565 | G12: =+G7-G10 -> 36.673021 | H12: =+H7-H10 -> 38.546229 | I12: =+I7-I10 -> 32.960014 | J12: =+J7-J10 -> 40.222155 | ... U12: =+U7-U10 -> 27969.012 | W12: =+W7-W8 -> 13.128723 | X12: =+X7-X8 -> 5.9310606 | Y12: =+Y7-Y8 -> 6.1650949 | Z12: =+Z7-Z8 -> 13.321351 | AA12: =+AA7-AA8 -> 3.04156 | AB12: =+AB7-AB8 -> 9.0975455 | AC12: =+AC7-AC8 -> 6.6734737 | AD12: =+AD7-AD8 -> 14.147435 | ... BP12: =+BP7-BP8 -> 3366.6186 | BQ12: =+Assumption!P260 -> 4091.0261 | BR12: =+Assumption!Q260 -> 4672.9309 | BS12: =+Assumption!R260 -> 4796.573 | BT12: =+Assumption!S260 -> 5368.6066 | BU12: =+Assumption!T260 -> 6042.782 | BV12: =+Assumption!U260 -> 6637.7858 | BW12: =+Assumption!V260 -> 5983.0413 | BX12: =+Assumption!W260 -> 6794.5812 | ... BZ12: =+Assumption!Y260 -> 7807.0885
B13: Gross margin % | C13: =C12/C$7 -> 0.49769393 | D13: =D12/D$7 -> 0.50796225 | E13: =E12/E$7 -> 0.50184399 | F13: =F12/F$7 -> 0.48686565 | G13: =G12/G$7 -> 0.40510969 | H13: =H12/H$7 -> 0.32461019 | I13: =I12/I$7 -> 0.27147707 | J13: =J12/J$7 -> 0.30559214 | ... U13: =U12/U$7 -> 0.45545176 | W13: =W12/W$7 -> 0.34224413 | X13: =X12/X$7 -> 0.29917639 | Y13: =Y12/Y$7 -> 0.28168397 | Z13: =Z12/Z$7 -> 0.34444955 | AA13: =AA12/AA$7 -> 0.15851349 | AB13: =AB12/AB$7 -> 0.38083066 | AC13: =AC12/AC$7 -> 0.25461965 | AD13: =AD12/AD$7 -> 0.27142065 | ... BZ13: =BZ12/BZ$7 -> 0.46602934
B15: Operating expense | C15: =C16+C17+C18+C19 -> 11.332818 | D15: =D16+D17+D18+D19 -> 12.913831 | E15: =E16+E17+E18+E19 -> 20.299495 | F15: =F16+F17+F18+F19 -> 26.722241 | G15: =G16+G17+G18+G19 -> 35.194178 | H15: =H16+H17+H18+H19 -> 40.911796 | I15: =I16+I17+I18+I19 -> 36.656887 | J15: =J16+J17+J18+J19 -> 47.264307 | ... S15: =S16+S17+S18+S19 -> 2640.2498 | T15: =SUMIF($W$3:$BZ$3,T$4,$W15:$BZ15) -> 3112.8343 | U15: =SUMIF($W$3:$BZ$3,U$4,$W15:$BZ15) -> 3605.8216 | W15: =W16+W17+W18+W19 -> 11.258247 | X15: =X16+X17+X18+X19 -> 11.489717 | Y15: =Y16+Y17+Y18+Y19 -> 10.457258 | Z15: =Z16+Z17+Z18+Z19 -> 7.7065744 | AA15: =AA16+AA17+AA18+AA19 -> 8.2691805 | AB15: =AB16+AB17+AB18+AB19 -> 9.6986421 | AC15: =AC16+AC17+AC18+AC19 -> 8.3204128 | AD15: =AD16+AD17+AD18+AD19 -> 10.368652 | ... BZ15: =BZ16+BZ17+BZ18+BZ19 -> 1284.5958
B16: Sales tax | C16: 0 | D16: 0.06298541 | E16: 1.4004868 | F16: 1.099027 | G16: 0.56964762 | H16: 0.82507994 | I16: 1.0701732 | J16: 2.7481565 | K16: 6.4469656 | L16: 10.182498 | M16: 16.597006 | N16: 21.973475 | O16: 21.012073 | P16: =SUMIF($W$3:$BR$3,P$4,$W16:$BR16) -> 62.999788 | Q16: =SUMIF($W$3:$BR$3,Q$4,$W16:$BR16) -> 50.63378 | R16: =SUMIF($W$3:$BR$3,R$4,$W16:$BR16) -> 46.908394 | S16: =SUMIF($W$3:$BR$3,S$4,$W16:$BR16) -> 85.463532 | T16: =SUMIF($W$3:$BZ$3,T$4,$W16:$BZ16) -> 101.16522 | U16: =SUMIF($W$3:$BZ$3,U$4,$W16:$BZ16) -> 122.81877 | W16: 0.55219575 | X16: 0.10853597 | Y16: 0.00229916 | Z16: 0.16204906 | AA16: 0.14487756 | AB16: 0.07281863 | AC16: 0.0283934 | AD16: 0.82408357 | AE16: 0.03186119 | AF16: 0.72010979 | AG16: 0.05195411 | AH16: 1.9442314 | AI16: 0.51099421 | AJ16: 0.92781885 | AK16: 2.2470597 | AL16: 2.7610929 | AM16: 2.3088487 | AN16: 2.5529347 | AO16: 2.7681516 | AP16: 2.5525628 | AQ16: 1.9911661 | AR16: 6.1621618 | AS16: 4.7861507 | AT16: 3.657528 | AU16: 2.9466197 | AV16: 3.916195 | AW16: 5.0707368 | AX16: 10.039923 | AY16: 4.717842 | AZ16: 4.4937591 | BA16: 0.88746472 | BB16: 10.913007 | BC16: 5.8975238 | BD16: 5.8595587 | BE16: 5.542641 | BF16: 45.700065 | BG16: 4.4719719 | BH16: 4.7102712 | BI16: 6.9594304 | BJ16: 34.492107 | BK16: 35.521545 | BL16: -13.935084 | BM16: 11.294864 | BN16: 14.02707 | BO16: 10.625145 | BP16: 34.332624 | BQ16: =BQ$7*BQ80 -> 19.089866 | BR16: =BR$7*BR80 -> 21.415898 | BS16: =BS$7*BS80 -> 21.636037 | BT16: =BT$7*BT80 -> 24.117066 | BU16: =BU$7*BU80 -> 26.557554 | BV16: =BV$7*BV80 -> 28.854567 | BW16: =BW$7*BW80 -> 26.762276 | BX16: =BX$7*BX80 -> 30.251227 | ... BZ16: =BZ$7*BZ80 -> 33.504708
B17: Marketing expense | C17: 2.4544344 | D17: 2.3420214 | E17: 3.0847901 | F17: 3.8827589 | G17: 3.2593719 | H17: 4.6013024 | I17: 3.840157 | J17: 3.6971494 | K17: 32.022266 | L17: 60.233089 | M17: 54.84009 | N17: 106.71352 | O17: 73.036515 | P17: =SUMIF($W$3:$BR$3,P$4,$W17:$BR17) -> 90.729655 | Q17: =SUMIF($W$3:$BR$3,Q$4,$W17:$BR17) -> 124.83987 | R17: =SUMIF($W$3:$BR$3,R$4,$W17:$BR17) -> 199.26812 | S17: =SUMIF($W$3:$BR$3,S$4,$W17:$BR17) -> 235.03778 | T17: =SUMIF($W$3:$BZ$3,T$4,$W17:$BZ17) -> 276 | U17: =SUMIF($W$3:$BZ$3,U$4,$W17:$BZ17) -> 327 | W17: 0.73327105 | X17: 1.0667551 | Y17: 1.5364283 | Z17: 1.264848 | AA17: 0.67469142 | AB17: 1.4096789 | AC17: 1.0156605 | AD17: 0.74012607 | AE17: 1.115911 | AF17: 1.0306053 | AG17: 0.70578328 | AH17: 0.84484985 | AI17: 0.79184657 | AJ17: 0.87935077 | AK17: 16.740203 | AL17: 13.610865 | AM17: 13.991238 | AN17: 13.120208 | AO17: 15.721994 | AP17: 17.399649 | AQ17: 13.217812 | AR17: 11.288367 | AS17: 13.066561 | AT17: 17.267349 | AU17: 14.232697 | AV17: 16.347494 | AW17: 43.276412 | AX17: 32.856912 | AY17: 15.488438 | AZ17: 14.38302 | BA17: 17.745673 | BB17: 25.419384 | BC17: 18.569296 | BD17: 20.622353 | BE17: 30.167126 | BF17: 21.37088 | BG17: 22.253674 | BH17: 21.415118 | BI17: 36.879483 | BJ17: 44.291597 | BK17: 44.826387 | BL17: 44.347236 | BM17: 45.975534 | BN17: 64.118962 | BO17: 50.101678 | BP17: 50.986105 | BQ17: =+Assumption!P278 -> 63.45 | BR17: =+Assumption!Q278 -> 70.5 | BS17: =+Assumption!R278 -> 60.72 | BT17: =+Assumption!S278 -> 63.48 | BU17: =+Assumption!T278 -> 69 | BV17: =+Assumption!U278 -> 82.8 | BW17: =+Assumption!V278 -> 71.94 | BX17: =+Assumption!W278 -> 75.21 | ... BZ17: =+Assumption!Y278 -> 98.1
B18: Administrative expense | C18: 2.3807042 | D18: 3.1882013 | E18: 7.4623433 | F18: 13.732331 | G18: 22.669534 | H18: 28.16479 | I18: 25.248878 | J18: 34.069814 | K18: 116.58222 | L18: 253.34741 | M18: 274.58427 | N18: 370.13664 | O18: 434.16554 | P18: =SUMIF($W$3:$BR$3,P$4,$W18:$BR18) -> 506.80314 | Q18: =SUMIF($W$3:$BR$3,Q$4,$W18:$BR18) -> 433.59245 | R18: =SUMIF($W$3:$BR$3,R$4,$W18:$BR18) -> 679.53645 | S18: =SUMIF($W$3:$BR$3,S$4,$W18:$BR18) -> 726.20985 | T18: =SUMIF($W$3:$BZ$3,T$4,$W18:$BZ18) -> 807 | U18: =SUMIF($W$3:$BZ$3,U$4,$W18:$BZ18) -> 865 | W18: 8.142624 | X18: 8.4842703 | Y18: 7.0883745 | Z18: 4.4495216 | AA18: 5.8251917 | AB18: 6.5917247 | AC18: 5.6519391 | AD18: 7.1800224 | AE18: 8.5104732 | AF18: 9.9425762 | AG18: 6.9774187 | AH18: 8.6393455 | AI18: 7.559295 | AJ18: 8.5351047 | AK18: 65.359824 | AL18: =K18-SUM(AI18:AK18) -> 35.128001 | AM18: 58.470632 | AN18: 66.315122 | AO18: 67.906138 | AP18: 62.967676 | AQ18: 58.167642 | AR18: 60.689629 | AS18: 64.815741 | AT18: 90.911259 | AU18: 72.470847 | AV18: 81.432431 | AW18: 97.284163 | AX18: 118.9492 | AY18: 93.026836 | AZ18: 105.21694 | BA18: 103.77852 | BB18: 132.14325 | BC18: 136.72008 | BD18: 106.51918 | BE18: 136.89125 | BF18: 126.67263 | BG18: 90.76264 | BH18: 96.312496 | BI18: 102.30281 | BJ18: 144.2145 | BK18: 129.26853 | BL18: 177.20631 | BM18: 165.27938 | BN18: 207.78223 | BO18: 148.38785 | BP18: 142.242 | BQ18: =+Assumption!P279 -> 195.26 | BR18: =+Assumption!Q279 -> 240.32 | BS18: =+Assumption!R279 -> 177.54 | BT18: =+Assumption!S279 -> 185.61 | BU18: =+Assumption!T279 -> 201.75 | BV18: =+Assumption!U279 -> 242.1 | BW18: =+Assumption!V279 -> 190.3 | BX18: =+Assumption!W279 -> 198.95 | ... BZ18: =+Assumption!Y279 -> 259.5
B19: R&D | C19: 6.4976791 | D19: 7.3206229 | E19: 8.3518744 | F19: 8.0081239 | G19: 8.6956249 | H19: 7.3206229 | I19: 6.4976791 | J19: 6.7491872 | K19: =SUM(AI19:AL19) -> 129.32626 | L19: 309.4728 | M19: 362.35314 | N19: 506.42898 | O19: 541.09931 | P19: =SUMIF($W$3:$BR$3,P$4,$W19:$BR19) -> 767.01896 | Q19: =SUMIF($W$3:$BR$3,Q$4,$W19:$BR19) -> 739.36758 | R19: =SUMIF($W$3:$BR$3,R$4,$W19:$BR19) -> 1244.0269 | S19: =SUMIF($W$3:$BR$3,S$4,$W19:$BR19) -> 1593.5387 | T19: =SUMIF($W$3:$BZ$3,T$4,$W19:$BZ19) -> 1928.6691 | U19: =SUMIF($W$3:$BZ$3,U$4,$W19:$BZ19) -> 2291.0029 | W19: 1.8301557 | X19: 1.8301557 | Y19: 1.8301557 | Z19: 1.8301557 | AA19: 1.6244198 | AB19: 1.6244198 | AC19: 1.6244198 | AD19: 1.6244198 | AE19: 1.6872968 | AF19: 1.6872968 | AG19: 1.6872968 | AH19: 1.6872968 | AI19: 2 | AJ19: 2 | AK19: 32.326256 | AL19: 93 | AM19: 77.368201 | AN19: 77.368201 | AO19: 80.220011 | AP19: 72.204235 | AQ19: 49.432657 | AR19: 93.978855 | AS19: 81.079602 | AT19: 137.86202 | AU19: 88.009579 | AV19: 87.662414 | AW19: 116.57199 | AX19: 214.185 | AY19: 119.93255 | AZ19: 107.65336 | BA19: 124.63302 | BB19: 188.88037 | BC19: 154.44994 | BD19: 194.57905 | BE19: 211.55509 | BF19: 206.43488 | BG19: 156.38524 | BH19: 166.11044 | BI19: 148.86798 | BJ19: 268.00392 | BK19: 257.38558 | BL19: 267.32643 | BM19: 217.26564 | BN19: 502.04921 | BO19: 290.34105 | BP19: 295.27595 | BQ19: =+Assumption!P280 -> 386.92728 | BR19: =+Assumption!Q280 -> 620.99439 | BS19: =+Assumption!R280 -> 366.44713 | BT19: =+Assumption!S280 -> 385.73382 | BU19: =+Assumption!T280 -> 424.30721 | BV19: =+Assumption!U280 -> 752.18096 | BW19: =+Assumption!V280 -> 435.29055 | BX19: =+Assumption!W280 -> 458.20057 | ... BZ19: =+Assumption!Y280 -> 893.49112
B20: Operating income | C20: =+C12-C15 -> 33.645634 | D20: =+D12-D15 -> 49.843444 | E20: =+E12-E15 -> 61.038965 | F20: =+F12-F15 -> 30.075325 | G20: =+G12-G15 -> 1.4788426 | H20: =+H12-H15 -> -2.3655665 | I20: =+I12-I15 -> -3.6968731 | J20: =+J12-J15 -> -7.0421513 | ... U20: =+U12-U15 -> 24363.191 | W20: =W12-W15 -> 1.8704763 | X20: =X12-X15 -> -5.5586565 | Y20: =Y12-Y15 -> -4.2921627 | Z20: =Z12-Z15 -> 5.6147765 | AA20: =AA12-AA15 -> -5.2276204 | AB20: =AB12-AB15 -> -0.60109657 | AC20: =AC12-AC15 -> -1.6469391 | AD20: =AD12-AD15 -> 3.7787829 | ... BZ20: =BZ12-BZ15 -> 6522.4927
B22: Other income (loss)
B23: Finance cost | C23: =C24+C25 -> 0.4314 | D23: =D24+D25 -> 0.8052 | E23: =E24+E25 -> 0.90568252 | F23: =F24+F25 -> 7.5852688 | G23: =G24+G25 -> 12.762349 | H23: =H24+H25 -> 11.70566 | I23: =I24+I25 -> 6.9046709 | J23: =J24+J25 -> 6.0126569 | ... U23: =U24+U25 -> 80 | W23: =W24+W25 -> 3.0064433 | X23: =X24+X25 -> 3.0064433 | Y23: =Y24+Y25 -> 2.8463865 | Z23: =Z24+Z25 -> 2.8463865 | AA23: =AA24+AA25 -> 2.8703947 | AB23: =AB24+AB25 -> 2.8703947 | AC23: =AC24+AC25 -> 0.5819408 | AD23: =AD24+AD25 -> 0.5819408 | ... BZ23: =BZ24+BZ25 -> 20
B24: Interest income | C24: 0.4314 | D24: 0.8052 | E24: 0.90568252 | F24: 7.5852688 | G24: 12.762349 | H24: 11.70566 | I24: 6.9046709 | J24: 6.0126569 | K24: 3.8327269 | L24: 5.7473989 | M24: 18.132316 | N24: 9.8038459 | O24: 15.721944 | P24: =SUMIF($W$3:$BR$3,P$4,$W24:$BR24) -> 37.571588 | Q24: =SUMIF($W$3:$BR$3,Q$4,$W24:$BR24) -> 104.62682 | R24: =SUMIF($W$3:$BR$3,R$4,$W24:$BR24) -> 108.03043 | S24: =SUMIF($W$3:$BR$3,S$4,$W24:$BR24) -> 190.55613 | T24: =SUMIF($W$3:$BZ$3,T$4,$W24:$BZ24) -> 160 | U24: =SUMIF($W$3:$BZ$3,U$4,$W24:$BZ24) -> 160 | W24: 3.0064433 | X24: 3.0064433 | Y24: 2.8463865 | Z24: 2.8463865 | AA24: 2.8703947 | AB24: 2.8703947 | AC24: 0.5819408 | AD24: 0.5819408 | AE24: 0.40029653 | AF24: 0.40029653 | AG24: 2.6060319 | AH24: 2.6060319 | AI24: 0.098226635 | AJ24: 0.098226635 | AK24: 1.8181368 | AL24: 1.8181368 | AM24: 1.2000018 | AN24: 1.2000018 | AO24: 3.4596026 | AP24: 0 | AQ24: 2.8260327 | AR24: 8.0180394 | AS24: 5.1867575 | AT24: 2.1014867 | AU24: 1.4523238 | AV24: 3.544259 | AW24: 2.1558405 | AX24: 2.6514226 | AY24: 3.0367062 | AZ24: 2.225764 | BA24: 2.1572471 | BB24: 8.3022272 | BC24: 6.2698819 | BD24: 7.3917769 | BE24: 10.946838 | BF24: 12.963092 | BG24: 15.114083 | BH24: 30.854243 | BI24: 29.940874 | BJ24: 28.71762 | BK24: 24.634075 | BL24: 17.35339 | BM24: 37.96675 | BN24: 28.076218 | BO24: 41.677725 | BP24: 68.878409 | BQ24: 40 | BR24: 40 | BS24: 40 | BT24: 40 | BU24: 40 | BV24: 40 | BW24: 40 | BX24: 40 | BY24: 40 | BZ24: 40
B25: Interest expense | C25: 0 | D25: 0 | E25: 0 | F25: 0 | G25: 0 | H25: 0 | I25: 0 | J25: 0 | K25: 0 | L25: -50.25234 | M25: -50.163872 | N25: -61.806144 | O25: -82.987066 | P25: =SUMIF($W$3:$BR$3,P$4,$W25:$BR25) -> -63.360987 | Q25: =SUMIF($W$3:$BR$3,Q$4,$W25:$BR25) -> -54.024538 | R25: =SUMIF($W$3:$BR$3,R$4,$W25:$BR25) -> -53.553118 | S25: =SUMIF($W$3:$BR$3,S$4,$W25:$BR25) -> -73.758301 | T25: =SUMIF($W$3:$BZ$3,T$4,$W25:$BZ25) -> -80 | U25: =SUMIF($W$3:$BZ$3,U$4,$W25:$BZ25) -> -80 | W25: 0 | X25: 0 | Y25: 0 | Z25: 0 | AA25: 0 | AB25: 0 | AC25: 0 | AD25: 0 | AE25: 0 | AF25: 0 | AG25: 0 | AH25: 0 | AI25: 0 | AJ25: 0 | AK25: 0 | AL25: 0 | AM25: 0 | AN25: 0 | AO25: -14.591351 | AP25: -9.0494042 | AQ25: -15.489862 | AR25: -8.7015942 | AS25: -13.151791 | AT25: -12.820625 | AU25: -11.902846 | AV25: -24.81448 | AW25: -13.321954 | AX25: -11.766863 | AY25: -17.062579 | AZ25: -18.817166 | BA25: -24.285847 | BB25: -22.821473 | BC25: -15.849299 | BD25: -14.718377 | BE25: -17.291932 | BF25: -15.50138 | BG25: -15.238871 | BH25: -22.62918 | BI25: -16.156487 | BJ25: 0 | BK25: -13.620137 | BL25: -9.7040147 | BM25: -28.479104 | BN25: -1.7498623 | BO25: -16.715193 | BP25: -17.043109 | BQ25: -20 | BR25: -20 | BS25: -20 | BT25: -20 | BU25: -20 | BV25: -20 | BW25: -20 | BX25: -20 | BY25: -20 | BZ25: -20
B26: Impairement loss | C26: 1.567615 | D26: -0.39454544 | E26: -0.75063602 | F26: -2.4282996 | G26: -2.3239709 | H26: -1.8906766 | I26: -0.27153873 | J26: 0.13126878 | K26: -20.2895 | L26: -66.017827 | M26: 141.65827 | N26: -65.371898 | O26: -82.716344 | P26: =SUMIF($W$3:$BR$3,P$4,$W26:$BR26) -> -339.97956 | Q26: =SUMIF($W$3:$BR$3,Q$4,$W26:$BR26) -> -149.12989 | R26: =SUMIF($W$3:$BR$3,R$4,$W26:$BR26) -> -78.580366 | S26: =SUMIF($W$3:$BR$3,S$4,$W26:$BR26) -> -136.97261 | T26: =SUMIF($W$3:$BZ$3,T$4,$W26:$BZ26) -> -80 | U26: =SUMIF($W$3:$BZ$3,U$4,$W26:$BZ26) -> -80 | W26: 0 | X26: -0.71721864 | Y26: -0.29604331 | Z26: -1.173458 | AA26: 0 | AB26: 0.93464079 | AC26: 0 | AD26: -1.2061795 | AE26: 0 | AF26: 0.47531946 | AG26: 0.44487624 | AH26: -0.78892692 | AI26: 0 | AJ26: -0.78888753 | AK26: -8.8288289 | AL26: -10.671783 | AM26: 0.92495291 | AN26: -2.2734669 | AO26: -20.462011 | AP26: -44.207303 | AQ26: 4.5811823 | AR26: -4.0036553 | AS26: 67.451296 | AT26: 23.156069 | AU26: 0 | AV26: -28.980091 | AW26: -4.0616549 | AX26: -32.093174 | AY26: -0.75715221 | AZ26: -1.5925966 | BA26: -3.0793512 | BB26: -77.287244 | BC26: -2.0350264 | BD26: -23.482999 | BE26: -31.275359 | BF26: -283.18618 | BG26: -3.9609047 | BH26: -28.576053 | BI26: -0.94620838 | BJ26: -115.64672 | BK26: -1.770597 | BL26: -2.6848395 | BM26: -13.653038 | BN26: -60.471892 | BO26: -26.711331 | BP26: -25.261281 | BQ26: -35 | BR26: -50 | BS26: -10 | BT26: -10 | BU26: -10 | BV26: -50 | BW26: -10 | BX26: -10 | BY26: -10 | BZ26: -50
B27: Profit/(loss) on disposal of assets (pre-tax) | C27: 0 | D27: 0 | E27: 0 | F27: 0 | G27: 0 | H27: 0 | I27: 0 | J27: 0 | K27: =SUMIF($W$3:$BB$3,K$4,$W27:$BB27) -> -1.7673325 | L27: =SUMIF($W$3:$BB$3,L$4,$W27:$BB27) -> -0.00245777 | M27: =SUMIF($W$3:$BB$3,M$4,$W27:$BB27) -> -0.13168538 | N27: =SUMIF($W$3:$BB$3,N$4,$W27:$BB27) -> -4.2560443 | O27: =SUMIF($W$3:$BB$3,O$4,$W27:$BB27) -> 2.5290906 | P27: =SUMIF($W$3:$BR$3,P$4,$W27:$BR27) -> 0.19344325 | Q27: =SUMIF($W$3:$BR$3,Q$4,$W27:$BR27) -> -5.7458165 | R27: =SUMIF($W$3:$BR$3,R$4,$W27:$BR27) -> -8.8821038 | S27: =SUMIF($W$3:$BR$3,S$4,$W27:$BR27) -> -6.3379681 | T27: =SUMIF($W$3:$BZ$3,T$4,$W27:$BZ27) -> 0 | U27: =SUMIF($W$3:$BZ$3,U$4,$W27:$BZ27) -> 0 | W27: 0 | X27: 0 | Y27: 0 | Z27: 0 | AA27: 0 | AB27: 0 | AC27: 0 | AD27: 0 | AE27: 0 | AF27: 0 | AG27: 0 | AH27: =J27-SUM(AE27:AG27) -> 0 | AI27: 0 | AJ27: 0 | AK27: 0 | AL27: -1.7673325 | AM27: 0 | AN27: -0.00245777 | AO27: 0 | AP27: 0 | AQ27: -0.01598569 | AR27: 0 | AS27: 0.01010615 | AT27: -0.12580584 | AU27: -0.01577185 | AV27: 0.0095409 | AW27: 0.0644887 | AX27: -4.314302 | AY27: 3.2194994 | AZ27: -0.66556457 | BA27: 0.09718759 | BB27: -0.12203179 | BC27: -0.01735809 | BD27: 0.02454729 | BE27: -0.06699709 | BF27: 0.25325114 | BG27: 0 | BH27: 0.87451131 | BI27: -0.51025372 | BJ27: -6.1100741 | BK27: -0.09378976 | BL27: -6.6950293 | BM27: 0.94546299 | BN27: -3.0387477 | BO27: -3.1270358 | BP27: -3.2109323 | BQ27: 0 | BR27: 0 | BS27: 0 | BT27: 0 | BU27: 0 | BV27: 0 | BW27: 0 | BX27: 0 | BY27: 0 | BZ27: 0
B28: Foreign exchange gain/(loss) | C28: -0.4794046 | D28: -1.5433853 | E28: -3.0584846 | F28: -3.9351954 | G28: -10.060272 | H28: -7.4208825 | I28: -3.9263415 | J28: -4.9062542 | K28: -40.959178 | L28: -34.708512 | M28: 14.954346 | N28: -11.935535 | O28: -16.547993 | P28: =SUMIF($W$3:$BR$3,P$4,$W28:$BR28) -> 47.990243 | Q28: =SUMIF($W$3:$BR$3,Q$4,$W28:$BR28) -> 32.967905 | R28: =SUMIF($W$3:$BR$3,R$4,$W28:$BR28) -> 89.953837 | S28: =SUMIF($W$3:$BR$3,S$4,$W28:$BR28) -> -37.4441 | T28: =SUMIF($W$3:$BZ$3,T$4,$W28:$BZ28) -> 0 | U28: =SUMIF($W$3:$BZ$3,U$4,$W28:$BZ28) -> 0 | W28: -2.5313556 | X28: -5.3889413 | Y28: -6.3544988 | Z28: 4.6591015 | AA28: -1.3591176 | AB28: -3.2503101 | AC28: -1.2995528 | AD28: 1.933039 | AE28: 0.26398918 | AF28: -0.28985981 | AG28: -2.1083951 | AH28: -2.7719885 | AI28: 0.24498405 | AJ28: 0.57927363 | AK28: -22.439101 | AL28: -19.344335 | AM28: -34.788586 | AN28: -19.557479 | AO28: -1.5252973 | AP28: -5.5609415 | AQ28: -1.3150042 | AR28: 5.0708227 | AS28: 16.497568 | AT28: -5.2990407 | AU28: 6.5781706 | AV28: -6.0780315 | AW28: 8.6274449 | AX28: -21.063119 | AY28: -2.6280031 | AZ28: -5.2522157 | BA28: 2.1433355 | BB28: -10.81111 | BC28: -10.024343 | BD28: 46.17252 | BE28: 25.956611 | BF28: -14.114546 | BG28: -16.36203 | BH28: 64.931908 | BI28: -8.4609244 | BJ28: -7.1410489 | BK28: 14.462298 | BL28: 32.517495 | BM28: -82.418831 | BN28: 125.39287 | BO28: -7.6687683 | BP28: -29.775332 | BQ28: 0 | BR28: 0 | BS28: 0 | BT28: 0 | BU28: 0 | BV28: 0 | BW28: 0 | BX28: 0 | BY28: 0 | BZ28: 0
B29: Income (loss) from associates | C29: 0 | D29: 0 | E29: 0 | F29: 0 | G29: 0 | H29: =SUMIF($W$3:$BB$3,H$4,$W29:$BB29) -> 0 | I29: =SUMIF($W$3:$BB$3,I$4,$W29:$BB29) -> 0 | J29: =SUMIF($W$3:$BB$3,J$4,$W29:$BB29) -> 0 | K29: =SUMIF($W$3:$BB$3,K$4,$W29:$BB29) -> 0 | L29: =SUMIF($W$3:$BB$3,L$4,$W29:$BB29) -> 5.0666752 | M29: =SUMIF($W$3:$BB$3,M$4,$W29:$BB29) -> 53.448619 | N29: =SUMIF($W$3:$BB$3,N$4,$W29:$BB29) -> 209.35382 | O29: =SUMIF($W$3:$BB$3,O$4,$W29:$BB29) -> 62.776311 | P29: =SUMIF($W$3:$BR$3,P$4,$W29:$BR29) -> 72.518985 | Q29: =SUMIF($W$3:$BR$3,Q$4,$W29:$BR29) -> 294.23791 | R29: =SUMIF($W$3:$BR$3,R$4,$W29:$BR29) -> -45.685118 | S29: =SUMIF($W$3:$BR$3,S$4,$W29:$BR29) -> 58.68665 | T29: =SUMIF($W$3:$BZ$3,T$4,$W29:$BZ29) -> 0 | U29: =SUMIF($W$3:$BZ$3,U$4,$W29:$BZ29) -> 0 | W29: 0 | X29: 0 | Y29: 0 | Z29: 0 | AA29: 0 | AB29: 0 | AC29: 0 | AD29: 0 | AE29: 0 | AF29: 0 | AG29: 0 | AH29: 0 | AI29: 0 | AJ29: 0 | AK29: 0 | AL29: 0 | AM29: 0 | AN29: 0 | AO29: 0 | AP29: 5.0666752 | AQ29: 1.6457945 | AR29: 0 | AS29: 0.87104401 | AT29: 50.931781 | AU29: 0 | AV29: 0 | AW29: 0 | AX29: 209.35382 | AY29: 0 | AZ29: 30.700322 | BA29: 0 | BB29: 32.07599 | BC29: 0 | BD29: 0.04120373 | BE29: 0.79594674 | BF29: 71.681835 | BG29: 0 | BH29: 1.71 | BI29: 4.3881 | BJ29: 288.13981 | BK29: 0 | BL29: 1.0332576 | BM29: 0 | BN29: -46.718376 | BO29: 19.141743 | BP29: 39.544907 | BQ29: 0 | BR29: 0 | BS29: 0 | BT29: 0 | BU29: 0 | BV29: 0 | BW29: 0 | BX29: 0 | BY29: 0 | BZ29: 0
B30: Share of results in jointly controlled entities | C30: 0 | D30: 0 | E30: 0 | F30: 0 | G30: 0 | H30: 0 | I30: 0 | J30: 0 | K30: 0 | L30: 0 | M30: 0 | N30: 0 | O30: 0 | P30: =SUMIF($W$3:$BR$3,P$4,$W30:$BR30) -> 0 | Q30: =SUMIF($W$3:$BR$3,Q$4,$W30:$BR30) -> 2 | R30: =SUMIF($W$3:$BR$3,R$4,$W30:$BR30) -> 9 | S30: =SUMIF($W$3:$BR$3,S$4,$W30:$BR30) -> 6 | T30: =SUMIF($W$3:$BZ$3,T$4,$W30:$BZ30) -> 0 | U30: =SUMIF($W$3:$BZ$3,U$4,$W30:$BZ30) -> 0 | W30: 0 | X30: 0 | Y30: 0 | Z30: 0 | AA30: 0 | AB30: 0 | AC30: 0 | AD30: 0 | AE30: 0 | AF30: 0 | AG30: 0 | AH30: 0 | AI30: 0 | AJ30: 0 | AK30: 0 | AL30: 0 | AM30: 0 | AN30: 0 | AO30: 0 | AP30: 0 | AQ30: 0 | AR30: 0 | AS30: 0 | AT30: 0 | AU30: 0 | AV30: 0 | AW30: 0 | AX30: 0 | AY30: 0 | AZ30: 0 | BA30: 0 | BB30: 0 | BC30: 0 | BD30: 0 | BE30: 0 | BF30: 0 | BG30: 0 | BH30: 0 | BI30: 1 | BJ30: 1 | BK30: 1 | BL30: 2 | BM30: 3 | BN30: 3 | BO30: 3 | BP30: 3 | BQ30: 0 | BR30: 0 | BS30: 0 | BT30: 0 | BU30: 0 | BV30: 0 | BW30: 0 | BX30: 0 | BY30: 0 | BZ30: 0
B31: Other non-operating income/expense | C31: =+C32-C23-C26-C27-C29-C30-C28 -> 0.26656564 | D31: =+D32-D23-D26-D27-D29-D30-D28 -> 0.2254469 | E31: =+E32-E23-E26-E27-E29-E30-E28 -> 1.5631601 | F31: =+F32-F23-F26-F27-F29-F30-F28 -> 2.3436417 | G31: =+G32-G23-G26-G27-G29-G30-G28 -> 14.355195 | H31: =+H32-H23-H26-H27-H29-H30-H28 -> 6.3347259 | I31: =+I32-I23-I26-I27-I29-I30-I28 -> 7.31333 | J31: =+J32-J23-J26-J27-J29-J30-J28 -> 16.715341 | ... O31: =+O32-O23-O26-O27-O29-O30-O28 -> 162.44787 | P31: =SUMIF($W$3:$BR$3,P$4,$W31:$BR31) -> 197.96603 | Q31: =SUMIF($W$3:$BR$3,Q$4,$W31:$BR31) -> 79.857533 | R31: =SUMIF($W$3:$BR$3,R$4,$W31:$BR31) -> 135.30049 | S31: =SUMIF($W$3:$BR$3,S$4,$W31:$BR31) -> 71.593122 | T31: =SUMIF($W$3:$BZ$3,T$4,$W31:$BZ31) -> 63 | U31: =SUMIF($W$3:$BZ$3,U$4,$W31:$BZ31) -> 116.15217 | W31: =+W32-W23-W26-W27-W29-W30-W28 -> 3.1096156 | X31: =+X32-X23-X26-X27-X29-X30-X28 -> 0.12677372 | Y31: =+Y32-Y23-Y26-Y27-Y29-Y30-Y28 -> 12.816932 | Z31: =+Z32-Z23-Z26-Z27-Z29-Z30-Z28 -> -7.2277408 | AA31: =+AA32-AA23-AA26-AA27-AA29-AA30-AA28 -> -0.11691668 | AB31: =+AB32-AB23-AB26-AB27-AB29-AB30-AB28 -> -1.2252309 | AC31: =+AC32-AC23-AC26-AC27-AC29-AC30-AC28 -> 2.0992708 | AD31: =+AD32-AD23-AD26-AD27-AD29-AD30-AD28 -> 6.6058068 | ... BP31: =+BP32-BP23-BP26-BP27-BP29-BP30-BP28 -> 11.440948 | BQ31: 11 | BR31: 19 | BS31: 15 | BT31: 15 | BU31: 15 | BV31: 18 | BW31: 30.152174 | BX31: 30 | BY31: 30 | BZ31: 26
B32: Other income (loss) | C32: =+C33-C20 -> 1.786176 | D32: =+D33-D20 -> -0.90728387 | E32: =+E33-E20 -> -1.3402781 | F32: =+F33-F20 -> 3.5654155 | G32: =+G33-G20 -> 14.733301 | H32: =+H33-H20 -> 8.7288263 | I32: =+I33-I20 -> 10.020121 | J32: =+J33-J20 -> 17.953013 | ... O32: =+O33-O20 -> 61.223817 | P32: =SUM(P24:P31) -> -47.100259 | Q32: =SUM(Q24:Q31) -> 304.78992 | R32: =SUM(R24:R31) -> 155.58405 | S32: =SUM(S24:S31) -> 72.322925 | T32: =SUM(T24:T31) -> 63 | U32: =SUM(U24:U31) -> 116.15217 | W32: =+W33-W20 -> 3.5847033 | X32: =+X33-X20 -> -2.9729429 | Y32: =+Y33-Y20 -> 9.0127767 | Z32: =+Z33-Z20 -> -0.89571079 | AA32: =+AA33-AA20 -> 1.3943604 | AB32: =+AB33-AB20 -> -0.67050549 | AC32: =+AC33-AC20 -> 1.3816588 | AD32: =+AD33-AD20 -> 7.914607 | ... BP32: =+BP33-BP20 -> 47.57361 | BQ32: =SUM(BQ24:BQ31) -> -4 | BR32: =SUM(BR24:BR31) -> -11 | BS32: =SUM(BS24:BS31) -> 25 | BT32: =SUM(BT24:BT31) -> 25 | BU32: =SUM(BU24:BU31) -> 25 | BV32: =SUM(BV24:BV31) -> -12 | BW32: =SUM(BW24:BW31) -> 40.152174 | BX32: =SUM(BX24:BX31) -> 40 | ... BZ32: =SUM(BZ24:BZ31) -> -4
B33: Pre-tax profit | C33: 35.43181 | D33: 48.936161 | E33: 59.698687 | F33: 33.64074 | G33: 16.212143 | H33: =SUM(W33:Z33) -> 6.3632598 | I33: =SUM(AA33:AD33) -> 6.3232475 | J33: 10.910862 | K33: =SUM(AI33:AL33) -> 205.89282 | L33: 694.95248 | M33: 576.67677 | N33: 986.95919 | O33: 959.91532 | P33: =P20+P32 -> 1351.5513 | Q33: =Q20+Q32 -> 2492.4634 | R33: =R20+R32 -> 6052.4374 | S33: =S20+S32 -> 12012.138 | T33: =T20+T32 -> 19795.913 | U33: =U20+U32 -> 24479.343 | W33: 5.4551796 | X33: -8.5315994 | Y33: 4.7206139 | Z33: 4.7190657 | AA33: -3.8332601 | AB33: -1.2716021 | AC33: -0.26528028 | AD33: 11.69339 | AE33: -6.4971679 | AF33: 12.787396 | AG33: -1.6313039 | AH33: 6.251937 | AI33: -4.3815274 | AJ33: 8.7629566 | AK33: 144.81164 | AL33: 56.699752 | AM33: 168.59379 | AN33: 198.18916 | AO33: 183.29088 | AP33: 144.87865 | AQ33: 117.04086 | AR33: 115.13951 | AS33: 156.96568 | AT33: 187.53072 | AU33: 171.22008 | AV33: 257.76848 | AW33: 268.8283 | AX33: 289.14233 | AY33: 147.2281 | AZ33: 222.75426 | BA33: 242.13319 | BB33: 347.79977 | BC33: 233.26123 | BD33: 290.03491 | BE33: 409.13812 | BF33: 419.11702 | BG33: 270.0942 | BH33: 444.20014 | BI33: 754.71227 | BJ33: 1023.4567 | BK33: 1175.334 | BL33: 1554.1839 | BM33: 1683.1363 | BN33: 1639.7832 | BO33: 1989.783 | BP33: 2891.3555 | BQ33: =BQ20+BQ32 -> 3422.299 | BR33: =BR20+BR32 -> 3708.7006 | BS33: =BS20+BS32 -> 4195.2299 | BT33: =BT20+BT32 -> 4734.6658 | BU33: =BU20+BU32 -> 5346.1672 | BV33: =BV20+BV32 -> 5519.8503 | BW33: =BW20+BW32 -> 5298.9007 | BX33: =BX20+BX32 -> 6071.9694 | ... BZ33: =BZ20+BZ32 -> 6518.4927
B34: Check | C34: =+C12-C15+C32-C33 -> 0 | D34: =+D12-D15+D32-D33 -> 0 | E34: =+E12-E15+E32-E33 -> 0 | F34: =+F12-F15+F32-F33 -> 0 | G34: =+G12-G15+G32-G33 -> 0 | H34: =+H12-H15+H32-H33 -> 0 | I34: =+I12-I15+I32-I33 -> 0 | J34: =+J12-J15+J32-J33 -> 0 | ... U34: =+U12-U15+U32-U33 -> 0 | W34: =+W12-W15+W32-W33 -> 0 | X34: =+X12-X15+X32-X33 -> 0 | Y34: =+Y12-Y15+Y32-Y33 -> 0 | Z34: =+Z12-Z15+Z32-Z33 -> 0 | AA34: =+AA12-AA15+AA32-AA33 -> 0 | AB34: =+AB12-AB15+AB32-AB33 -> 0 | AC34: =+AC12-AC15+AC32-AC33 -> 0 | AD34: =+AD12-AD15+AD32-AD33 -> 0 | ... BR34: =+BR12-BR15+BR32-BR33 -> 0
B36: Income taxes | C36: 4.1602532 | D36: 7.0203088 | E36: 8.4882779 | F36: 4.8648626 | G36: 1.9712163 | H36: 0.50694349 | I36: 0.77887854 | J36: 0.85673003 | K36: 44.387407 | L36: 71.836498 | M36: 63.189572 | N36: 110.53494 | O36: 73.41867 | P36: =SUMIF($W$3:$BR$3,P$4,$W36:$BR36) -> 117.86204 | Q36: =SUMIF($W$3:$BR$3,Q$4,$W36:$BR36) -> 284.8132 | R36: =SUMIF($W$3:$BR$3,R$4,$W36:$BR36) -> 680.66223 | S36: =SUMIF($W$3:$BR$3,S$4,$W36:$BR36) -> 1494.401 | T36: =SUMIF($W$3:$BZ$3,T$4,$W36:$BZ36) -> 2375.5096 | U36: =SUMIF($W$3:$BZ$3,U$4,$W36:$BZ36) -> 2937.5211 | W36: 0.81827694 | X36: -0.90110974 | Y36: 0.70809209 | Z36: -0.01565628 | AA36: 0 | AB36: 0 | AC36: 0 | AD36: 0.77887854 | AE36: 0 | AF36: 0.96845216 | AG36: -0.45922029 | AH36: 0.34749816 | AI36: 0 | AJ36: 0.41265871 | AK36: 22.476526 | AL36: 21.498222 | AM36: 20.827133 | AN36: 29.051968 | AO36: 18.721022 | AP36: 3.2363751 | AQ36: 17.540925 | AR36: 7.3253887 | AS36: 6.3952057 | AT36: 31.928052 | AU36: 17.558211 | AV36: 45.283206 | AW36: 30.688738 | AX36: 17.004789 | AY36: 12.251967 | AZ36: 12.460759 | BA36: 21.706855 | BB36: 26.999089 | BC36: 17.961131 | BD36: 15.689839 | BE36: 47.86208 | BF36: 36.348992 | BG36: 25.505658 | BH36: 41.668273 | BI36: 89.529402 | BJ36: 128.10986 | BK36: 147.63652 | BL36: 174.95993 | BM36: 218.4883 | BN36: 139.57748 | BO36: 299.26768 | BP36: 339.41335 | BQ36: =+BQ89*BQ33 -> 410.67588 | BR36: =+BR89*BR33 -> 445.04408 | BS36: =+BS89*BS33 -> 503.42758 | BT36: =+BT89*BT33 -> 568.15989 | BU36: =+BU89*BU33 -> 641.54006 | BV36: =+BV89*BV33 -> 662.38204 | BW36: =+BW89*BW33 -> 635.86808 | BX36: =+BX89*BX33 -> 728.63633 | ... BZ36: =+BZ89*BZ33 -> 782.21912
B37: Minority interest | C37: =+C33-C36-C40 -> 0 | D37: =+D33-D36-D40 -> 0 | E37: =+E33-E36-E40 -> 0 | F37: =+F33-F36-F40 -> 0 | G37: =+G33-G36-G40 -> 0 | H37: =+H33-H36-H40 -> 0.10265952 | I37: =+I33-I36-I40 -> 0 | J37: =+J33-J36-J40 -> 0 | ... O37: =+O33-O36-O40 -> 9.5195194 | P37: =SUMIF($W$3:$BR$3,P$4,$W37:$BR37) -> 9.6983767 | Q37: =SUMIF($W$3:$BR$3,Q$4,$W37:$BR37) -> 34.122409 | R37: =SUMIF($W$3:$BR$3,R$4,$W37:$BR37) -> 200.28917 | S37: =SUMIF($W$3:$BR$3,S$4,$W37:$BR37) -> 623.85889 | T37: =SUMIF($W$3:$BZ$3,T$4,$W37:$BZ37) -> 889.90631 | U37: =SUMIF($W$3:$BZ$3,U$4,$W37:$BZ37) -> 1052.587 | W37: =+W33-W36-W40 -> 0 | X37: =+X33-X36-X40 -> 0 | Y37: =+Y33-Y36-Y40 -> 0 | Z37: =+Z33-Z36-Z40 -> 0 | AA37: =+AA33-AA36-AA40 -> 0 | AB37: =+AB33-AB36-AB40 -> 0 | AC37: =+AC33-AC36-AC40 -> 0 | AD37: =+AD33-AD36-AD40 -> 0 | ... AN37: =+AN33-AN36-AN40 -> 0 | AO37: =+AO33-AO36-AO40-AO38-AO39 -> 0 | AP37: =+AP33-AP36-AP40-AP38-AP39 -> -2.8421709e-14 | AQ37: =+AQ33-AQ36-AQ40-AQ38-AQ39 -> -1.4210855e-14 | AR37: =+AR33-AR36-AR40-AR38-AR39 -> -1.4210855e-14 | AS37: =+AS33-AS36-AS40-AS38-AS39 -> 0 | AT37: =+AT33-AT36-AT40-AT38-AT39 -> -2.8421709e-14 | AU37: =+AU33-AU36-AU40-AU38-AU39 -> -2.8421709e-14 | AV37: =+AV33-AV36-AV40-AV38-AV39 -> 1.006929 | ... BP37: =+BP33-BP36-BP40-BP38-BP39 -> 139.70288 | BQ37: =+(BQ33-BQ36)*0.06 -> 180.69739 | BR37: =+(BR33-BR36)*0.06 -> 195.81939 | BS37: =+Assumption!R379 -> 188.70838 | BT37: =+Assumption!S379 -> 211.60842 | BU37: =+Assumption!T379 -> 234.32999 | BV37: =+Assumption!U379 -> 255.25953 | BW37: =+Assumption!V379 -> 236.56778 | BX37: =+Assumption!W379 -> 268.43237 | BY37: =+Assumption!X379 -> 274.58679 | BZ37: =+Assumption!Y379 -> 273.0001
B38: Preferred dividends | C38: 0 | D38: 0 | E38: 0 | F38: 0 | G38: 0 | H38: 0 | I38: 0 | J38: 0 | K38: =+K12/J12-1 -> 14.702158 | L38: =+L12/K12-1 -> 1.2267283 | M38: =+M12/L12-1 -> -0.082798449 | N38: 0 | O38: 0 | P38: =SUMIF($W$3:$BR$3,P$4,$W38:$BR38) -> 0 | Q38: =SUMIF($W$3:$BR$3,Q$4,$W38:$BR38) -> 0 | R38: =SUMIF($W$3:$BR$3,R$4,$W38:$BR38) -> 0 | S38: =SUMIF($W$3:$BR$3,S$4,$W38:$BR38) -> 0 | T38: =SUMIF($W$3:$BZ$3,T$4,$W38:$BZ38) -> 0 | U38: =SUMIF($W$3:$BZ$3,U$4,$W38:$BZ38) -> 0 | AI38: 0 | AJ38: 0 | AK38: 0 | AL38: 0 | AM38: 0 | AN38: 0 | AO38: 0 | AP38: 0 | AQ38: 0 | AR38: 0 | AS38: 0 | AT38: 0 | AU38: 0 | AV38: 0 | AW38: 0 | AX38: 0 | AY38: 0 | AZ38: 0 | BA38: 0 | BB38: 0 | BC38: 0 | BD38: 0 | BE38: 0 | BF38: 0 | BG38: 0 | BH38: 0 | BI38: 0 | BJ38: 0 | BK38: 0 | BL38: 0 | BM38: 0 | BN38: 0 | BO38: 0 | BP38: 0 | BQ38: 0 | BR38: 0 | BS38: 0 | BT38: 0 | BU38: 0 | BV38: 0 | BW38: 0 | BX38: 0 | BY38: 0 | BZ38: 0
B39: Extraordinary gain/(loss) | C39: 0 | D39: 0 | E39: 0 | F39: 0 | G39: 0 | H39: 0 | I39: 0 | J39: 0 | K39: 0 | L39: 0 | M39: 0 | N39: 0 | O39: 0 | P39: =SUMIF($W$3:$BR$3,P$4,$W39:$BR39) -> 0 | Q39: =SUMIF($W$3:$BR$3,Q$4,$W39:$BR39) -> 0 | R39: =SUMIF($W$3:$BR$3,R$4,$W39:$BR39) -> 0 | S39: =SUMIF($W$3:$BR$3,S$4,$W39:$BR39) -> 0 | T39: =SUMIF($W$3:$BZ$3,T$4,$W39:$BZ39) -> 0 | U39: =SUMIF($W$3:$BZ$3,U$4,$W39:$BZ39) -> 0 | AI39: 0 | AJ39: 0 | AK39: 0 | AL39: 0 | AM39: 0 | AN39: 0 | AO39: 0 | AP39: 0 | AQ39: 0 | AR39: 0 | AS39: 0 | AT39: 0 | AU39: 0 | AV39: 0 | AW39: 0 | AX39: 0 | AY39: 0 | AZ39: 0 | BA39: 0 | BB39: 0 | BC39: 0 | BD39: 0 | BE39: 0 | BF39: 0 | BG39: 0 | BH39: 0 | BI39: 0 | BJ39: 0 | BK39: 0 | BL39: 0 | BM39: 0 | BN39: 0 | BO39: 0 | BP39: 0 | BQ39: 0 | BR39: 0 | BS39: 0 | BT39: 0 | BU39: 0 | BV39: 0 | BW39: 0 | BX39: 0 | BY39: 0 | BZ39: 0
B40: Net income | C40: 31.271556 | D40: 41.915852 | E40: 51.210409 | F40: 28.775878 | G40: 14.240927 | H40: =SUM(W40:Z40) -> 5.7536568 | I40: =SUM(AA40:AD40) -> 5.544369 | J40: 10.054132 | K40: =SUM(AI40:AL40) -> 161.50542 | L40: 623.11598 | M40: 513.4872 | N40: 865.48355 | O40: 876.97713 | P40: =+P33-P36-P37-P38+P39 -> 1223.9909 | Q40: =+Q33-Q36-Q37-Q38+Q39 -> 2173.5277 | R40: =+R33-R36-R37-R38+R39 -> 5171.486 | S40: =+S33-S36-S37-S38+S39 -> 9893.8783 | T40: =+T33-T36-T37-T38+T39 -> 16530.497 | U40: =+U33-U36-U37-U38+U39 -> 20489.235 | W40: 4.6369027 | X40: -7.6304896 | Y40: 4.0125218 | Z40: 4.7347219 | AA40: -3.8332601 | AB40: -1.2716021 | AC40: -0.26528028 | AD40: 10.914511 | AE40: -6.4971679 | AF40: 11.818944 | AG40: -1.1720836 | AH40: 5.9044388 | AI40: -4.3815274 | AJ40: 8.3502979 | AK40: 122.33512 | AL40: 35.20153 | AM40: 147.76666 | AN40: 169.13719 | AO40: 164.56986 | AP40: 141.64227 | AQ40: 99.499939 | AR40: 107.81412 | AS40: 150.57048 | AT40: 155.60266 | AU40: 153.66187 | AV40: 211.47835 | AW40: 234.73558 | AX40: 265.60775 | AY40: 133.0697 | AZ40: 207.75126 | BA40: 219.2824 | BB40: 316.87377 | BC40: 217.4126 | BD40: 275.04257 | BE40: 360.05326 | BF40: 371.48243 | BG40: 249.92027 | BH40: 363.83251 | BI40: 682.1151 | BJ40: 877.65987 | BK40: 1009.2663 | BL40: 1349.1548 | BM40: 1394.2381 | BN40: 1418.8268 | BO40: 1582.8761 | BP40: 2412.2393 | BQ40: =+BQ33-BQ36-BQ37-BQ38+BQ39 -> 2830.9257 | BR40: =+BR33-BR36-BR37-BR38+BR39 -> 3067.8372 | BS40: =+BS33-BS36-BS37-BS38+BS39 -> 3503.0939 | BT40: =+BT33-BT36-BT37-BT38+BT39 -> 3954.8974 | BU40: =+BU33-BU36-BU37-BU38+BU39 -> 4470.2972 | BV40: =+BV33-BV36-BV37-BV38+BV39 -> 4602.2087 | BW40: =+BW33-BW36-BW37-BW38+BW39 -> 4426.4648 | BX40: =+BX33-BX36-BX37-BX38+BX39 -> 5074.9007 | ... BZ40: =+BZ33-BZ36-BZ37-BZ38+BZ39 -> 5463.2734
B41: Check | C41: =+C33-C36-C37-C40 -> 0 | D41: =+D33-D36-D37-D40 -> 0 | E41: =+E33-E36-E37-E40 -> 0 | F41: =+F33-F36-F37-F40 -> 0 | G41: =+G33-G36-G37-G40 -> 0 | H41: =+H33-H36-H37-H40 -> 0 | I41: =+I33-I36-I37-I40 -> 0 | J41: =+J33-J36-J37-J40 -> 0 | ... U41: =+U33-U36-U37-U40 -> 0 | AI41: =+AI33-AI36-AI37-AI40 -> 0 | AJ41: =+AJ33-AJ36-AJ37-AJ40 -> 0 | AK41: =+AK33-AK36-AK37-AK40 -> 0 | AL41: =+AL33-AL36-AL37-AL40 -> 0 | AM41: =+AM33-AM36-AM37-AM40 -> 0 | AN41: =+AN33-AN36-AN37-AN40 -> 0 | AO41: =+AO33-AO36-AO37-AO40 -> 0 | AP41: =+AP33-AP36-AP37-AP40 -> 0 | ... BZ41: =+BZ33-BZ36-BZ37-BZ40 -> 0
B43: Minority as % of net profit | BC43: =+BC37/(BC33-BC36) -> -0.0098118981 | BD43: =+BD37/(BD33-BD36) -> -0.0025424227 | BE43: =+BE37/(BE33-BE36) -> 0.0033846103 | BF43: =+BF37/(BF33-BF36) -> 0.029484181 | BG43: =+BG37/(BG33-BG36) -> -0.021798785 | BH43: =+BH37/(BH33-BH36) -> 0.096139869 | BI43: =+BI37/(BI33-BI36) -> -0.02545501 | BJ43: =+BJ37/(BJ33-BJ36) -> 0.019754373 | ... BZ43: =+BZ37/(BZ33-BZ36) -> 0.047591891
B45: EBIT | C45: =+C20 -> 33.645634 | D45: =+D20 -> 49.843444 | E45: =+E20 -> 61.038965 | F45: =+F20 -> 30.075325 | G45: =+G20 -> 1.4788426 | H45: =+H20 -> -2.3655665 | I45: =+I20 -> -3.6968731 | J45: =+J20 -> -7.0421513 | ... U45: =+U20 -> 24363.191 | W45: =+W20 -> 1.8704763 | X45: =+X20 -> -5.5586565 | Y45: =+Y20 -> -4.2921627 | Z45: =+Z20 -> 5.6147765 | AA45: =+AA20 -> -5.2276204 | AB45: =+AB20 -> -0.60109657 | AC45: =+AC20 -> -1.6469391 | AD45: =+AD20 -> 3.7787829 | ... BZ45: =+BZ20 -> 6522.4927
B46: Depreciation | C46: 1.9408838 | D46: 3.9522376 | E46: 6.3353015 | F46: 8.994307 | G46: 11.870318 | H46: 12.538386 | I46: 15.11947 | J46: 18.808306 | K46: 60.37121 | L46: 130.24076 | M46: 172.48206 | N46: 250.66216 | O46: 320.64924 | P46: 361.31217 | Q46: =+Q179 -> 384.59687 | R46: =+R179 -> 545.14848 | S46: =+S179 -> 640.187 | T46: =+T179 -> 893.09919 | U46: =+U179 -> 1080.3578 | W46: 2.9944527 | X46: 2.9944527 | Y46: 3.2747401 | Z46: 3.2747401 | AA46: 3.6350838 | AB46: 3.6350838 | AC46: 3.9246514 | AD46: 3.9246514 | AE46: 2.4186165 | AF46: 2.4186165 | AG46: 6.9855367 | AH46: 6.9855367 | AI46: 4.8081469 | AJ46: 4.8081469 | AK46: 25.377458 | AL46: 25.377458 | AM46: 29.567363 | AN46: 29.567363 | AO46: 35.553018 | AP46: 35.553018 | AQ46: 39.186095 | AR46: 39.186095 | AS46: 47.054933 | AT46: 47.054933 | AU46: 56.4832 | AV46: 56.4832 | AW46: 68.847881 | AX46: 68.847881 | AY46: 77.122581 | AZ46: 77.122581 | BA46: 83.202039 | BB46: 83.202039 | BC46: 87.298491 | BD46: 87.298491 | BE46: 93.357593 | BF46: 93.357593 | BG46: =+$Q$46/4 -> 96.149217 | BH46: =+$Q$46/4 -> 96.149217 | BI46: =+$Q$46/4 -> 96.149217 | BJ46: =+$Q$46/4 -> 96.149217 | BK46: =+$R$46/4 -> 136.28712 | BL46: =+$R$46/4 -> 136.28712 | BM46: =+$R$46/4 -> 136.28712 | BN46: =+$R$46/4 -> 136.28712 | BO46: =+$S$46/4 -> 160.04675 | BP46: =+$S$46/4 -> 160.04675 | BQ46: =+$S$46/4 -> 160.04675 | BR46: =+$S$46/4 -> 160.04675 | BS46: =+$T$46/4 -> 223.2748 | BT46: =+$T$46/4 -> 223.2748 | BU46: =+$T$46/4 -> 223.2748 | BV46: =+$T$46/4 -> 223.2748 | BW46: =+$U$46/4 -> 270.08944 | BX46: =+$U$46/4 -> 270.08944 | BY46: =+$U$46/4 -> 270.08944 | BZ46: =+$U$46/4 -> 270.08944
B47: Amortization | C47: 0.11056381 | D47: 0.29378618 | E47: 0.62512884 | F47: 0.63826525 | G47: 8.4850257 | H47: 12.380054 | I47: 12.263715 | J47: 12.265049 | K47: 40.980841 | L47: 71.075269 | M47: 68.808505 | N47: 80.367939 | O47: 85.874897 | P47: 83.428534 | Q47: =+Q187 -> 85.462292 | R47: =+R187 -> 98.327096 | S47: =+S187 -> 90.655063 | T47: =+T187 -> 76.097848 | U47: =+U187 -> 65.034364 | W47: 3.0969504 | X47: 3.0969504 | Y47: 3.0930767 | Z47: 3.0930767 | AA47: 3.0630875 | AB47: 3.0630875 | AC47: 3.0687698 | AD47: 3.0687698 | AE47: 3.0737646 | AF47: 3.0737646 | AG47: 3.0587601 | AH47: 3.0587601 | AI47: 3.0791833 | AJ47: 3.0791833 | AK47: 17.411237 | AL47: 17.411237 | AM47: 17.721112 | AN47: 17.721112 | AO47: 17.816522 | AP47: 17.816522 | AQ47: 17.575764 | AR47: 17.575764 | AS47: 16.828489 | AT47: 16.828489 | AU47: 18.924339 | AV47: 18.924339 | AW47: 21.25963 | AX47: 21.25963 | AY47: 20.972787 | AZ47: 20.972787 | BA47: 21.964662 | BB47: 21.964662 | BC47: 20.711653 | BD47: 20.711653 | BE47: 21.002614 | BF47: 21.002614 | BG47: =+$Q$47/4 -> 21.365573 | BH47: =+$Q$47/4 -> 21.365573 | BI47: =+$Q$47/4 -> 21.365573 | BJ47: =+$Q$47/4 -> 21.365573 | BK47: =+$R$47/4 -> 24.581774 | BL47: =+$R$47/4 -> 24.581774 | BM47: =+$R$47/4 -> 24.581774 | BN47: =+$R$47/4 -> 24.581774 | BO47: =+$S$47/4 -> 22.663766 | BP47: =+$S$47/4 -> 22.663766 | BQ47: =+$S$47/4 -> 22.663766 | BR47: =+$S$47/4 -> 22.663766 | BS47: =+$T$47/4 -> 19.024462 | BT47: =+$T$47/4 -> 19.024462 | BU47: =+$T$47/4 -> 19.024462 | BV47: =+$T$47/4 -> 19.024462 | BW47: =+$U$47/4 -> 16.258591 | BX47: =+$U$47/4 -> 16.258591 | BY47: =+$U$47/4 -> 16.258591 | BZ47: =+$U$47/4 -> 16.258591
B48: EBITDA | C48: =+C45+C46+C47 -> 35.697081 | D48: =+D45+D46+D47 -> 54.089468 | E48: =+E45+E46+E47 -> 67.999395 | F48: =+F45+F46+F47 -> 39.707897 | G48: =+G45+G46+G47 -> 21.834186 | H48: =+H45+H46+H47 -> 22.552873 | I48: =+I45+I46+I47 -> 23.686312 | J48: =+J45+J46+J47 -> 24.031204 | ... U48: =+U45+U46+U47 -> 25508.583 | W48: =+W45+W46+W47 -> 7.9618795 | X48: =+X45+X46+X47 -> 0.5327467 | Y48: =+Y45+Y46+Y47 -> 2.075654 | Z48: =+Z45+Z46+Z47 -> 11.982593 | AA48: =+AA45+AA46+AA47 -> 1.4705508 | AB48: =+AB45+AB46+AB47 -> 6.0970747 | AC48: =+AC45+AC46+AC47 -> 5.3464822 | AD48: =+AD45+AD46+AD47 -> 10.772204 | ... BZ48: =+BZ45+BZ46+BZ47 -> 6808.8407
B50: EPS - basic | C50: 0.69 | D50: 0.89 | E50: 1.02 | F50: 0.46 | G50: 0.12 | H50: =SUMIF($W$3:$BR$3,H$4,$W50:$BR50) -> 0.0303 | I50: =SUMIF($W$3:$BR$3,I$4,$W50:$BR50) -> 0.0257 | J50: =SUMIF($W$3:$BR$3,J$4,$W50:$BR50) -> 0.0465 | K50: =SUMIF($W$3:$BR$3,K$4,$W50:$BR50) -> 0.3509 | L50: =SUMIF($W$3:$BR$3,L$4,$W50:$BR50) -> 1.3127 | M50: =SUMIF($W$3:$BR$3,M$4,$W50:$BR50) -> 0.8002 | N50: =SUMIF($W$3:$BR$3,N$4,$W50:$BR50) -> 1.2135 | O50: =SUMIF($W$3:$BR$3,O$4,$W50:$BR50) -> 1.1815 | ... S50: =SUMIF($W$3:$BR$3,S$4,$W50:$BR50) -> 8.8246288 | T50: =SUMIF($W$3:$BZ$3,T$4,$W50:$BZ50) -> 14.744016 | U50: =SUMIF($W$3:$BZ$3,U$4,$W50:$BZ50) -> 18.274926 | W50: 0.0386 | X50: -0.0636 | Y50: 0.0334 | Z50: 0.0219 | AA50: -0.0177 | AB50: -0.0059 | AC50: -0.0012 | AD50: 0.0505 | AE50: -0.0301 | AF50: 0.0547 | AG50: -0.0054 | AH50: 0.0273 | AI50: -0.0203 | AJ50: 0.0387 | AK50: 0.2582 | AL50: 0.0743 | AM50: 0.3118 | AN50: 0.3569 | AO50: 0.3461 | AP50: 0.2979 | AQ50: 0.22 | AR50: 0.151 | AS50: 0.211 | AT50: 0.2182 | AU50: 0.2155 | AV50: 0.2965 | AW50: 0.3291 | AX50: 0.3724 | AY50: 0.1866 | AZ50: 0.2914 | BA50: 0.3075 | BB50: 0.396 | BC50: 0.2719 | BD50: 0.3439 | BE50: 0.4495 | BF50: 0.4638 | BG50: 0.312 | BH50: 0.4532 | BI50: =+BI40/BI57 -> 0.60690124 | BJ50: =+BJ40/BJ57 -> 0.78088414 | BK50: =+BK40/BK57 -> 0.89797891 | BL50: =+BL40/BL57 -> 1.2033491 | BM50: =+BM40/BM57 -> 1.2435603 | BN50: =+BN40/BN57 -> 1.2654916 | BO50: =+BO40/BO57 -> 1.4118118 | BP50: =+BP40/BP57 -> 2.1515442 | ... BZ50: =+BZ40/BZ57 -> 4.8728475
B51: EPS - fully diluted | C51: 0.69 | D51: 0.89 | E51: 1.02 | F51: 0.46 | G51: 0.12 | H51: =SUMIF($W$3:$BR$3,H$4,$W51:$BR51) -> 0.0303 | I51: =SUMIF($W$3:$BR$3,I$4,$W51:$BR51) -> 0.0257 | J51: =SUMIF($W$3:$BR$3,J$4,$W51:$BR51) -> 0.0465 | K51: =SUMIF($W$3:$BR$3,K$4,$W51:$BR51) -> 0.3509 | L51: =SUMIF($W$3:$BR$3,L$4,$W51:$BR51) -> 1.3127 | M51: =SUMIF($W$3:$BR$3,M$4,$W51:$BR51) -> 0.8 | N51: =SUMIF($W$3:$BR$3,N$4,$W51:$BR51) -> 1.2135 | O51: =SUMIF($W$3:$BR$3,O$4,$W51:$BR51) -> 1.1815 | ... S51: =SUMIF($W$3:$BR$3,S$4,$W51:$BR51) -> 8.8246288 | T51: =SUMIF($W$3:$BZ$3,T$4,$W51:$BZ51) -> 14.744016 | U51: =SUMIF($W$3:$BZ$3,U$4,$W51:$BZ51) -> 18.274926 | W51: 0.0386 | X51: -0.0636 | Y51: 0.0334 | Z51: 0.0219 | AA51: -0.0177 | AB51: -0.0059 | AC51: -0.0012 | AD51: 0.0505 | AE51: -0.0301 | AF51: 0.0547 | AG51: -0.0054 | AH51: 0.0273 | AI51: -0.0203 | AJ51: 0.0387 | AK51: 0.2582 | AL51: 0.0743 | AM51: 0.3118 | AN51: 0.3569 | AO51: 0.3461 | AP51: 0.2979 | AQ51: 0.22 | AR51: 0.151 | AS51: 0.211 | AT51: 0.218 | AU51: 0.2155 | AV51: 0.2965 | AW51: 0.3291 | AX51: 0.3724 | AY51: 0.1866 | AZ51: 0.2914 | BA51: 0.3075 | BB51: 0.396 | BC51: 0.2719 | BD51: 0.3439 | BE51: 0.4495 | BF51: 0.4638 | BG51: 0.312 | BH51: 0.4532 | BI51: =+BI40/BI58 -> 0.60690124 | BJ51: =+BJ40/BJ58 -> 0.78088414 | BK51: =+BK40/BK58 -> 0.89797891 | BL51: =+BL40/BL58 -> 1.2033491 | BM51: =+BM40/BM58 -> 1.2435603 | BN51: =+BN40/BN58 -> 1.2654916 | BO51: =+BO40/BO58 -> 1.4118118 | BP51: =+BP40/BP58 -> 2.1515442 | ... BZ51: =+BZ40/BZ58 -> 4.8728475
B52: EPS (based on current shares outstanding) | C52: =C40/C60 -> #DIV/0! | D52: =D40/D60 -> #DIV/0! | E52: =E40/E60 -> 1.02 | F52: =F40/F60 -> 0.46 | G52: =G40/G60 -> 0.12 | H52: =H40/H60 -> 0.0303 | I52: =I40/I60 -> 0.0257 | J52: =J40/J60 -> 0.0465 | ... U52: =U40/U60 -> 18.274926
C53: =+C50/1.1 -> 0.62727273
B55: Common dividends declared | C55: 0 | D55: 51.102125 | E55: 0 | F55: 76.8 | G55: 28.16 | H55: 23.232 | I55: 34.660598 | J55: 66.561764 | K55: 94.49367 | L55: 103.93306 | M55: 121.93953 | N55: 135.77 | O55: 149.2535 | P55: 156.89916 | Q55: =+Q64 -> 356.72585 | R55: =+R64 -> 557.131 | S55: =+S64 -> 989.38783 | T55: =+T64 -> 1653.0497 | U55: =+U64 -> 2048.9235
B56: Dividends per share | C56: 0 | D56: 4.8982177 | E56: 0.2 | F56: 0.1 | G56: 0.022 | H56: 0.01 | I56: 0.01 | J56: 0.01 | K56: 0.038 | L56: 0.123 | M56: 0.084 | N56: 0.121 | O56: 0.22 | P56: 0.2 | Q56: =+Q64/Q57 -> 0.35335438 | R56: =+R64/R57 -> 0.4966823 | S56: =+S64/S57 -> 0.88246288 | T56: =+T64/T57 -> 1.4744016 | U56: =+U64/U57 -> 1.8274926
B57: Weighted avg. adj. shares outstanding (mn) | C57: =C40/C50 -> 45.321096 | D57: =D40/D50 -> 47.096463 | E57: =E40/E50 -> 50.206283 | F57: =F40/F50 -> 62.556256 | G57: =G40/G50 -> 118.67439 | H57: =H40/H50 -> 189.88966 | I57: =I40/I50 -> 215.7342 | J57: =J40/J50 -> 216.21788 | ... U57: =U40/U50 -> 1121.1665 | W57: 0.1 | X57: 0.1 | Y57: 0.1 | Z57: 302.67629 | AA57: 303.19571 | AB57: 301.73608 | AC57: 309.49366 | AD57: 302.58051 | AE57: 302.19386 | AF57: 302.49583 | AG57: 303.87352 | AH57: 302.79173 | AI57: 302.1743 | AJ57: 302.07796 | AK57: 663.31976 | AL57: 663.28589 | AM57: 663.48082 | AN57: 663.46895 | AO57: 665.6972 | AP57: 665.65688 | AQ57: 633.18143 | AR57: 999.6011 | AS57: 999.04583 | AT57: 998.36724 | AU57: 998.26735 | AV57: 998.5487 | AW57: 998.5713 | AX57: 998.52539 | AY57: 998.37929 | AZ57: 998.11862 | BA57: 998.35889 | BB57: 1120.2608 | BC57: 1119.447 | BD57: 1119.6848 | BE57: 1121.4117 | BF57: 1121.3355 | BG57: 1121.4371 | BH57: 1123.931 | BI57: 1123.931 | BJ57: 1123.931 | BK57: 1123.931 | BL57: 1121.1665 | BM57: 1121.1665 | BN57: 1121.1665 | BO57: 1121.1665 | BP57: 1121.1665 | BQ57: 1121.1665 | BR57: 1121.1665 | BS57: 1121.1665 | BT57: 1121.1665 | BU57: 1121.1665 | BV57: 1121.1665 | BW57: 1121.1665 | BX57: 1121.1665 | BY57: 1121.1665 | BZ57: 1121.1665 | CO57: =+A7 -> 0
B58: Fully diluted shares outstanding (mn) | C58: =C40/C51 -> 45.321096 | D58: =D40/D51 -> 47.096463 | E58: =E40/E51 -> 50.206283 | F58: =F40/F51 -> 62.556256 | G58: =G40/G51 -> 118.67439 | H58: =H40/H51 -> 189.88966 | I58: =I40/I51 -> 215.7342 | J58: =J40/J51 -> 216.21788 | ... U58: =U40/U51 -> 1121.1665 | W58: 168.17782 | X58: 167.96675 | Y58: 168.18954 | Z58: 302.67629 | AA58: 303.19571 | AB58: 301.73608 | AC58: 309.49366 | AD58: 302.58051 | AE58: 302.19386 | AF58: 302.49583 | AG58: 303.87352 | AH58: 302.79173 | AI58: 302.1743 | AJ58: 302.07796 | AK58: 663.31976 | AL58: 663.28589 | AM58: 663.48082 | AN58: 663.46895 | AO58: 665.6972 | AP58: 665.65688 | AQ58: 633.18143 | AR58: 999.6011 | AS58: 999.04583 | AT58: 999.28317 | AU58: 998.26735 | AV58: 998.5487 | AW58: 998.5713 | AX58: 998.52539 | AY58: 998.37929 | AZ58: 998.11862 | BA58: 998.35889 | BB58: 1120.2608 | BC58: 1119.447 | BD58: 1119.6848 | BE58: 1121.4117 | BF58: 1121.3355 | BG58: 1121.4371 | BH58: 1123.931 | BI58: 1123.931 | BJ58: 1123.931 | BK58: 1123.931 | BL58: 1121.1665 | BM58: 1121.1665 | BN58: 1121.1665 | BO58: 1121.1665 | BP58: 1121.1665 | BQ58: 1121.1665 | BR58: 1121.1665 | BS58: 1121.1665 | BT58: 1121.1665 | BU58: 1121.1665 | BV58: 1121.1665 | BW58: 1121.1665 | BX58: 1121.1665 | BY58: 1121.1665 | BZ58: 1121.1665
B59: Period end shares outstanding (mn) | C59: =+C58 -> 45.321096 | D59: =+D58 -> 47.096463 | E59: =+E58 -> 50.206283 | F59: =+F58 -> 62.556256 | G59: =+G58 -> 118.67439 | H59: =+H58 -> 189.88966 | I59: =+I58 -> 215.7342 | J59: =+J58 -> 216.21788 | ... U59: =+U58 -> 1121.1665 | W59: 168.17782 | X59: 167.96675 | Y59: 168.18954 | Z59: 302.67629 | AA59: 303.19571 | AB59: 301.73608 | AC59: 309.49366 | AD59: 302.58051 | AE59: 302.19386 | AF59: 302.49583 | AG59: 303.87352 | AH59: 302.79173 | AI59: 302.1743 | AJ59: 302.07796 | AK59: 663.31976 | AL59: 663.28589 | AM59: 663.48082 | AN59: 663.46895 | AO59: 665.6972 | AP59: 665.65688 | AQ59: 633.18143 | AR59: 999.6011 | AS59: 999.04583 | AT59: 999.28317 | AU59: 998.26735 | AV59: 998.5487 | AW59: 998.5713 | AX59: 998.52539 | AY59: 998.37929 | AZ59: 998.11862 | BA59: 998.35889 | BB59: 1120.2608 | BC59: 1119.447 | BD59: 1119.6848 | BE59: 1121.4117 | BF59: 1121.3355 | BG59: 1121.4371 | BH59: 1123.931 | BI59: 1123.931 | BJ59: 1123.931 | BK59: 1123.931 | BL59: 1121.1665 | BM59: 1121.1665 | BN59: 1121.1665 | BO59: 1121.1665 | BP59: 1121.1665 | BQ59: 1121.1665 | BR59: 1121.1665 | BS59: 1121.1665 | BT59: 1121.1665 | BU59: 1121.1665 | BV59: 1121.1665 | BW59: 1121.1665 | BX59: 1121.1665 | BY59: 1121.1665 | BZ59: 1121.1665
B60: Current shares outstanding | E60: =+E59 -> 50.206283 | F60: =+F59 -> 62.556256 | G60: =+G59 -> 118.67439 | H60: =+H59 -> 189.88966 | I60: =+I59 -> 215.7342 | J60: =+J59 -> 216.21788 | K60: =+K59 -> 460.26052 | L60: =+L59 -> 474.6827 | ... U60: =+U59 -> 1121.1665
B62: Dividend payout
B63: Net income | C63: =C40 -> 31.271556 | D63: =D40 -> 41.915852 | E63: =E40 -> 51.210409 | F63: =F40 -> 28.775878 | G63: =G40 -> 14.240927 | H63: =H40 -> 5.7536568 | I63: =I40 -> 5.544369 | J63: =J40 -> 10.054132 | ... U63: =U40 -> 20489.235
B64: Dividend declared | C64: =C55 -> 0 | D64: =D55 -> 51.102125 | E64: =E55 -> 0 | F64: =F55 -> 76.8 | G64: =G55 -> 28.16 | H64: =H55 -> 23.232 | I64: =I55 -> 34.660598 | J64: =J55 -> 66.561764 | ... O64: =O55 -> 149.2535 | P64: 157.981 | Q64: 356.72585 | R64: 557.131 | S64: =+S63*S65 -> 989.38783 | T64: =+T63*T65 -> 1653.0497 | U64: =+U63*U65 -> 2048.9235
B65: Payout ratio | C65: =C64/C63 -> 0 | D65: =D64/D63 -> 1.2191599 | E65: =E64/E63 -> 0 | F65: =F64/F63 -> 2.6689021 | G65: =G64/G63 -> 1.9773994 | H65: =H64/H63 -> 4.0377799 | I65: =I64/I63 -> 6.2514955 | J65: =J64/J63 -> 6.6203395 | ... O65: =O64/O63 -> 0.17019088 | P65: =+P64/P63 -> 0.12907041 | Q65: =+Q64/Q63 -> 0.16412298 | R65: =+R64/R63 -> 0.10773132 | S65: 0.1 | T65: 0.1 | U65: 0.1
B67: Growth YoY% | C67: =C4 -> 2009 | D67: =D4 -> 2010 | E67: =E4 -> 2011 | F67: =F4 -> 2012 | G67: =G4 -> 2013 | H67: =H4 -> 2014 | I67: =I4 -> 2015 | J67: =J4 -> 2016 | ... U67: =U4 -> 2027 | W67: =W4 -> 1Q14 | X67: =X4 -> 2Q14 | Y67: =Y4 -> 3Q14 | Z67: =Z4 -> 4Q14 | AA67: =AA4 -> 1Q15 | AB67: =AB4 -> 2Q15 | AC67: =AC4 -> 3Q15 | AD67: =AD4 -> 4Q15 | ... BZ67: =BZ4 -> 4Q27
B68: Revenue | C68: =IF(ISERROR(C7/B7-1)," ",(C7/B7-1)) | D68: =IF(ISERROR(D7/C7-1)," ",(D7/C7-1)) -> 0.36706919 | E68: =IF(ISERROR(E7/D7-1)," ",(E7/D7-1)) -> 0.31188139 | F68: =IF(ISERROR(F7/E7-1)," ",(F7/E7-1)) -> -0.28023061 | G68: =IF(ISERROR(G7/F7-1)," ",(G7/F7-1)) -> -0.22401475 | H68: =IF(ISERROR(H7/G7-1)," ",(H7/G7-1)) -> 0.31173375 | I68: =IF(ISERROR(I7/H7-1)," ",(I7/H7-1)) -> 0.022432131 | J68: =IF(ISERROR(J7/I7-1)," ",(J7/I7-1)) -> 0.084098944 | ... U68: =IF(ISERROR(U7/T7-1)," ",(U7/T7-1)) -> 0.21404138 | Z68: =IF(ISERROR(Z7/#REF!-1),"",Z7/#REF!-1) | AA68: =IF(ISERROR(AA7/W7-1),"",AA7/W7-1) -> -0.49979999 | AB68: =IF(ISERROR(AB7/X7-1),"",AB7/X7-1) -> 0.20500065 | AC68: =IF(ISERROR(AC7/Y7-1),"",AC7/Y7-1) -> 0.19751895 | AD68: =IF(ISERROR(AD7/Z7-1),"",AD7/Z7-1) -> 0.34775876 | AE68: =IF(ISERROR(AE7/AA7-1),"",AE7/AA7-1) -> -0.46189111 | AF68: =IF(ISERROR(AF7/AB7-1),"",AF7/AB7-1) -> 0.9407814 | AG68: =IF(ISERROR(AG7/AC7-1),"",AG7/AC7-1) -> -0.0098386509 | AH68: =IF(ISERROR(AH7/AD7-1),"",AH7/AD7-1) -> -0.06029787 | ... BZ68: =IF(ISERROR(BZ7/BV7-1),"",BZ7/BV7-1) -> 0.16115786
B69: Gross profit | C69: =IF(ISERROR(C12/B12-1)," ",(C12/B12-1)) | D69: =IF(ISERROR(D12/C12-1)," ",(D12/C12-1)) -> 0.39527426 | E69: =IF(ISERROR(E12/D12-1)," ",(E12/D12-1)) -> 0.29608015 | F69: =IF(ISERROR(F12/E12-1)," ",(F12/E12-1)) -> -0.30171329 | G69: =IF(ISERROR(G12/F12-1)," ",(G12/F12-1)) -> -0.35432055 | H69: =IF(ISERROR(H12/G12-1)," ",(H12/G12-1)) -> 0.051078655 | I69: =IF(ISERROR(I12/H12-1)," ",(I12/H12-1)) -> -0.14492248 | J69: =IF(ISERROR(J12/I12-1)," ",(J12/I12-1)) -> 0.22033187 | ... U69: =IF(ISERROR(U12/T12-1)," ",(U12/T12-1)) -> 0.22425464 | Z69: =IF(ISERROR(Z12/#REF!-1),"",Z12/#REF!-1) | AA69: =IF(ISERROR(AA12/W12-1),"",AA12/W12-1) -> -0.7683278 | AB69: =IF(ISERROR(AB12/X12-1),"",AB12/X12-1) -> 0.53388172 | AC69: =IF(ISERROR(AC12/Y12-1),"",AC12/Y12-1) -> 0.082460828 | AD69: =IF(ISERROR(AD12/Z12-1),"",AD12/Z12-1) -> 0.062012027 | AE69: =IF(ISERROR(AE12/AA12-1),"",AE12/AA12-1) -> 0.11613395 | AF69: =IF(ISERROR(AF12/AB12-1),"",AF12/AB12-1) -> 0.3662181 | AG69: =IF(ISERROR(AG12/AC12-1),"",AG12/AC12-1) -> 0.096911512 | AH69: =IF(ISERROR(AH12/AD12-1),"",AH12/AD12-1) -> 0.20713937 | ... BZ69: =IF(ISERROR(BZ12/BV12-1),"",BZ12/BV12-1) -> 0.17615854
B70: Operating income | C70: =IF(ISERROR(C45/B45-1)," ",(C45/B45-1)) | D70: =IF(ISERROR(D45/C45-1)," ",(D45/C45-1)) -> 0.48142386 | E70: =IF(ISERROR(E45/D45-1)," ",(E45/D45-1)) -> 0.22461369 | F70: =IF(ISERROR(F45/E45-1)," ",(F45/E45-1)) -> -0.50727662 | G70: =IF(ISERROR(G45/F45-1)," ",(G45/F45-1)) -> -0.95082871 | H70: =IF(ISERROR(H45/G45-1)," ",(H45/G45-1)) -> -2.5996067 | I70: =IF(ISERROR(I45/H45-1)," ",(I45/H45-1)) -> 0.56278558 | J70: =IF(ISERROR(J45/I45-1)," ",(J45/I45-1)) -> 0.90489396 | ... U70: =IF(ISERROR(U45/T45-1)," ",(U45/T45-1)) -> 0.23464744 | AK70: =IF(ISERROR(AK20/AG20-1),"",AK20/AG20-1) -> -82.198544 | AL70: =IF(ISERROR(AL20/AH20-1),"",AL20/AH20-1) -> 43.353459 | AM70: =IF(ISERROR(AM20/AI20-1),"",AM20/AI20-1) -> -30.961913 | AN70: =IF(ISERROR(AN20/AJ20-1),"",AN20/AJ20-1) -> 29.015127 | AO70: =IF(ISERROR(AO20/AK20-1),"",AO20/AK20-1) -> 0.27505882 | AP70: =IF(ISERROR(AP20/AL20-1),"",AP20/AL20-1) -> -0.10538073 | AQ70: =IF(ISERROR(AQ20/AM20-1),"",AQ20/AM20-1) -> -0.34254661 | AR70: =IF(ISERROR(AR20/AN20-1),"",AR20/AN20-1) -> -0.23721171 | ... BZ70: =IF(ISERROR(BZ20/BV20-1),"",BZ20/BV20-1) -> 0.17907975
B71: Profit before tax | C71: =IF(ISERROR(C33/B33-1)," ",(C33/B33-1)) | D71: =IF(ISERROR(D33/C33-1)," ",(D33/C33-1)) -> 0.38113636 | E71: =IF(ISERROR(E33/D33-1)," ",(E33/D33-1)) -> 0.21992992 | F71: =IF(ISERROR(F33/E33-1)," ",(F33/E33-1)) -> -0.43649112 | G71: =IF(ISERROR(G33/F33-1)," ",(G33/F33-1)) -> -0.51808006 | H71: =IF(ISERROR(H33/G33-1)," ",(H33/G33-1)) -> -0.6075004 | I71: =IF(ISERROR(I33/H33-1)," ",(I33/H33-1)) -> -0.0062880192 | J71: =IF(ISERROR(J33/I33-1)," ",(J33/I33-1)) -> 0.72551549 | ... U71: =IF(ISERROR(U33/T33-1)," ",(U33/T33-1)) -> 0.23658569 | Z71: =IF(ISERROR(Z33/#REF!-1)," ",(Z33/#REF!-1)) | AA71: =IF(ISERROR(AA33/W33-1)," ",(AA33/W33-1)) -> -1.7026827 | AB71: =IF(ISERROR(AB33/X33-1)," ",(AB33/X33-1)) -> -0.85095385 | AC71: =IF(ISERROR(AC33/Y33-1)," ",(AC33/Y33-1)) -> -1.0561961 | AD71: =IF(ISERROR(AD33/Z33-1)," ",(AD33/Z33-1)) -> 1.4779036 | AE71: =IF(ISERROR(AE33/AA33-1)," ",(AE33/AA33-1)) -> 0.69494577 | AF71: =IF(ISERROR(AF33/AB33-1)," ",(AF33/AB33-1)) -> -11.056131 | AG71: =IF(ISERROR(AG33/AC33-1)," ",(AG33/AC33-1)) -> 5.1493597 | AH71: =IF(ISERROR(AH33/AD33-1)," ",(AH33/AD33-1)) -> -0.46534435 | ... BZ71: =IF(ISERROR(BZ33/BV33-1)," ",(BZ33/BV33-1)) -> 0.18091838
B72: Net income to common shareholders | C72: =IF(ISERROR(C40/B40-1)," ",(C40/B40-1)) | D72: =IF(ISERROR(D40/C40-1)," ",(D40/C40-1)) -> 0.34038265 | E72: =IF(ISERROR(E40/D40-1)," ",(E40/D40-1)) -> 0.22174324 | F72: =IF(ISERROR(F40/E40-1)," ",(F40/E40-1)) -> -0.43808538 | G72: =IF(ISERROR(G40/F40-1)," ",(G40/F40-1)) -> -0.50510885 | H72: =IF(ISERROR(H40/G40-1)," ",(H40/G40-1)) -> -0.59597737 | I72: =IF(ISERROR(I40/H40-1)," ",(I40/H40-1)) -> -0.03637475 | J72: =IF(ISERROR(J40/I40-1)," ",(J40/I40-1)) -> 0.81339509 | ... U72: =IF(ISERROR(U40/T40-1)," ",(U40/T40-1)) -> 0.23948085 | Z72: =IF(ISERROR(Z40/#REF!-1)," ",(Z40/#REF!-1)) | AA72: =IF(ISERROR(AA40/W40-1)," ",(AA40/W40-1)) -> -1.8266855 | AB72: =IF(ISERROR(AB40/X40-1)," ",(AB40/X40-1)) -> -0.83335249 | AC72: =IF(ISERROR(AC40/Y40-1)," ",(AC40/Y40-1)) -> -1.0661131 | AD72: =IF(ISERROR(AD40/Z40-1)," ",(AD40/Z40-1)) -> 1.3052064 | AE72: =IF(ISERROR(AE40/AA40-1)," ",(AE40/AA40-1)) -> 0.69494577 | AF72: =IF(ISERROR(AF40/AB40-1)," ",(AF40/AB40-1)) -> -10.294531 | AG72: =IF(ISERROR(AG40/AC40-1)," ",(AG40/AC40-1)) -> 3.4182838 | AH72: =IF(ISERROR(AH40/AD40-1)," ",(AH40/AD40-1)) -> -0.45902857 | ... BZ72: =IF(ISERROR(BZ40/BV40-1)," ",(BZ40/BV40-1)) -> 0.18709814
B73: EBITDA | C73: =IF(ISERROR(C20/B20-1)," ",(C20/B20-1)) | D73: =IF(ISERROR(D20/C20-1)," ",(D20/C20-1)) -> 0.48142386 | E73: =IF(ISERROR(E20/D20-1)," ",(E20/D20-1)) -> 0.22461369 | F73: =IF(ISERROR(F20/E20-1)," ",(F20/E20-1)) -> -0.50727662 | G73: =IF(ISERROR(G20/F20-1)," ",(G20/F20-1)) -> -0.95082871 | H73: =IF(ISERROR(H20/G20-1)," ",(H20/G20-1)) -> -2.5996067 | I73: =IF(ISERROR(I48/H48-1)," ",(I48/H48-1)) -> 0.050256941 | J73: =IF(ISERROR(J48/I48-1)," ",(J48/I48-1)) -> 0.014560839 | K73: =IF(ISERROR(K48/J48-1)," ",(K48/J48-1)) -> 17.665272 | L73: =IF(ISERROR(L48/K48-1)," ",(L48/K48-1)) -> 1.1723945 | M73: =IF(ISERROR(M48/L48-1)," ",(M48/L48-1)) -> -0.15558644 | N73: =IF(ISERROR(N48/M48-1)," ",(N48/M48-1)) -> 0.35924282 | O73: =IF(ISERROR(O48/N48-1)," ",(O48/N48-1)) -> 0.16702849 | P73: =IF(ISERROR(P48/O48-1)," ",(P48/O48-1)) -> 0.41232774 | ... U73: =IF(ISERROR(U48/T48-1)," ",(U48/T48-1)) -> 0.23217308 | Z73: =IF(ISERROR(Z20/#REF!-1),"",Z20/#REF!-1) | AA73: =IF(ISERROR(AA20/W20-1),"",AA20/W20-1) -> -3.7948071 | AB73: =IF(ISERROR(AB20/X20-1),"",AB20/X20-1) -> -0.89186298 | AC73: =IF(ISERROR(AC20/Y20-1),"",AC20/Y20-1) -> -0.61629156 | AD73: =IF(ISERROR(AD20/Z20-1),"",AD20/Z20-1) -> -0.32699317 | AE73: =IF(ISERROR(AE20/AA20-1),"",AE20/AA20-1) -> 0.5209126 | AF73: =IF(ISERROR(AF20/AB20-1),"",AF20/AB20-1) -> 0.58270193 | AG73: =IF(ISERROR(AG20/AC20-1),"",AG20/AC20-1) -> 0.2764545 | AH73: =IF(ISERROR(AH20/AD20-1),"",AH20/AD20-1) -> 0.048539182 | ... BZ73: =IF(ISERROR(BZ20/BV20-1),"",BZ20/BV20-1) -> 0.17907975
B74: EBIT | C74: =IF(ISERROR(C45/B45-1)," ",(C45/B45-1)) | D74: =IF(ISERROR(D45/C45-1)," ",(D45/C45-1)) -> 0.48142386 | E74: =IF(ISERROR(E45/D45-1)," ",(E45/D45-1)) -> 0.22461369 | F74: =IF(ISERROR(F45/E45-1)," ",(F45/E45-1)) -> -0.50727662 | G74: =IF(ISERROR(G45/F45-1)," ",(G45/F45-1)) -> -0.95082871 | H74: =IF(ISERROR(H45/G45-1)," ",(H45/G45-1)) -> -2.5996067 | I74: =IF(ISERROR(I45/H45-1)," ",(I45/H45-1)) -> 0.56278558 | J74: =IF(ISERROR(J45/I45-1)," ",(J45/I45-1)) -> 0.90489396 | ... U74: =IF(ISERROR(U45/T45-1)," ",(U45/T45-1)) -> 0.23464744 | Z74: =IF(ISERROR(Z45/#REF!-1)," ",(Z45/#REF!-1)) | AA74: =IF(ISERROR(AA45/W45-1)," ",(AA45/W45-1)) -> -3.7948071 | AB74: =IF(ISERROR(AB45/X45-1)," ",(AB45/X45-1)) -> -0.89186298 | AC74: =IF(ISERROR(AC45/Y45-1)," ",(AC45/Y45-1)) -> -0.61629156 | AD74: =IF(ISERROR(AD45/Z45-1)," ",(AD45/Z45-1)) -> -0.32699317 | AE74: =IF(ISERROR(AE45/AA45-1)," ",(AE45/AA45-1)) -> 0.5209126 | AF74: =IF(ISERROR(AF45/AB45-1)," ",(AF45/AB45-1)) -> 0.58270193 | AG74: =IF(ISERROR(AG45/AC45-1)," ",(AG45/AC45-1)) -> 0.2764545 | AH74: =IF(ISERROR(AH45/AD45-1)," ",(AH45/AD45-1)) -> 0.048539182 | ... BZ74: =IF(ISERROR(BZ45/BV45-1)," ",(BZ45/BV45-1)) -> 0.17907975
B75: EPS | D75: =D50/C50-1 -> 0.28985507 | E75: =E50/D50-1 -> 0.14606742 | F75: =F50/E50-1 -> -0.54901961 | G75: =G50/F50-1 -> -0.73913043 | H75: =H50/G50-1 -> -0.7475 | I75: =I50/H50-1 -> -0.15181518 | J75: =J50/I50-1 -> 0.80933852 | K75: =K50/J50-1 -> 6.5462366 | ... U75: =U50/T50-1 -> 0.23948085 | AK75: =AK50/AG50-1 -> -48.814815 | AL75: =AL50/AH50-1 -> 1.7216117 | AM75: =AM50/AI50-1 -> -16.359606 | AN75: =AN50/AJ50-1 -> 8.2222222 | AO75: =AO50/AK50-1 -> 0.34043377 | AP75: =AP50/AL50-1 -> 3.0094213 | AQ75: =AQ50/AM50-1 -> -0.2944195 | AR75: =AR50/AN50-1 -> -0.5769123 | ... BZ75: =BZ50/BV50-1 -> 0.18709814
B77: Margin analysis | C77: =C4 -> 2009 | D77: =D4 -> 2010 | E77: =E4 -> 2011 | F77: =F4 -> 2012 | G77: =G4 -> 2013 | H77: =H4 -> 2014 | I77: =I4 -> 2015 | J77: =J4 -> 2016 | ... U77: =U4 -> 2027 | W77: =W4 -> 1Q14 | X77: =X4 -> 2Q14 | Y77: =Y4 -> 3Q14 | Z77: =Z4 -> 4Q14 | AA77: =AA4 -> 1Q15 | AB77: =AB4 -> 2Q15 | AC77: =AC4 -> 3Q15 | AD77: =AD4 -> 4Q15 | ... BZ77: =BZ4 -> 4Q27
B78: % of sales
B79: Operating expense | C79: =C15/C7 -> 0.12539949 | D79: =D15/D7 -> 0.10452555 | E79: =E15/E7 -> 0.12524431 | F79: =F15/F7 -> 0.2290616 | G79: =G15/G7 -> 0.38877361 | H79: =H15/H7 -> 0.34453139 | I79: =I15/I7 -> 0.30192658 | J79: =J15/J7 -> 0.35909564 | ... U79: =U15/U7 -> 0.058717763 | W79: =W15/W7 -> 0.2934839 | X79: =X15/X7 -> 0.57956785 | Y79: =Y15/Y7 -> 0.47779343 | Z79: =Z15/Z7 -> 0.19926853 | AA79: =AA15/AA7 -> 0.43095537 | AB79: =AB15/AB7 -> 0.40599305 | AC79: =AC15/AC7 -> 0.31745695 | AD79: =AD15/AD7 -> 0.19892414 | ... BZ79: =BZ15/BZ7 -> 0.076681512
B80: Sales tax | C80: =IF(ISERROR(C16/C$7)," ",C16/C$7) -> 0 | D80: =IF(ISERROR(D16/D$7)," ",D16/D$7) -> 0.00050980879 | E80: =IF(ISERROR(E16/E$7)," ",E16/E$7) -> 0.0086407571 | F80: =IF(ISERROR(F16/F$7)," ",F16/F$7) -> 0.0094207998 | G80: =IF(ISERROR(G16/G$7)," ",G16/G$7) -> 0.0062926306 | H80: =IF(ISERROR(H16/H$7)," ",H16/H$7) -> 0.0069482635 | I80: =IF(ISERROR(I16/I$7)," ",I16/I$7) -> 0.0088145434 | J80: =IF(ISERROR(J16/J$7)," ",J16/J$7) -> 0.020879414 | ... U80: =IF(ISERROR(U16/U$7)," ",U16/U$7) -> 0.002 | W80: =IF(ISERROR(W16/W$7)," ",W16/W$7) -> 0.014394831 | X80: =IF(ISERROR(X16/X$7)," ",X16/X$7) -> 0.0054748048 | Y80: =IF(ISERROR(Y16/Y$7)," ",Y16/Y$7) -> 0.00010504891 | Z80: =IF(ISERROR(Z16/Z$7)," ",Z16/Z$7) -> 0.004190095 | AA80: =IF(ISERROR(AA16/AA$7)," ",AA16/AA$7) -> 0.0075504172 | AB80: =IF(ISERROR(AB16/AB$7)," ",AB16/AB$7) -> 0.0030482471 | AC80: =IF(ISERROR(AC16/AC$7)," ",AC16/AC$7) -> 0.0010833215 | AD80: =IF(ISERROR(AD16/AD$7)," ",AD16/AD$7) -> 0.015810167 | ... BO80: =IF(ISERROR(BO16/BO$7)," ",BO16/BO$7) -> 0.0015919784 | BP80: 0.002 | BQ80: 0.002 | BR80: 0.002 | BS80: 0.002 | BT80: 0.002 | BU80: 0.002 | BV80: 0.002 | BW80: 0.002 | BX80: 0.002 | BY80: 0.002 | BZ80: 0.002
B81: Marketing expense | C81: =IF(ISERROR(C17/C$7)," ",C17/C$7) -> 0.027158719 | D81: =IF(ISERROR(D17/D$7)," ",D17/D$7) -> 0.018956502 | E81: =IF(ISERROR(E17/E$7)," ",E17/E$7) -> 0.019032612 | F81: =IF(ISERROR(F17/F$7)," ",F17/F$7) -> 0.033282799 | G81: =IF(ISERROR(G17/G$7)," ",G17/G$7) -> 0.036004756 | H81: =IF(ISERROR(H17/H$7)," ",H17/H$7) -> 0.038749047 | I81: =IF(ISERROR(I17/I$7)," ",I17/I$7) -> 0.031629676 | J81: =IF(ISERROR(J17/J$7)," ",J17/J$7) -> 0.02808949 | ... U81: =IF(ISERROR(U17/U$7)," ",U17/U$7) -> 0.0053249191 | W81: =IF(ISERROR(W17/W$7)," ",W17/W$7) -> 0.019115166 | X81: =IF(ISERROR(X17/X$7)," ",X17/X$7) -> 0.053809589 | Y81: =IF(ISERROR(Y17/Y$7)," ",Y17/Y$7) -> 0.070199603 | Z81: =IF(ISERROR(Z17/Z$7)," ",Z17/Z$7) -> 0.032705115 | AA81: =IF(ISERROR(AA17/AA$7)," ",AA17/AA$7) -> 0.035162117 | AB81: =IF(ISERROR(AB17/AB$7)," ",AB17/AB$7) -> 0.059010307 | AC81: =IF(ISERROR(AC17/AC$7)," ",AC17/AC$7) -> 0.038751502 | AD81: =IF(ISERROR(AD17/AD$7)," ",AD17/AD$7) -> 0.014199429 | ... BZ81: =IF(ISERROR(BZ17/BZ$7)," ",BZ17/BZ$7) -> 0.0058558935
B82: Administrative expense | C82: =IF(ISERROR(C18/C$7)," ",C18/C$7) -> 0.026342883 | D82: =IF(ISERROR(D18/D$7)," ",D18/D$7) -> 0.025805548 | E82: =IF(ISERROR(E18/E$7)," ",E18/E$7) -> 0.046041346 | F82: =IF(ISERROR(F18/F$7)," ",F18/F$7) -> 0.11771279 | G82: =IF(ISERROR(G18/G$7)," ",G18/G$7) -> 0.25041972 | H82: =IF(ISERROR(H18/H$7)," ",H18/H$7) -> 0.23718476 | I82: =IF(ISERROR(I18/I$7)," ",I18/I$7) -> 0.20796385 | J82: =IF(ISERROR(J18/J$7)," ",J18/J$7) -> 0.25884907 | ... U82: =IF(ISERROR(U18/U$7)," ",U18/U$7) -> 0.014085795 | W82: =IF(ISERROR(W18/W$7)," ",W18/W$7) -> 0.21226476 | X82: =IF(ISERROR(X18/X$7)," ",X18/X$7) -> 0.42796617 | Y82: =IF(ISERROR(Y18/Y$7)," ",Y18/Y$7) -> 0.32386873 | Z82: =IF(ISERROR(Z18/Z$7)," ",Z18/Z$7) -> 0.11505107 | AA82: =IF(ISERROR(AA18/AA$7)," ",AA18/AA$7) -> 0.30358482 | AB82: =IF(ISERROR(AB18/AB$7)," ",AB18/AB$7) -> 0.27593496 | AC82: =IF(ISERROR(AC18/AC$7)," ",AC18/AC$7) -> 0.21564403 | AD82: =IF(ISERROR(AD18/AD$7)," ",AD18/AD$7) -> 0.1377498 | ... BZ82: =IF(ISERROR(BZ18/BZ$7)," ",BZ18/BZ$7) -> 0.01549036
B83: R&D | C83: =IF(ISERROR(C19/C$7)," ",C19/C$7) -> 0.071897884 | D83: =IF(ISERROR(D19/D$7)," ",D19/D$7) -> 0.059253688 | E83: =IF(ISERROR(E19/E$7)," ",E19/E$7) -> 0.051529596 | F83: =IF(ISERROR(F19/F$7)," ",F19/F$7) -> 0.068645203 | G83: =IF(ISERROR(G19/G$7)," ",G19/G$7) -> 0.096056497 | H83: =IF(ISERROR(H19/H$7)," ",H19/H$7) -> 0.06164932 | I83: =IF(ISERROR(I19/I$7)," ",I19/I$7) -> 0.053518511 | J83: =IF(ISERROR(J19/J$7)," ",J19/J$7) -> 0.051277674 | ... U83: =IF(ISERROR(U19/U$7)," ",U19/U$7) -> 0.037307049 | W83: =IF(ISERROR(W19/W$7)," ",W19/W$7) -> 0.047709138 | X83: =IF(ISERROR(X19/X$7)," ",X19/X$7) -> 0.092317278 | Y83: =IF(ISERROR(Y19/Y$7)," ",Y19/Y$7) -> 0.083620047 | Z83: =IF(ISERROR(Z19/Z$7)," ",Z19/Z$7) -> 0.047322251 | AA83: =IF(ISERROR(AA19/AA$7)," ",AA19/AA$7) -> 0.084658018 | AB83: =IF(ISERROR(AB19/AB$7)," ",AB19/AB$7) -> 0.067999533 | AC83: =IF(ISERROR(AC19/AC$7)," ",AC19/AC$7) -> 0.061978097 | AD83: =IF(ISERROR(AD19/AD$7)," ",AD19/AD$7) -> 0.031164736 | ... BZ83: =IF(ISERROR(BZ19/BZ$7)," ",BZ19/BZ$7) -> 0.053335258
B84: Gross margin | C84: =IF(ISERROR(C12/C$7)," ",C12/C$7) -> 0.49769393 | D84: =IF(ISERROR(D12/D$7)," ",D12/D$7) -> 0.50796225 | E84: =IF(ISERROR(E12/E$7)," ",E12/E$7) -> 0.50184399 | F84: =IF(ISERROR(F12/F$7)," ",F12/F$7) -> 0.48686565 | G84: =IF(ISERROR(G12/G$7)," ",G12/G$7) -> 0.40510969 | H84: =IF(ISERROR(H12/H$7)," ",H12/H$7) -> 0.32461019 | I84: =IF(ISERROR(I12/I$7)," ",I12/I$7) -> 0.27147707 | J84: =IF(ISERROR(J12/J$7)," ",J12/J$7) -> 0.30559214 | ... U84: =IF(ISERROR(U12/U$7)," ",U12/U$7) -> 0.45545176 | W84: =IF(ISERROR(W12/W$7)," ",W12/W$7) -> 0.34224413 | X84: =IF(ISERROR(X12/X$7)," ",X12/X$7) -> 0.29917639 | Y84: =IF(ISERROR(Y12/Y$7)," ",Y12/Y$7) -> 0.28168397 | Z84: =IF(ISERROR(Z12/Z$7)," ",Z12/Z$7) -> 0.34444955 | AA84: =IF(ISERROR(AA12/AA$7)," ",AA12/AA$7) -> 0.15851349 | AB84: =IF(ISERROR(AB12/AB$7)," ",AB12/AB$7) -> 0.38083066 | AC84: =IF(ISERROR(AC12/AC$7)," ",AC12/AC$7) -> 0.25461965 | AD84: =IF(ISERROR(AD12/AD$7)," ",AD12/AD$7) -> 0.27142065 | ... BZ84: =IF(ISERROR(BZ12/BZ$7)," ",BZ12/BZ$7) -> 0.46602934
B85: Operating margin | C85: =IF(ISERROR(C20/C$7)," ",C20/C$7) -> 0.37229445 | D85: =IF(ISERROR(D20/D$7)," ",D20/D$7) -> 0.4034367 | E85: =IF(ISERROR(E20/E$7)," ",E20/E$7) -> 0.37659968 | F85: =IF(ISERROR(F20/F$7)," ",F20/F$7) -> 0.25780405 | G85: =IF(ISERROR(G20/G$7)," ",G20/G$7) -> 0.016336081 | H85: =IF(ISERROR(H20/H$7)," ",H20/H$7) -> -0.019921196 | I85: =IF(ISERROR(I20/I$7)," ",I20/I$7) -> -0.03044951 | J85: =IF(ISERROR(J20/J$7)," ",J20/J$7) -> -0.053503501 | ... U85: =IF(ISERROR(U20/U$7)," ",U20/U$7) -> 0.396734 | W85: =IF(ISERROR(W20/W$7)," ",W20/W$7) -> 0.048760229 | X85: =IF(ISERROR(X20/X$7)," ",X20/X$7) -> -0.28039146 | Y85: =IF(ISERROR(Y20/Y$7)," ",Y20/Y$7) -> -0.19610946 | Z85: =IF(ISERROR(Z20/Z$7)," ",Z20/Z$7) -> 0.14518101 | AA85: =IF(ISERROR(AA20/AA$7)," ",AA20/AA$7) -> -0.27244188 | AB85: =IF(ISERROR(AB20/AB$7)," ",AB20/AB$7) -> -0.025162391 | AC85: =IF(ISERROR(AC20/AC$7)," ",AC20/AC$7) -> -0.062837298 | AD85: =IF(ISERROR(AD20/AD$7)," ",AD20/AD$7) -> 0.072496515 | ... BZ85: =IF(ISERROR(BZ20/BZ$7)," ",BZ20/BZ$7) -> 0.38934783
B86: EBITDA margin | C86: =IF(ISERROR(C48/C$7)," ",C48/C$7) -> 0.39499405 | D86: =IF(ISERROR(D48/D$7)," ",D48/D$7) -> 0.43780434 | E86: =IF(ISERROR(E48/E$7)," ",E48/E$7) -> 0.41954431 | F86: =IF(ISERROR(F48/F$7)," ",F48/F$7) -> 0.34037394 | G86: =IF(ISERROR(G48/G$7)," ",G48/G$7) -> 0.24119203 | H86: =IF(ISERROR(H48/H$7)," ",H48/H$7) -> 0.189925 | I86: =IF(ISERROR(I48/I$7)," ",I48/I$7) -> 0.19509368 | J86: =IF(ISERROR(J48/J$7)," ",J48/J$7) -> 0.18257965 | ... U86: =IF(ISERROR(U48/U$7)," ",U48/U$7) -> 0.41538575 | W86: =IF(ISERROR(W48/W$7)," ",W48/W$7) -> 0.20755305 | X86: =IF(ISERROR(X48/X$7)," ",X48/X$7) -> 0.026872973 | Y86: =IF(ISERROR(Y48/Y$7)," ",Y48/Y$7) -> 0.094836897 | Z86: =IF(ISERROR(Z48/Z$7)," ",Z48/Z$7) -> 0.30983336 | AA86: =IF(ISERROR(AA48/AA$7)," ",AA48/AA$7) -> 0.076639006 | AB86: =IF(ISERROR(AB48/AB$7)," ",AB48/AB$7) -> 0.25522851 | AC86: =IF(ISERROR(AC48/AC$7)," ",AC48/AC$7) -> 0.20398963 | AD86: =IF(ISERROR(AD48/AD$7)," ",AD48/AD$7) -> 0.20666635 | ... AR86: =IF(ISERROR(AR48/AR$7)," ",AR48/AR$7) -> 0.18755566 | AS86: =IF(ISERROR(AS20/AS$7)," ",AS20/AS$7) -> 0.14948023 | AT86: =IF(ISERROR(AT20/AT$7)," ",AT20/AT$7) -> 0.07521665 | AU86: =IF(ISERROR(AU20/AU$7)," ",AU20/AU$7) -> 0.11546702 | AV86: =IF(ISERROR(AV20/AV$7)," ",AV20/AV$7) -> 0.15671637 | AW86: =IF(ISERROR(AW20/AW$7)," ",AW20/AW$7) -> 0.10981624 | AX86: =IF(ISERROR(AX20/AX$7)," ",AX20/AX$7) -> 0.06414444 | AY86: =IF(ISERROR(AY20/AY$7)," ",AY20/AY$7) -> 0.09266492 | AZ86: =IF(ISERROR(AZ20/AZ$7)," ",AZ20/AZ$7) -> 0.11139588 | ... BZ86: =IF(ISERROR(BZ20/BZ$7)," ",BZ20/BZ$7) -> 0.38934783
B87: EBIT margin | C87: =IF(ISERROR(C45/C$7)," ",C45/C$7) -> 0.37229445 | D87: =IF(ISERROR(D45/D$7)," ",D45/D$7) -> 0.4034367 | E87: =IF(ISERROR(E45/E$7)," ",E45/E$7) -> 0.37659968 | F87: =IF(ISERROR(F45/F$7)," ",F45/F$7) -> 0.25780405 | G87: =IF(ISERROR(G45/G$7)," ",G45/G$7) -> 0.016336081 | H87: =IF(ISERROR(H45/H$7)," ",H45/H$7) -> -0.019921196 | I87: =IF(ISERROR(I45/I$7)," ",I45/I$7) -> -0.03044951 | J87: =IF(ISERROR(J45/J$7)," ",J45/J$7) -> -0.053503501 | ... U87: =IF(ISERROR(U45/U$7)," ",U45/U$7) -> 0.396734 | W87: =IF(ISERROR(W45/W$7)," ",W45/W$7) -> 0.048760229 | X87: =IF(ISERROR(X45/X$7)," ",X45/X$7) -> -0.28039146 | Y87: =IF(ISERROR(Y45/Y$7)," ",Y45/Y$7) -> -0.19610946 | Z87: =IF(ISERROR(Z45/Z$7)," ",Z45/Z$7) -> 0.14518101 | AA87: =IF(ISERROR(AA45/AA$7)," ",AA45/AA$7) -> -0.27244188 | AB87: =IF(ISERROR(AB45/AB$7)," ",AB45/AB$7) -> -0.025162391 | AC87: =IF(ISERROR(AC45/AC$7)," ",AC45/AC$7) -> -0.062837298 | AD87: =IF(ISERROR(AD45/AD$7)," ",AD45/AD$7) -> 0.072496515 | ... BZ87: =IF(ISERROR(BZ45/BZ$7)," ",BZ45/BZ$7) -> 0.38934783
B88: Pre-tax margin | C88: =IF(ISERROR(C33/C$7)," ",C33/C$7) -> 0.39205878 | D88: =IF(ISERROR(D33/D$7)," ",D33/D$7) -> 0.39609307 | E88: =IF(ISERROR(E33/E$7)," ",E33/E$7) -> 0.3683304 | F88: =IF(ISERROR(F33/F$7)," ",F33/F$7) -> 0.2883666 | G88: =IF(ISERROR(G33/G$7)," ",G33/G$7) -> 0.17908796 | H88: =IF(ISERROR(H33/H$7)," ",H33/H$7) -> 0.053587058 | I88: =IF(ISERROR(I33/I$7)," ",I33/I$7) -> 0.052081796 | J88: =IF(ISERROR(J33/J$7)," ",J33/J$7) -> 0.082896442 | ... U88: =IF(ISERROR(U33/U$7)," ",U33/U$7) -> 0.39862544 | W88: =IF(ISERROR(W33/W$7)," ",W33/W$7) -> 0.14220752 | X88: =IF(ISERROR(X33/X$7)," ",X33/X$7) -> -0.43035356 | Y88: =IF(ISERROR(Y33/Y$7)," ",Y33/Y$7) -> 0.21568545 | Z88: =IF(ISERROR(Z33/Z$7)," ",Z33/Z$7) -> 0.12202066 | AA88: =IF(ISERROR(AA33/AA$7)," ",AA33/AA$7) -> -0.19977361 | AB88: =IF(ISERROR(AB33/AB$7)," ",AB33/AB$7) -> -0.053230297 | AC88: =IF(ISERROR(AC33/AC$7)," ",AC33/AC$7) -> -0.010121501 | AD88: =IF(ISERROR(AD33/AD$7)," ",AD33/AD$7) -> 0.22433944 | ... BZ88: =IF(ISERROR(BZ33/BZ$7)," ",BZ33/BZ$7) -> 0.38910906
B89: Effective tax rate (excl. income from associate) | C89: =+C36/C33 -> 0.11741577 | D89: =+D36/D33 -> 0.14345851 | E89: =+E36/E33 -> 0.14218534 | F89: =IF(F36/F33 < 0, 0%, F36/F33) -> 0.14461223 | G89: =IF(G36/G33 < 0, 0%, G36/G33) -> 0.12158888 | H89: =IF(H36/H33 < 0, 0%, H36/H33) -> 0.079667262 | I89: =IF(I36/I33 < 0, 0%, I36/I33) -> 0.12317698 | J89: =IF(J36/J33 < 0, 0%, J36/J33) -> 0.078520841 | K89: =IF(K36/K33 < 0, 0%, K36/K33) -> 0.21558501 | L89: =IF(L36/L33 < 0, 0%, L36/L33) -> 0.10336894 | M89: =IF(M36/M33 < 0, 0%, M36/M33) -> 0.10957537 | ... U89: =IF(U36/U33 < 0, 0%, U36/U33) -> 0.12 | W89: =+W36/W33 -> 0.15 | X89: =+X36/X33 -> 0.10562026 | Y89: =+Y36/Y33 -> 0.15 | Z89: =+Z36/Z33 -> -0.0033176652 | AA89: =+AA36/AA33 -> 0 | AB89: =+AB36/AB33 -> 0 | AC89: =+AC36/AC33 -> 0 | AD89: =+AD36/AD33 -> 0.066608447 | ... AH89: =+AH36/AH33 -> 0.05558248 | AI89: =IF(AI36/AI33 < 0, 0%, AI36/AI33) -> 0 | AJ89: =IF(AJ36/AJ33 < 0, 0%, AJ36/AJ33) -> 0.047091265 | AK89: =IF(AK36/AK33 < 0, 0%, AK36/AK33) -> 0.15521215 | AL89: =IF(AL36/AL33 < 0, 0%, AL36/AL33) -> 0.37915901 | AM89: =IF(AM36/AM33 < 0, 0%, AM36/AM33) -> 0.1235344 | AN89: =IF(AN36/AN33 < 0, 0%, AN36/AN33) -> 0.14658707 | AO89: =IF(AO36/AO33 < 0, 0%, AO36/AO33) -> 0.10213832 | AP89: =IF(AP36/AP33 < 0, 0%, AP36/AP33) -> 0.022338524 | ... BP89: =IF(BP36/BP33 < 0, 0%, BP36/BP33) -> 0.11738901 | BQ89: 0.12 | BR89: 0.12 | BS89: 0.12 | BT89: 0.12 | BU89: 0.12 | BV89: 0.12 | BW89: 0.12 | BX89: 0.12 | BY89: 0.12 | BZ89: 0.12
B90: Net margins | C90: =IF(ISERROR(C40/C$7)," ",C40/C$7) -> 0.3460249 | D90: =IF(ISERROR(D40/D$7)," ",D40/D$7) -> 0.33927015 | E90: =IF(ISERROR(E40/E$7)," ",E40/E$7) -> 0.31595921 | F90: =IF(ISERROR(F40/F$7)," ",F40/F$7) -> 0.24666526 | G90: =IF(ISERROR(G40/G$7)," ",G40/G$7) -> 0.15731285 | H90: =IF(ISERROR(H40/H$7)," ",H40/H$7) -> 0.048453395 | I90: =IF(ISERROR(I40/I$7)," ",I40/I$7) -> 0.045666517 | J90: =IF(ISERROR(J40/J$7)," ",J40/J$7) -> 0.076387343 | ... U90: =IF(ISERROR(U40/U$7)," ",U40/U$7) -> 0.3336499 | W90: =IF(ISERROR(W40/W$7)," ",W40/W$7) -> 0.1208764 | X90: =IF(ISERROR(X40/X$7)," ",X40/X$7) -> -0.3848995 | Y90: =IF(ISERROR(Y40/Y$7)," ",Y40/Y$7) -> 0.18333263 | Z90: =IF(ISERROR(Z40/Z$7)," ",Z40/Z$7) -> 0.12242548 | AA90: =IF(ISERROR(AA40/AA$7)," ",AA40/AA$7) -> -0.19977361 | AB90: =IF(ISERROR(AB40/AB$7)," ",AB40/AB$7) -> -0.053230297 | AC90: =IF(ISERROR(AC40/AC$7)," ",AC40/AC$7) -> -0.010121501 | AD90: =IF(ISERROR(AD40/AD$7)," ",AD40/AD$7) -> 0.20939653 | ... BZ90: =IF(ISERROR(BZ40/BZ$7)," ",BZ40/BZ$7) -> 0.32611975
B92: Quarterly distribution | W92: =W4 -> 1Q14 | X92: =X4 -> 2Q14 | Y92: =Y4 -> 3Q14 | Z92: =Z4 -> 4Q14 | AA92: =AA4 -> 1Q15 | AB92: =AB4 -> 2Q15 | AC92: =AC4 -> 3Q15 | AD92: =AD4 -> 4Q15 | ... BB92: =BB4 -> 4Q21
B93: Revenue | W93: =W7/$I$7 -> 0.3159601 | X93: =X7/$I$7 -> 0.1632867 | Y93: =Y7/$I$7 -> 0.18026997 | Z93: =Z7/$I$7 -> 0.31854325 | AA93: =AA7/$I$7 -> 0.15804324 | AB93: =AB7/$I$7 -> 0.19676058 | AC93: =AC7/$I$7 -> 0.21587671 | AD93: =AD7/$I$7 -> 0.42931946 | AE93: =AE7/$J$7 -> 0.078447153 | AF93: =AF7/$J$7 -> 0.35224578 | AG93: =AG7/$J$7 -> 0.19717091 | AH93: =AH7/$J$7 -> 0.37213615 | AI93: =AI7/$K$7 -> 0.0061790668 | AJ93: =AJ7/$K$7 -> 0.023767976 | AK93: =AK7/$K$7 -> 0.45347801 | AL93: =AL7/$K$7 -> 0.51657495 | AM93: =AM7/$L$7 -> 0.27123991 | AN93: =AN7/$L$7 -> 0.27674075 | AO93: =AO7/$L$7 -> 0.26710177 | AP93: =AP7/$L$7 -> 0.18491758 | AQ93: =AQ7/$L$7 -> 0.1698203 | AR93: =AR7/$L$7 -> 0.22488076 | AS93: =AS7/$M$7 -> 0.26246235 | AT93: =AT7/$M$7 -> 0.3097653 | AU93: =AU7/$M$7 -> 0.27872644 | AV93: =AV7/$N$7 -> 0.27215562 | AW93: =AW7/$N$7 -> 0.2780459 | AX93: =AX7/$N$7 -> 0.26168962 | AY93: =AY7/$O$7 -> 0.19125159 | AZ93: =AZ7/$O$7 -> 0.23729667 | BA93: =BA7/$O$7 -> 0.26304457 | BB93: =BB7/$O$7 -> 0.30840717
B94: Net income to common shareholders | W94: =W40/$I$40 -> 0.83632649 | X94: =X40/$I$40 -> -1.3762593 | Y94: =Y40/$I$40 -> 0.72371118 | Z94: =Z40/$I$40 -> 0.85396949 | AA94: =AA40/$I$40 -> -0.69137896 | AB94: =AB40/$I$40 -> -0.22935019 | AC94: =AC40/$I$40 -> -0.047846794 | AD94: =AD40/$I$40 -> 1.9685759 | AE94: =AE40/$J$40 -> -0.64621871 | AF94: =AF40/$J$40 -> 1.1755311 | AG94: =AG40/$J$40 -> -0.11657731 | AH94: =AH40/$J$40 -> 0.58726493 | AI94: =AI40/$K$40 -> -0.027129291 | AJ94: =AJ40/$K$40 -> 0.051702897 | AK94: =AK40/$K$40 -> 0.75746758 | AL94: =AL40/$K$40 -> 0.21795882 | AM94: =AM40/$L$40 -> 0.2371415 | AN94: =AN40/$L$40 -> 0.27143774 | AO94: =AO40/$L$40 -> 0.26410791 | AP94: =AP40/$L$40 -> 0.22731286 | AQ94: =AQ40/$M$40 -> 0.19377297 | AR94: =AR40/$M$40 -> 0.20996457 | AS94: =AS40/$M$40 -> 0.29323122 | AT94: =AT40/$M$40 -> 0.30303124 | AU94: =AU40/$M$40 -> 0.2992516 | AV94: =AV40/$N$40 -> 0.24434705 | AW94: =AW40/$N$40 -> 0.271219 | AX94: =AX40/$N$40 -> 0.30688943 | AY94: =AY40/$O$40 -> 0.15173679 | AZ94: =AZ40/$O$40 -> 0.23689473 | BA94: =BA40/$O$40 -> 0.25004346 | BB94: =BB40/$O$40 -> 0.36132501
B96: Other income statement assumptions
B98: Interest income calculation:
B99: Previous cash balance
B100: Interest income as a % of cash
B102: Interest expense calculation:
B103: Total debt | C103: =C145+C141 -> 0 | D103: =D145+D141 -> 20 | E103: =E145+E141 -> 40 | F103: =F145+F141 -> 0 | G103: =G145+G141 -> 19.482643 | H103: =H145+H141 -> 30 | I103: =I145+I141 -> 0 | J103: =J145+J141 -> 7.2771731 | ... U103: =U145+U141 -> 2676.3785
B104: Interest charges | C104: =C25 -> 0 | D104: =D25 -> 0 | E104: =E25 -> 0 | F104: =F25 -> 0 | G104: =G25 -> 0 | H104: =H25 -> 0 | I104: =I25 -> 0 | J104: =J25 -> 0 | ... U104: =U25 -> -80
B105: Effective interest rate | D105: =IFERROR(-D104/AVERAGE(C103:D103),"") -> 0 | E105: =IFERROR(-E104/AVERAGE(D103:E103),"") -> 0 | F105: =IFERROR(-F104/AVERAGE(E103:F103),"") -> 0 | G105: =IFERROR(-G104/AVERAGE(F103:G103),"") -> 0 | H105: =IFERROR(-H104/AVERAGE(G103:H103),"") -> 0 | I105: =IFERROR(-I104/AVERAGE(H103:I103),"") -> 0 | J105: =IFERROR(-J104/AVERAGE(I103:J103),"") -> 0 | K105: =IFERROR(-K104/AVERAGE(J103:K103),"") -> 0 | ... P105: =IFERROR(-P104/AVERAGE(O103:P103),"") -> 0.027877722
B107: Interest income calculation:
B108: Cash balance | C108: =C123 -> 28.353355 | D108: =D123 -> 36.992299 | E108: =E123 -> 37.328881 | F108: =F123 -> 242.63506 | G108: =G123 -> 210.59394 | H108: =H123 -> 136.40814 | I108: =I123 -> 112.31353 | J108: =J123 -> 69.262624 | ... U108: =U123 -> 26301.671
B109: Interest income | C109: =C24 -> 0.4314 | D109: =D24 -> 0.8052 | E109: =E24 -> 0.90568252 | F109: =F24 -> 7.5852688 | G109: =G24 -> 12.762349 | H109: =H24 -> 11.70566 | I109: =I24 -> 6.9046709 | J109: =J24 -> 6.0126569 | ... U109: =U24 -> 160
B110: Interest income as % of cash | D110: =D109/AVERAGE(C108:D108) -> 0.024644332 | E110: =E109/AVERAGE(D108:E108) -> 0.024372124 | F110: =F109/AVERAGE(E108:F108) -> 0.054187469 | G110: =G109/AVERAGE(F108:G108) -> 0.05631744 | H110: =H109/AVERAGE(G108:H108) -> 0.067467373 | I110: =I109/AVERAGE(H108:I108) -> 0.055521266 | J110: =J109/AVERAGE(I108:J108) -> 0.066227385 | K110: =K109/AVERAGE(J108:K108) -> 0.0074676038 | ... P110: =P109/AVERAGE(O108:P108) -> 0.01184171
B112: Income from associates:
B113: Interests in an associate | C113: 0 | D113: 0 | E113: 0 | F113: 0 | G113: 0 | H113: 0 | I113: 0 | J113: 0 | K113: 0 | L113: 0 | M113: 0 | N113: 0 | O113: 0 | P113: 0 | Q113: 0 | R113: 0 | S113: 0
B114: As a % of interest in associates | C114: 0 | D114: 0 | E114: 0 | F114: 0 | G114: 0 | H114: 0 | I114: 0 | J114: 0 | K114: 0 | L114: 0 | M114: 0 | N114: 0 | O114: 0 | P114: 0 | Q114: 0 | R114: 0 | S114: 0
B116: Income from jointly controlled entities:
B117: Interest in a jointly controlled entity | C117: 0 | D117: 0 | E117: 0 | F117: 0 | G117: 0 | H117: 0 | I117: 0 | J117: 0 | K117: 0 | L117: 0 | M117: 0 | N117: 0 | O117: 0 | P117: 0 | Q117: 0 | R117: 0 | S117: 0
B118: As a % of interest in jointly controlled entities | C118: 0 | D118: 0 | E118: 0 | F118: 0 | G118: 0 | H118: 0 | I118: 0 | J118: 0 | K118: 0 | L118: 0 | M118: 0 | N118: 0 | O118: 0 | P118: 0 | Q118: 0 | R118: 0 | S118: 0
B121: Balance sheet | C121: =C4 -> 2009 | D121: =D4 -> 2010 | E121: =E4 -> 2011 | F121: =F4 -> 2012 | G121: =G4 -> 2013 | H121: =H4 -> 2014 | I121: =I4 -> 2015 | J121: =J4 -> 2016 | ... U121: =U4 -> 2027
B123: Cash and equivalents | C123: 28.353355 | D123: 36.992299 | E123: 37.328881 | F123: 242.63506 | G123: 210.59394 | H123: 136.40814 | I123: 112.31353 | J123: 69.262624 | K123: 957.23182 | L123: 1041.1801 | M123: 1236.1909 | N123: 1679.4828 | O123: 3514.6131 | P123: 2831.0227 | Q123: 3317.2785 | R123: 5053.8051 | S123: =R123+S232 -> 6366.7463 | T123: =S123+T232 -> 13855.972 | U123: =T123+U232 -> 26301.671
...

Sheet Assumption
A1: =TODAY() -> 45923
A2: Innolight (300308.SZ)
A3: (Rmb m) | B3: 1Q22 | C3: 2Q22 | D3: 3Q22 | E3: 4Q22 | F3: 1Q23 | G3: 2Q23 | H3: 3Q23 | I3: 4Q23 | J3: 1Q24 | K3: 2Q24 | L3: 3Q24 | M3: 4Q24 | N3: 1Q25 | O3: 2Q25 | P3: 3Q25E | Q3: 4Q25E | R3: 1Q26E | S3: 2Q26E | T3: 3Q26E | U3: 4Q26E | V3: 1Q27E | W3: 2Q27E | X3: 3Q27E | Y3: 4Q27E | AB3: 2014 | AC3: 2015 | AD3: 2016 | AE3: 2017 | AF3: 2018 | AG3: 2019 | AH3: 2020 | AI3: 2021 | AJ3: 2022 | AK3: 2023 | AL3: 2024 | AM3: 2025E | AN3: 2026E | AO3: 2027E | AP3: =A3 -> (Rmb m) | AQ3: Remark
A4: Net income | B4: =Model!BC40 -> 217.4126 | C4: =Model!BD40 -> 275.04257 | D4: =Model!BE40 -> 360.05326 | E4: =Model!BF40 -> 371.48243 | F4: =Model!BG40 -> 249.92027 | G4: =Model!BH40 -> 363.83251 | H4: =Model!BI40 -> 682.1151 | I4: =Model!BJ40 -> 877.65987 | ... Y4: =Model!BZ40 -> 5463.2734 | AD4: =Model!J40 -> 10.054132 | AE4: =Model!K40 -> 161.50542 | AF4: =Model!L40 -> 623.11598 | AG4: =Model!M40 -> 513.4872 | AH4: =Model!N40 -> 865.48355 | AI4: =Model!O40 -> 876.97713 | AJ4: =Model!P40 -> 1223.9909 | AK4: =Model!Q40 -> 2173.5277 | ... AO4: =Model!U40 -> 20489.235 | AP4: Net income
A5: EPS | B5: =Model!BC50 -> 0.2719 | C5: =Model!BD50 -> 0.3439 | D5: =Model!BE50 -> 0.4495 | E5: =Model!BF50 -> 0.4638 | F5: =Model!BG50 -> 0.312 | G5: =Model!BH50 -> 0.4532 | H5: =Model!BI50 -> 0.60690124 | I5: =Model!BJ50 -> 0.78088414 | ... Y5: =Model!BZ50 -> 4.8728475 | AD5: =Model!J50 -> 0.0465 | AE5: =Model!K50 -> 0.3509 | AF5: =Model!L50 -> 1.3127 | AG5: =Model!M50 -> 0.8002 | AH5: =Model!N50 -> 1.2135 | AI5: =Model!O50 -> 1.1815 | AJ5: =Model!P50 -> 1.5291 | AK5: =Model!Q50 -> 2.1529854 | ... AO5: =Model!U50 -> 18.274926 | AP5: EPS
A6: YoY | B6: =Model!BC75 -> 0.45712755 | C6: =Model!BD75 -> 0.18016472 | D6: =Model!BE75 -> 0.46178862 | E6: =Model!BF75 -> 0.17121212 | F6: =Model!BG75 -> 0.14748069 | G6: =Model!BH75 -> 0.31782495 | H6: =Model!BI75 -> 0.35016962 | I6: =Model!BJ75 -> 0.68366568 | ... Y6: =Model!BZ75 -> 0.18709814 | AD6: =Model!J75 -> 0.80933852 | AE6: =Model!K75 -> 6.5462366 | AF6: =Model!L75 -> 2.7409518 | AG6: =Model!M75 -> -0.3904167 | AH6: =Model!N75 -> 0.51649588 | AI6: =Model!O75 -> -0.026370004 | AJ6: =Model!P75 -> 0.29420229 | AK6: =Model!Q75 -> 0.40800823 | ... AO6: =Model!U75 -> 0.23948085 | AP6: YoY
A7: GM | B7: =B197 -> 0.27280443 | C7: =C197 -> 0.27441984 | D7: =D197 -> 0.2977164 | E7: =E197 -> 0.32881312 | F7: =F197 -> 0.28774532 | G7: =G197 -> 0.30441705 | H7: =H197 -> 0.33511423 | I7: =I197 -> 0.35398327 | ... Y7: =Y197 -> 0.46602934 | AD7: =AD197 -> 0 | AE7: =AE197 -> 0 | AF7: =AF197 -> 0.26712491 | AG7: =AG197 -> 0.26040669 | AH7: =AH197 -> 0.26485172 | AI7: =AI197 -> 0.27777104 | AJ7: =AJ197 -> 0.29609915 | AK7: =AK197 -> 0.32728101 | ... AO7: =AO197 -> 0.45545176 | AP7: GM
A8: OPM | B8: =Model!BC87 -> 0.11168883 | C8: =Model!BD87 -> 0.1198616 | D8: =Model!BE87 -> 0.15149166 | E8: =Model!BF87 -> 0.18350615 | F8: =Model!BG87 -> 0.14641988 | G8: =Model!BH87 -> 0.17781796 | H8: =Model!BI87 -> 0.23796138 | I8: =Model!BJ87 -> 0.22052598 | ... Y8: =Model!BZ87 -> 0.38934783 | AD8: =Model!J87 -> -0.053503501 | AE8: =Model!K87 -> 0.14729937 | AF8: =Model!L87 -> 0.14993448 | AG8: =Model!M87 -> 0.12222927 | AH8: =Model!N87 -> 0.1116915 | AI8: =Model!O87 -> 0.11678288 | AJ8: =Model!P87 -> 0.14506133 | AK8: =Model!Q87 -> 0.20411239 | ... AO8: =Model!U87 -> 0.396734 | AP8: OPM
A9: ROE | AD9: =Model!J196 -> 0.018214182 | AE9: =Model!K196 -> 0.070810234 | AF9: =Model!L196 -> 0.14190204 | AG9: =Model!M196 -> 0.087755353 | AH9: =Model!N196 -> 0.11683539 | AI9: =Model!O196 -> 0.090511863 | AJ9: =Model!P196 -> 0.10446208 | AK9: =Model!Q196 -> 0.16587867 | ... AO9: =Model!U196 -> 0.39299606 | AP9: ROE
A10: Capex / Revenue | AD10: =-Model!J216/Model!J7 -> 0.26914705 | AE10: =-Model!K216/Model!K7 -> 0.17851649 | AF10: =-Model!L216/Model!L7 -> 0.11786228 | AG10: =-Model!M216/Model!M7 -> 0.15959604 | AH10: =-Model!N216/Model!N7 -> 0.13562047 | AI10: =-Model!O216/Model!O7 -> 0.10910128 | AJ10: =-Model!P216/Model!P7 -> 0.082125227 | AK10: =-Model!Q216/Model!Q7 -> 0.15902769 | ... AO10: =-Model!U216/Model!U7 -> 0.040813956 | AP10: Capex / Revenue
A12: Revenue (Rmb million) | B12: =+Model!BC7 -> 2088.6226 | C12: =+Model!BD7 -> 2142.4212 | D12: =+Model!BE7 -> 2633.9444 | E12: =+Model!BF7 -> 2776.8065 | F12: =+Model!BG7 -> 1837.1632 | G12: =+Model!BH7 -> 2166.818 | H12: =+Model!BI7 -> 3026.3091 | I12: =+Model!BJ7 -> 3687.6941 | ... O12: =+Model!BP7 -> 8114.8984 | P12: =SUM(P13:P20) -> 9544.9328 | Q12: =SUM(Q13:Q20) -> 10707.949 | R12: =SUM(R13:R20) -> 10818.019 | S12: =SUM(S13:S20) -> 12058.533 | T12: =SUM(T13:T20) -> 13278.777 | U12: =SUM(U13:U20) -> 14427.284 | V12: =SUM(V13:V20) -> 13381.138 | W12: =SUM(W13:W20) -> 15125.613 | ... Y12: =SUM(Y13:Y20) -> 16752.354 | AB12: =Model!H7 -> 118.74621 | AC12: =Model!I7 -> 121.40994 | AD12: =Model!J7 -> 131.62038 | AE12: =Model!K7 -> 2357.0835 | AF12: =Model!L7 -> 5156.3142 | AG12: =Model!M7 -> 4757.677 | AH12: =Model!N7 -> 7049.5901 | AI12: =Model!O7 -> 7695.4048 | AJ12: =Model!P7 -> 9641.7948 | AK12: =SUM(AK13:AK20) -> 10717.984 | AL12: =SUM(AL13:AL20) -> 23862.16 | AM12: =SUM(AM13:AM20) -> 35041.957 | AN12: =SUM(AN13:AN20) -> 50582.612 | AO12: =SUM(AO13:AO20) -> 61409.384 | AP12: Revenue (Rmb million)
A13: 10G/40G | B13: =+B45 -> 162.4 | C13: =+C45 -> 182.7 | D13: =+D45 -> 182.7 | E13: =+E45 -> 140.07 | F13: =+F45 -> 156.31 | G13: =+G45 -> 178.64 | H13: =+H45 -> 156.31 | I13: =+I45 -> 156.19835 | ... Y13: =+Y45 -> 98.252 | AF13: =+AF45 -> 1248.7628 | AG13: =+AG45 -> 1029.8327 | AH13: =+AH45 -> 501.58826 | AI13: =+AI45 -> 897.05834 | AJ13: =+AJ45 -> 666.38668 | AK13: =SUM(F13:I13) -> 647.45835 | AL13: =SUM(J13:M13) -> 687.764 | AM13: =SUM(N13:Q13) -> 589.512 | AN13: =SUM(R13:U13) -> 540.386 | AO13: =SUM(V13:Y13) -> 393.008
A14: 100G | B14: =+B46 -> 1153.11 | C14: =+C46 -> 1153.11 | D14: =+D46 -> 1225.1794 | E14: =+E46 -> 792.76312 | F14: =+F46 -> 799.68178 | G14: =+G46 -> 714.00159 | H14: =+H46 -> 285.60064 | I14: =+I46 -> 285.60064 | ... Y14: =+Y46 -> 174.46763 | AF14: =+AF46 -> 3749.13 | AG14: =+AG46 -> 3600.6 | AH14: =+AH46 -> 5705.727 | AI14: =+AI46 -> 4140.922 | AJ14: =+AJ46 -> 4324.1625 | AK14: =SUM(F14:I14) -> 2084.8847 | AL14: =SUM(J14:M14) -> 797.23657 | AM14: =SUM(N14:Q14) -> 771.93964 | AN14: =SUM(R14:U14) -> 734.60054 | AO14: =SUM(V14:Y14) -> 697.87051
A15: 200G | B15: =+B47 -> 323.4 | C15: =+C47 -> 385 | D15: =+D47 -> 462 | E15: =+E47 -> 523.6 | F15: =+F47 -> 375.804 | G15: =+G47 -> 216.81 | H15: =+H47 -> 86.724 | I15: =+I47 -> 86.724 | ... Y15: =+Y47 -> 66.919491 | AF15: =+AF47 -> 0 | AG15: =+AG47 -> 0 | AH15: =+AH47 -> 30.6 | AI15: =+AI47 -> 1003 | AJ15: =+AJ47 -> 1694 | AK15: =SUM(F15:I15) -> 766.062 | AL15: =SUM(J15:M15) -> 355.6872 | AM15: =SUM(N15:Q15) -> 296.08821 | AN15: =SUM(R15:U15) -> 281.76628 | AO15: =SUM(V15:Y15) -> 267.67796
A16: 400G | B16: =+B48 -> 364 | C16: =+C48 -> 364 | D16: =+D48 -> 728 | E16: =+E48 -> 1272.18 | F16: =+F48 -> 459.9 | G16: =+G48 -> 459.9 | H16: =+H48 -> 613.2 | I16: =+I48 -> 613.2 | ... Y16: =+Y48 -> 162.84402 | AF16: =+AF48 -> 0 | AG16: =+AG48 -> 0 | AH16: =+AH48 -> 272 | AI16: =+AI48 -> 1219.92 | AJ16: =+AJ48 -> 2728.18 | AK16: =SUM(F16:I16) -> 2146.2 | AL16: =SUM(J16:M16) -> 5839.704 | AM16: =SUM(N16:Q16) -> 4009.824 | AN16: =SUM(R16:U16) -> 1085.6268 | AO16: =SUM(V16:Y16) -> 651.37608
A17: 800G | B17: =+B49+B51 -> 0 | C17: =+C49+C51 -> 0 | D17: =+D49+D51 -> 0 | E17: =+E49+E51 -> 0 | F17: =+F49+F51 -> 0 | G17: =+G49+G51 -> 551.15 | H17: =+H49+H51 -> 1846.17 | I17: =+I49+I51 -> 2525.8 | J17: =+J49+J51+J50 -> 3455.09 | K17: =+K49+K51+K50 -> 3942 | L17: =+L49+L51+L50 -> 4284 | M17: =+M49+M51+M50 -> 4032 | N17: =+N49+N51+N50 -> 4253.0312 | O17: =+O49+O51+O50 -> 6083.82 | P17: =+P49+P51+P50 -> 6542.625 | Q17: =+Q49+Q51+Q50 -> 7079.175 | ... Y17: =+Y49+Y51+Y50 -> 2819.4163 | AF17: =+AF49 -> 0 | AG17: =+AG49 -> 0 | AH17: =+AH49 -> 0 | AI17: =+AI49 -> 0 | AJ17: =+AJ49 -> 0 | AK17: =SUM(F17:I17) -> 4923.12 | AL17: =SUM(J17:M17) -> 15713.09 | AM17: =SUM(N17:Q17) -> 23958.651 | AN17: =SUM(R17:U17) -> 30152.796 | AO17: =SUM(V17:Y17) -> 18369.317
A18: 1.6T | B18: =+B52+B53 -> 0 | C18: =+C52+C53 -> 0 | D18: =+D52+D53 -> 0 | E18: =+E52+E53 -> 0 | F18: =+F52+F53 -> 0 | G18: =+G52+G53 -> 0 | H18: =+H52+H53 -> 0 | I18: =+I52+I53 -> 0 | ... Y18: =+Y52+Y53 -> 11991.007 | AF18: =+AF52 -> 0 | AG18: =+AG52 -> 0 | AH18: =+AH52 -> 0 | AI18: =+AI52 -> 0 | AJ18: =+AJ52 -> 0 | AK18: =SUM(F18:I18) -> 0 | AL18: =SUM(J18:M18) -> 299.25 | AM18: =SUM(N18:Q18) -> 5198.875 | AN18: =SUM(R18:U18) -> 17570.37 | AO18: =SUM(V18:Y18) -> 38710.668
A19: 3.2T | X19: =+X54 -> 700.8 | Y19: =+Y54 -> 1401.6 | AO19: =+AO54 -> 2102.4
A20: Components/others | B20: =+B12-SUM(B13:B18) -> 85.71265 | C20: =+C12-SUM(C13:C18) -> 57.611181 | D20: =+D12-SUM(D13:D18) -> 36.065039 | E20: =+E12-SUM(E13:E18) -> 48.193397 | F20: =+F12-SUM(F13:F18) -> 45.467431 | G20: =+G12-SUM(G13:G18) -> 46.316435 | H20: =+H12-SUM(H13:H18) -> 38.30449 | I20: =+I12-SUM(I13:I18) -> 20.171112 | J20: =+J12-J13-J14-J15-J16-J17 -> 40.45387 | K20: =+K12-K13-K14-K15-K16-K17 -> 41.580207 | L20: =+L12-L13-L14-L15-L16-L17-L18 -> 49.546802 | M20: =+M12-M13-M14-M15-M16-M17-M18 -> 37.847085 | N20: =+N12-N13-N14-N15-N16-N17-N18 -> 66.439237 | O20: =+O12-O13-O14-O15-O16-O17-O18 -> 63.233399 | P20: =+L20*(1+P30) -> 49.546802 | Q20: =+M20*(1+Q30) -> 37.847085 | R20: =+N20*(1+R30) -> 66.439237 | S20: =+O20*(1+S30) -> 63.233399 | T20: =+P20*(1+T30) -> 49.546802 | U20: =+Q20*(1+U30) -> 37.847085 | V20: =+R20*(1+V30) -> 66.439237 | W20: =+S20*(1+W30) -> 63.233399 | ... Y20: =+U20*(1+Y30) -> 37.847085 | AF20: =+AF12-SUM(AF13:AF18) -> 158.42143 | AG20: =+AG12-SUM(AG13:AG18) -> 127.24437 | AH20: =+AH12-SUM(AH13:AH18) -> 539.67486 | AI20: =+AI12-SUM(AI13:AI18) -> 434.50441 | AJ20: =+AJ12-SUM(AJ13:AJ18) -> 229.06559 | AK20: =SUM(F20:I20) -> 150.25947 | AL20: =SUM(J20:M20) -> 169.42796 | AM20: =SUM(N20:Q20) -> 217.06652 | AN20: =SUM(R20:U20) -> 217.06652 | AO20: =SUM(V20:Y20) -> 217.06652
A22: Revenue YoY | F22: =+F12/B12-1 -> -0.12039486 | G22: =+G12/C12-1 -> 0.011387512 | H22: =+H12/D12-1 -> 0.14896469 | I22: =+I12/E12-1 -> 0.32803423 | J22: =+J12/F12-1 -> 1.6358828 | K22: =+K12/G12-1 -> 1.7487529 | L22: =+L12/H12-1 -> 1.1524594 | M22: =+M12/I12-1 -> 0.77605781 | ... Y22: =+Y12/U12-1 -> 0.16115786 | AG22: =+AG12/AF12-1 -> -0.077310497 | AH22: =+AH12/AG12-1 -> 0.48172944 | AI22: =+AI12/AH12-1 -> 0.091610245 | AJ22: =+AJ12/AI12-1 -> 0.25292886 | AK22: =+AK12/AJ12-1 -> 0.11161716 | AL22: =+AL12/AK12-1 -> 1.2263663 | AM22: =+AM12/AL12-1 -> 0.46851572 | AN22: =+AN12/AM12-1 -> 0.44348709 | AO22: =+AO12/AN12-1 -> 0.21404138
A23: 10G/40G | F23: =+F13/B13-1 -> -0.0375 | G23: =+G13/C13-1 -> -0.022222222 | H23: =+H13/D13-1 -> -0.14444444 | I23: =+I13/E13-1 -> 0.11514493 | J23: =+J13/F13-1 -> 0.1 | K23: =+K13/G13-1 -> -0.0375 | L23: =+L13/H13-1 -> 0.1 | M23: =+M13/I13-1 -> 0.10078628 | ... Y23: =+Y13/U13-1 -> -0.27272727 | AG23: =+AG13/AF13-1 -> -0.17531764 | AH23: =+AH13/AG13-1 -> -0.51294197 | AI23: =+AI13/AH13-1 -> 0.78843568 | AJ23: =+AJ13/AI13-1 -> -0.25714232 | AK23: =+AK13/AJ13-1 -> -0.02840442 | AL23: =+AL13/AK13-1 -> 0.062252112 | AM23: =+AM13/AL13-1 -> -0.14285714 | AN23: =+AN13/AM13-1 -> -0.083333333 | AO23: =+AO13/AN13-1 -> -0.27272727
A24: 100G | F24: =+F14/B14-1 -> -0.3065 | G24: =+G14/C14-1 -> -0.38080357 | H24: =+H14/D14-1 -> -0.76689076 | I24: =+I14/E14-1 -> -0.63974026 | J24: =+J14/F14-1 -> -0.74553571 | K24: =+K14/G14-1 -> -0.715 | L24: =+L14/H14-1 -> -0.31678082 | M24: =+M14/I14-1 -> -0.31678082 | ... Y24: =+Y14/U14-1 -> -0.05 | AG24: =+AG14/AF14-1 -> -0.039617191 | AH24: =+AH14/AG14-1 -> 0.58466006 | AI24: =+AI14/AH14-1 -> -0.27425163 | AJ24: =+AJ14/AI14-1 -> 0.044251123 | AK24: =+AK14/AJ14-1 -> -0.51785238 | AL24: =+AL14/AK14-1 -> -0.61761118 | AM24: =+AM14/AL14-1 -> -0.031730769 | AN24: =+AN14/AM14-1 -> -0.048370497 | AO24: =+AO14/AN14-1 -> -0.05
A25: 200G | F25: =+F15/B15-1 -> 0.16204082 | G25: =+G15/C15-1 -> -0.43685714 | H25: =+H15/D15-1 -> -0.81228571 | I25: =+I15/E15-1 -> -0.83436975 | J25: =+J15/F15-1 -> -0.79230769 | K25: =+K15/G15-1 -> -0.64 | L25: =+L15/H15-1 -> 0.15068493 | M25: =+M15/I15-1 -> 0.15068493 | ... Y25: =+Y15/U15-1 -> -0.05 | AG25: 0 | AH25: 0 | AI25: =+AI15/AH15-1 -> 31.777778 | AJ25: =+AJ15/AI15-1 -> 0.6889332 | AK25: =+AK15/AJ15-1 -> -0.54777922 | AL25: =+AL15/AK15-1 -> -0.53569398 | AM25: =+AM15/AL15-1 -> -0.16756012 | AN25: =+AN15/AM15-1 -> -0.048370497 | AO25: =+AO15/AN15-1 -> -0.05
A26: 400G | F26: =+F16/B16-1 -> 0.26346154 | G26: =+G16/C16-1 -> 0.26346154 | H26: =+H16/D16-1 -> -0.15769231 | I26: =+I16/E16-1 -> -0.51799274 | J26: =+J16/F16-1 -> 0.94285714 | K26: =+K16/G16-1 -> 2.3028571 | L26: =+L16/H16-1 -> 1.7945205 | M26: =+M16/I16-1 -> 1.7945205 | ... Y26: =+Y16/U16-1 -> -0.1 | AG26: 0 | AH26: 0 | AI26: =+AI16/AH16-1 -> 3.485 | AJ26: =+AJ16/AI16-1 -> 1.2363598 | AK26: =+AK16/AJ16-1 -> -0.2133217 | AL26: =+AL16/AK16-1 -> 1.7209505 | AM26: =+AM16/AL16-1 -> -0.3133515 | AN26: =+AN16/AM16-1 -> -0.72925824 | AO26: =+AO16/AN16-1 -> -0.4
A27: 800G | F27: 0 | G27: 0 | H27: 0 | I27: 0 | J27: =+J17/F17-1 -> #DIV/0! | K27: =+K17/G17-1 -> 6.1523179 | L27: =+L17/H17-1 -> 1.3204797 | M27: =+M17/I17-1 -> 0.59632592 | N27: =+N17/J17-1 -> 0.23094659 | O27: =+O17/K17-1 -> 0.54333333 | P27: =+P17/L17-1 -> 0.52722339 | Q27: =+Q17/M17-1 -> 0.75574777 | ... Y27: =+Y17/U17-1 -> -0.66069028 | AG27: 0 | AH27: 0 | AI27: 0 | AJ27: 0 | AK27: 0 | AL27: =+AL17/AK17-1 -> 2.1916935 | AM27: =+AM17/AL17-1 -> 0.52475746 | AN27: =+AN17/AM17-1 -> 0.25853479 | AO27: =+AO17/AN17-1 -> -0.39079225
A28: 1.6T | F28: 0 | G28: 0 | H28: 0 | I28: 0 | J28: 0 | K28: 0 | L28: 0 | M28: 0 | N28: 0 | O28: 0 | P28: 0 | Q28: 0 | R28: =+R18/N18-1 -> 7.1558621 | S28: =+S18/O18-1 -> 11.490526 | T28: =+T18/P18-1 -> 1.8381053 | U28: =+U18/Q18-1 -> 0.98631579 | V28: =+V18/R18-1 -> 1.1145614 | W28: =+W18/S18-1 -> 1.2431232 | X28: =+X18/T18-1 -> 1.248802 | Y28: =+Y18/U18-1 -> 1.1762106 | AG28: 0 | AH28: 0 | AI28: 0 | AJ28: 0 | AK28: 0 | AL28: 0 | AM28: =+AM18/AL18-1 -> 16.373016 | AN28: =+AN18/AM18-1 -> 2.3796485 | AO28: =+AO18/AN18-1 -> 1.2031789
A29: 3.2T | AO29: 0
A30: Components | F30: =+F20/B20-1 -> -0.46953651 | G30: =+G20/C20-1 -> -0.19605129 | H30: 0 | I30: 0 | J30: 0 | K30: 0 | L30: 0 | M30: 0 | N30: 0 | O30: 0 | P30: 0 | Q30: 0 | R30: 0 | S30: 0 | T30: 0 | U30: 0 | V30: 0 | W30: 0 | X30: 0 | Y30: 0 | AG30: =+AG20/AF20-1 -> -0.19679829 | AH30: =+AH20/AG20-1 -> 3.2412476 | AI30: =+AI20/AH20-1 -> -0.19487743 | AJ30: =+AJ20/AI20-1 -> -0.47281182 | AK30: =+AK20/AJ20-1 -> -0.344033 | AL30: =+AL20/AK20-1 -> 0.12756931 | AM30: =+AM20/AL20-1 -> 0.28117294 | AN30: =+AN20/AM20-1 -> 0 | AO30: =+AO20/AN20-1 -> 0
A32: Revenue mix (%) | B32: =SUM(B33:B40) -> 1 | C32: =SUM(C33:C40) -> 1 | D32: =SUM(D33:D40) -> 1 | E32: =SUM(E33:E40) -> 1 | F32: =SUM(F33:F40) -> 1 | G32: =SUM(G33:G40) -> 1 | H32: =SUM(H33:H40) -> 1 | I32: =SUM(I33:I40) -> 1 | ... Y32: =SUM(Y33:Y40) -> 0.91633415 | AF32: =SUM(AF33:AF40) -> 1 | AG32: =SUM(AG33:AG40) -> 1 | AH32: =SUM(AH33:AH40) -> 1 | AI32: =SUM(AI33:AI40) -> 1 | AJ32: =SUM(AJ33:AJ40) -> 1 | AK32: =SUM(AK33:AK40) -> 1 | AL32: =SUM(AL33:AL40) -> 1 | AM32: =SUM(AM33:AM40) -> 1 | ... AO32: =SUM(AO33:AO40) -> 1
A33: 10G/40G | B33: =+B13/B$12 -> 0.077754591 | C33: =+C13/C$12 -> 0.08527735 | D33: =+D13/D$12 -> 0.069363651 | E33: =+E13/E$12 -> 0.050442837 | F33: =+F13/F$12 -> 0.085082261 | G33: =+G13/G$12 -> 0.082443471 | H33: =+H13/H$12 -> 0.051650375 | I33: =+I13/I$12 -> 0.042356645 | ... Y33: =+Y13/Y$12 -> 0.0058649668 | AF33: =+AF13/AF$12 -> 0.24218128 | AG33: =+AG13/AG$12 -> 0.21645703 | AH33: =+AH13/AH$12 -> 0.071151408 | AI33: =+AI13/AI$12 -> 0.11657065 | AJ33: =+AJ13/AJ$12 -> 0.069114381 | AK33: =+AK13/AK$12 -> 0.060408592 | AL33: =+AL13/AL$12 -> 0.02882237 | AM33: =+AM13/AM$12 -> 0.016823033 | ... AO33: =+AO13/AO$12 -> 0.0063998036
A34: 100G | B34: =+B14/B$12 -> 0.55209111 | C34: =+C14/C$12 -> 0.5382275 | D34: =+D14/D$12 -> 0.46515005 | E34: =+E14/E$12 -> 0.28549455 | F34: =+F14/F$12 -> 0.43528075 | G34: =+G14/G$12 -> 0.32951618 | H34: =+H14/H$12 -> 0.094372592 | I34: =+I14/I$12 -> 0.077446944 | ... Y34: =+Y14/Y$12 -> 0.010414514 | AF34: =+AF14/AF$12 -> 0.72709494 | AG34: =+AG14/AG$12 -> 0.7567979 | AH34: =+AH14/AH$12 -> 0.80937003 | AI34: =+AI14/AI$12 -> 0.53810321 | AJ34: =+AJ14/AJ$12 -> 0.44848108 | AK34: =+AK14/AK$12 -> 0.19452208 | AL34: =+AL14/AL$12 -> 0.033410076 | AM34: =+AM14/AM$12 -> 0.022029011 | ... AO34: =+AO14/AO$12 -> 0.011364232
A35: 200G | B35: =+B15/B$12 -> 0.15483888 | C35: =+C15/C$12 -> 0.17970323 | D35: =+D15/D$12 -> 0.17540233 | E35: =+E15/E$12 -> 0.18856193 | F35: =+F15/F$12 -> 0.20455668 | G35: =+G15/G$12 -> 0.10005916 | H35: =+H15/H$12 -> 0.028656689 | I35: =+I15/I$12 -> 0.023517135 | ... Y35: =+Y15/Y$12 -> 0.0039946321 | AF35: =+AF15/AF$12 -> 0 | AG35: =+AG15/AG$12 -> 0 | AH35: =+AH15/AH$12 -> 0.0043406779 | AI35: =+AI15/AI$12 -> 0.13033752 | AJ35: =+AJ15/AJ$12 -> 0.17569343 | AK35: =+AK15/AK$12 -> 0.071474446 | AL35: =+AL15/AL$12 -> 0.01490591 | AM35: =+AM15/AM$12 -> 0.0084495342 | ... AO35: =+AO15/AO$12 -> 0.0043589097
A36: 400G | B36: =+B16/B$12 -> 0.17427753 | C36: =+C16/C$12 -> 0.16990123 | D36: =+D16/D$12 -> 0.27639156 | E36: =+E16/E$12 -> 0.45814499 | F36: =+F16/F$12 -> 0.2503316 | G36: =+G16/G$12 -> 0.21224671 | H36: =+H16/H$12 -> 0.20262305 | I36: =+I16/I$12 -> 0.16628277 | ... Y36: =+Y16/Y$12 -> 0.009720665 | AF36: =+AF16/AF$12 -> 0 | AG36: =+AG16/AG$12 -> 0 | AH36: =+AH16/AH$12 -> 0.038583803 | AI36: =+AI16/AI$12 -> 0.15852577 | AJ36: =+AJ16/AJ$12 -> 0.28295354 | AK36: =+AK16/AK$12 -> 0.20024287 | AL36: =+AL16/AL$12 -> 0.24472655 | AM36: =+AM16/AM$12 -> 0.11442923 | ... AO36: =+AO16/AO$12 -> 0.01060711
A37: 800G | B37: =+B17/B$12 -> 0 | C37: =+C17/C$12 -> 0 | D37: =+D17/D$12 -> 0 | E37: =+E17/E$12 -> 0 | F37: =+F17/F$12 -> 0 | G37: =+G17/G$12 -> 0.25435915 | H37: =+H17/H$12 -> 0.61004013 | I37: =+I17/I$12 -> 0.68492666 | ... Y37: =+Y17/Y$12 -> 0.16829971 | AF37: =+AF17/AF$12 -> 0 | AG37: =+AG17/AG$12 -> 0 | AH37: =+AH17/AH$12 -> 0 | AI37: =+AI17/AI$12 -> 0 | AJ37: =+AJ17/AJ$12 -> 0 | AK37: =+AK17/AK$12 -> 0.45933263 | AL37: =+AL17/AL$12 -> 0.65849404 | AM37: =+AM17/AM$12 -> 0.68371328 | ... AO37: =+AO17/AO$12 -> 0.29912882
A38: 1.6T | B38: =+B18/B$12 -> 0 | C38: =+C18/C$12 -> 0 | D38: =+D18/D$12 -> 0 | E38: =+E18/E$12 -> 0 | F38: =+F18/F$12 -> 0 | G38: =+G18/G$12 -> 0 | H38: =+H18/H$12 -> 0 | I38: =+I18/I$12 -> 0 | ... Y38: =+Y18/Y$12 -> 0.71578045 | AF38: =+AF18/AF$12 -> 0 | AG38: =+AG18/AG$12 -> 0 | AH38: =+AH18/AH$12 -> 0 | AI38: =+AI18/AI$12 -> 0 | AJ38: =+AJ18/AJ$12 -> 0 | AK38: =+AK18/AK$12 -> 0 | AL38: =+AL18/AL$12 -> 0.012540776 | AM38: =+AM18/AM$12 -> 0.14836144 | ... AO38: =+AO18/AO$12 -> 0.63037056
A39: 3.2T | AO39: =+AO19/AO$12 -> 0.03423581
A40: Components | B40: =+B20/B$12 -> 0.041037882 | C40: =+C20/C$12 -> 0.026890688 | D40: =+D20/D$12 -> 0.013692407 | E40: =+E20/E$12 -> 0.017355691 | F40: =+F20/F$12 -> 0.024748716 | G40: =+G20/G$12 -> 0.021375323 | H40: =+H20/H$12 -> 0.012657164 | I40: =+I20/I$12 -> 0.0054698441 | ... Y40: =+Y20/Y$12 -> 0.00225921 | AF40: =+AF20/AF$12 -> 0.030723774 | AG40: =+AG20/AG$12 -> 0.026745062 | AH40: =+AH20/AH$12 -> 0.076554077 | AI40: =+AI20/AI$12 -> 0.056462841 | AJ40: =+AJ20/AJ$12 -> 0.023757567 | AK40: =+AK20/AK$12 -> 0.014019377 | AL40: =+AL20/AL$12 -> 0.0071002779 | AM40: =+AM20/AM$12 -> 0.006194475 | ... AO40: =+AO20/AO$12 -> 0.0035347452
A43: Optical transceivers | AJ43: 2022 | AK43: 2023 | AL43: 2024 | AM43: 2025E | AN43: 2026E | AO43: =+AO3 -> 2027E
A44: Revenue by specs (Rmb mn) | B44: =+SUM(B45:B53) -> 2002.91 | C44: =+SUM(C45:C53) -> 2084.81 | D44: =+SUM(D45:D53) -> 2597.8794 | E44: =+SUM(E45:E53) -> 2728.6131 | F44: =+SUM(F45:F53) -> 1791.6958 | G44: =+SUM(G45:G53) -> 2120.5016 | H44: =+SUM(H45:H53) -> 2988.0046 | I44: =+SUM(I45:I53) -> 3667.523 | ... Y44: =+SUM(Y45:Y53) -> 15312.907 | AF44: =+SUM(AF45:AF52) -> 4997.8928 | AG44: =+SUM(AG45:AG52) -> 4630.4327 | AH44: =+SUM(AH45:AH52) -> 6509.9153 | AI44: =+SUM(AI45:AI52) -> 7260.9004 | AJ44: =+SUM(AJ45:AJ52) -> 9412.7292 | AK44: =+SUM(AK45:AK53) -> 10567.725 | AL44: =+SUM(AL45:AL53) -> 23692.732 | AM44: =+SUM(AM45:AM53) -> 34824.89 | AN44: =+SUM(AN45:AN53) -> 50365.546 | AO44: =+SUM(AO45:AO54) -> 61192.318
A45: 10G/40G | B45: =+B60*B106 -> 162.4 | C45: =+C60*C106 -> 182.7 | D45: =+D60*D106 -> 182.7 | E45: =+E60*E106 -> 140.07 | F45: =+F60*F106 -> 156.31 | G45: =+G60*G106 -> 178.64 | H45: =+H60*H106 -> 156.31 | I45: =+I60*I106 -> 156.19835 | ... Y45: =+Y60*Y106 -> 98.252 | AF45: =+AF119 -> 1248.7628 | AG45: =+AG119 -> 1029.8327 | AH45: =+AH119 -> 501.58826 | AI45: =+AI119 -> 897.05834 | AJ45: =+AJ119 -> 666.38668 | AK45: =SUM(F45:I45) -> 647.45835 | AL45: =SUM(J45:M45) -> 687.764 | AM45: =SUM(N45:Q45) -> 589.512 | AN45: =SUM(R45:U45) -> 540.386 | AO45: =SUM(V45:Y45) -> 393.008
A46: 100G | B46: =+B61*B107 -> 1153.11 | C46: =+C61*C107 -> 1153.11 | D46: =+D61*D107 -> 1225.1794 | E46: =+E61*E107 -> 792.76312 | F46: =+F61*F107 -> 799.68178 | G46: =+G61*G107 -> 714.00159 | H46: =+H61*H107 -> 285.60064 | I46: =+I61*I107 -> 285.60064 | ... Y46: =+Y61*Y107 -> 174.46763 | AF46: =+AF61*AF107 -> 3749.13 | AG46: =+AG61*AG107 -> 3600.6 | AH46: =+AH61*AH107 -> 5705.727 | AI46: =+AI61*AI107 -> 4140.922 | AJ46: =SUM(B46:E46) -> 4324.1625 | AK46: =SUM(F46:I46) -> 2084.8847 | AL46: =SUM(J46:M46) -> 797.23657 | AM46: =SUM(N46:Q46) -> 771.93964 | AN46: =SUM(R46:U46) -> 734.60054 | AO46: =SUM(V46:Y46) -> 697.87051
A47: 200G | B47: =+B62*B108 -> 323.4 | C47: =+C62*C108 -> 385 | D47: =+D62*D108 -> 462 | E47: =+E62*E108 -> 523.6 | F47: =+F62*F108 -> 375.804 | G47: =+G62*G108 -> 216.81 | H47: =+H62*H108 -> 86.724 | I47: =+I62*I108 -> 86.724 | ... Y47: =+Y62*Y108 -> 66.919491 | AF47: =+AF62*AF108 -> 0 | AG47: =+AG62*AG108 -> 0 | AH47: =+AH62*AH108 -> 30.6 | AI47: =+AI62*AI108 -> 1003 | AJ47: =SUM(B47:E47) -> 1694 | AK47: =SUM(F47:I47) -> 766.062 | AL47: =SUM(J47:M47) -> 355.6872 | AM47: =SUM(N47:Q47) -> 296.08821 | AN47: =SUM(R47:U47) -> 281.76628 | AO47: =SUM(V47:Y47) -> 267.67796
A48: 400G | B48: =+B63*B109 -> 364 | C48: =+C63*C109 -> 364 | D48: =+D63*D109 -> 728 | E48: =+E63*E109 -> 1272.18 | F48: =+F63*F109 -> 459.9 | G48: =+G63*G109 -> 459.9 | H48: =+H63*H109 -> 613.2 | I48: =+I63*I109 -> 613.2 | ... N48: =+N63*N109 -> 1597.32 | O48: =+O63*O109-O188 -> 1206.252 | P48: =+P63*P109-P188 -> 804.168 | Q48: =+Q63*Q109-Q188 -> 402.084 | R48: =+R63*R109-R188 -> 361.8756 | S48: =+S63*S109-S188 -> 361.8756 | T48: =+T63*T109-T188 -> 180.9378 | U48: =+U63*U109-U188 -> 180.9378 | V48: =+V63*V109-V188 -> 162.84402 | ... Y48: =+Y63*Y109-Y188 -> 162.84402 | AF48: =+AF63*AF109 -> 0 | AG48: =+AG63*AG109 -> 0 | AH48: =+AH63*AH109 -> 272 | AI48: =+AI63*AI109 -> 1219.92 | AJ48: =+AJ63*AJ109 -> 2728.18 | AK48: =SUM(F48:I48) -> 2146.2 | AL48: =SUM(J48:M48) -> 5839.704 | AM48: =SUM(N48:Q48) -> 4009.824 | AN48: =SUM(R48:U48) -> 1085.6268 | AO48: =SUM(V48:Y48) -> 651.37608
A49: 800G single mode (EML) | B49: =+B64*B110 -> 0 | C49: =+C64*C110 -> 0 | D49: =+D64*D110 -> 0 | E49: =+E64*E110 -> 0 | F49: =+F64*F110 -> 0 | G49: =+G64*G110 -> 321.2 | H49: =+H64*H110 -> 1156.32 | I49: =+I64*I110 -> 1606 | ... N49: =+N64*N110 -> 3099.375 | O49: =+O64*O110-O189 -> 2792.25 | P49: =+P64*P110-P189 -> 2978.4 | Q49: =+Q64*Q110-Q189 -> 3350.7 | R49: =+R64*R110-R189 -> 3611.31 | S49: =+S64*S110-S189 -> 3164.55 | T49: =+T64*T110-T189 -> 3164.55 | U49: =+U64*U110-U189 -> 3164.55 | V49: =+V64*V110-V189 -> 3101.259 | ... Y49: =+Y64*Y110-Y189 -> 1344.9337 | AF49: =+AF64*AF110 -> 0 | AG49: =+AG64*AG110 -> 0 | AH49: =+AH64*AH110 -> 0 | AI49: =+AI64*AI110 -> 0 | AJ49: =+AJ64*AJ110 -> 0 | AK49: =SUM(F49:I49) -> 3083.52 | AL49: =SUM(J49:M49) -> 10569.33 | AM49: =SUM(N49:Q49) -> 12220.725 | AN49: =SUM(R49:U49) -> 13104.96 | AO49: =SUM(V49:Y49) -> 8749.9808
A50: 800G single mode (SiPh) | L50: =+L65*L111 -> 0 | M50: =+M65*M111 -> 0 | N50: =+N65*N111 -> 378.8125 | O50: =+O65*O111-O190 -> 2956.5 | P50: =+P65*P111-P190 -> 3285 | Q50: =+Q65*Q111-Q190 -> 3449.25 | R50: =+R65*R111-R190 -> 3432.825 | S50: =+S65*S111-S190 -> 3629.925 | T50: =+T65*T111-T190 -> 4467.6 | U50: =+U65*U111-U190 -> 5026.05 | V50: =+V65*V111-V190 -> 3713.6925 | ... Y50: =+Y65*Y111-Y190 -> 1424.0475 | AK50: =SUM(F50:I50) -> 0 | AL50: =SUM(J50:M50) -> 0 | AM50: =SUM(N50:Q50) -> 10069.562 | AN50: =SUM(R50:U50) -> 16556.4 | AO50: =SUM(V50:Y50) -> 9409.8825
A51: 800G multi mode | B51: =+B66*B112 -> 0 | C51: =+C66*C112 -> 0 | D51: =+D66*D112 -> 0 | E51: =+E66*E112 -> 0 | F51: =+F66*F112 -> 0 | G51: =+G66*G112 -> 229.95 | H51: =+H66*H112 -> 689.85 | I51: =+I66*I112 -> 919.8 | ... N51: =+N66*N112 -> 774.84375 | O51: =+O66*O112-O191 -> 335.07 | P51: =+P66*P112-P191 -> 279.225 | Q51: =+Q66*Q112-Q191 -> 279.225 | R51: =+R66*R112-R191 -> 135.42412 | S51: =+S66*S112-S191 -> 118.67063 | T51: =+T66*T112-T191 -> 118.67063 | U51: =+U66*U112-U191 -> 118.67063 | V51: =+V66*V112-V191 -> 58.148606 | ... Y51: =+Y66*Y112-Y191 -> 50.435016 | AK51: =SUM(F51:I51) -> 1839.6 | AL51: =SUM(J51:M51) -> 5143.76 | AM51: =SUM(N51:Q51) -> 1668.3637 | AN51: =SUM(R51:U51) -> 491.436 | AO51: =SUM(V51:Y51) -> 209.45365
A52: 1.6T long-range | B52: =+B67*B113 -> 0 | C52: =+C67*C113 -> 0 | D52: =+D67*D113 -> 0 | E52: =+E67*E113 -> 0 | F52: =+F67*F113 -> 0 | G52: =+G67*G113 -> 0 | H52: =+H67*H113 -> 0 | I52: =+I67*I113 -> 0 | ... N52: =+N67*N113 -> 0 | O52: =+O67*O113-O192 -> 0 | P52: =+P67*P113-P192 -> 0 | Q52: =+Q67*Q113-Q192 -> 0 | R52: =+R67*R113-R192 -> 0 | S52: =+S67*S113-S192 -> 794.24 | T52: =+T67*T113-T192 -> 794.24 | U52: =+U67*U113-U192 -> 794.24 | V52: =+V67*V113-V192 -> 1429.632 | ... Y52: =+Y67*Y113-Y192 -> 4725.728 | AF52: =+AF67*AF113 -> 0 | AG52: =+AG67*AG113 -> 0 | AH52: =+AH67*AH113 -> 0 | AI52: =+AI67*AI113 -> 0 | AJ52: =+AJ67*AJ113 -> 0 | AK52: =SUM(F52:I52) -> 0 | AL52: =SUM(J52:M52) -> 0 | AM52: =SUM(N52:Q52) -> 0 | AN52: =SUM(R52:U52) -> 2382.72 | AO52: =SUM(V52:Y52) -> 12906.4
A53: 1.6T short-range | B53: =+B68*B114 -> 0 | C53: =+C68*C114 -> 0 | D53: =+D68*D114 -> 0 | E53: =+E68*E114 -> 0 | F53: =+F68*F114 -> 0 | G53: =+G68*G114 -> 0 | H53: =+H68*H114 -> 0 | I53: =+I68*I114 -> 0 | ... N53: =+N68*N114 -> 344.375 | O53: =+O68*O114-O193 -> 346.75 | P53: =+P68*P114-P193 -> 1733.75 | Q53: =+Q68*Q114-Q193 -> 2774 | R53: =+R68*R114-R193 -> 2808.675 | S53: =+S68*S114-S193 -> 3536.85 | T53: =+T68*T114-T193 -> 4126.325 | U53: =+U68*U114-U193 -> 4715.8 | V53: =+V68*V114-V193 -> 4509.4837 | ... Y53: =+Y68*Y114-Y193 -> 7265.2794 | AK53: =SUM(F53:I53) -> 0 | AL53: =SUM(J53:M53) -> 299.25 | AM53: =SUM(N53:Q53) -> 5198.875 | AN53: =SUM(R53:U53) -> 15187.65 | AO53: =SUM(V53:Y53) -> 25804.268
A54: 3.2T | X54: =+X115*X69 -> 700.8 | Y54: =+Y115*Y69 -> 1401.6 | AO54: =SUM(V54:Y54) -> 2102.4
A56: Mix
A57: SiPh (800G+1.6T) | B57: =+(B50+B53)/B12 -> 0 | C57: =+(C50+C53)/C12 -> 0 | D57: =+(D50+D53)/D12 -> 0 | E57: =+(E50+E53)/E12 -> 0 | F57: =+(F50+F53)/F12 -> 0 | G57: =+(G50+G53)/G12 -> 0 | H57: =+(H50+H53)/H12 -> 0 | I57: =+(I50+I53)/I12 -> 0 | ... Y57: =+(Y50+Y53)/Y12 -> 0.51869289 | AF57: =+(AF50+AF53)/AF12 -> 0 | AG57: =+(AG50+AG53)/AG12 -> 0 | AH57: =+(AH50+AH53)/AH12 -> 0 | AI57: =+(AI50+AI53)/AI12 -> 0 | AJ57: =+(AJ50+AJ53)/AJ12 -> 0 | AK57: =+(AK50+AK53)/AK12 -> 0 | AL57: =+(AL50+AL53)/AL12 -> 0.012540776 | AM57: =+(AM50+AM53)/AM12 -> 0.43571875 | ... AO57: =+(AO50+AO53)/AO12 -> 0.57343273
A59: Shipments (mn)
A60: 10G/40G | B60: 0.8 | C60: 0.9 | D60: 0.9 | E60: 0.69 | F60: 0.7 | G60: 0.8 | H60: 0.7 | I60: 0.6995 | J60: 0.7 | K60: 0.7 | L60: 0.7 | M60: 0.7 | N60: 0.6 | O60: 0.6 | P60: 0.6 | Q60: 0.6 | R60: 0.6 | S60: 0.55 | T60: 0.5 | U60: 0.55 | V60: 0.4 | W60: 0.4 | X60: 0.4 | Y60: 0.4 | AF60: =+AF45/AF106 -> 11.149668 | AG60: =+AG45/AG106 -> 9.1949344 | AH60: 4.47 | AI60: 5.64 | AJ60: =SUM(B60:E60) -> 3.29 | AK60: =SUM(F60:I60) -> 2.8995 | AL60: =SUM(J60:M60) -> 2.8 | AM60: =SUM(N60:Q60) -> 2.4 | AN60: =SUM(R60:U60) -> 2.2 | AO60: =SUM(V60:Y60) -> 1.6
A61: 100G | B61: 1.4324348 | C61: 1.4324348 | D61: 1.521962 | E61: 0.98479891 | F61: 1.6350067 | G61: 1.4598274 | H61: 0.58393097 | I61: 0.58393097 | J61: 0.4355532 | K61: 0.4355532 | L61: 0.4355532 | M61: 0.4355532 | N61: 0.43412515 | O61: 0.43412515 | P61: 0.43412515 | Q61: 0.43412515 | R61: 0.43375091 | S61: 0.43375091 | T61: 0.43375091 | U61: 0.43375091 | V61: 0.43453955 | W61: 0.43453955 | X61: 0.43453955 | Y61: 0.43453955 | AF61: 1.623 | AG61: 1.765 | AH61: 3.2905 | AI61: 2.8095 | AJ61: =SUM(B61:E61) -> 5.3716304 | AK61: =SUM(F61:I61) -> 4.2626961 | AL61: =SUM(J61:M61) -> 1.7422128 | AM61: =SUM(N61:Q61) -> 1.7365006 | AN61: =SUM(R61:U61) -> 1.7350036 | AO61: =SUM(V61:Y61) -> 1.7381582
A62: 200G | B62: 0.219 | C62: 0.26071429 | D62: 0.31285714 | E62: 0.35457143 | F62: 0.286 | G62: 0.165 | H62: 0.066 | I62: 0.066 | J62: 0.066 | K62: 0.066 | L62: 0.088 | M62: 0.088 | N62: 0.069666667 | O62: 0.069666667 | P62: 0.069666667 | Q62: 0.069666667 | R62: 0.069666667 | S62: 0.069666667 | T62: 0.069666667 | U62: 0.069666667 | V62: 0.069666667 | W62: 0.069666667 | X62: 0.069666667 | Y62: 0.069666667 | AF62: 0 | AG62: 0 | AH62: 0.015 | AI62: 0.59 | AJ62: =SUM(B62:E62) -> 1.1471429 | AK62: =SUM(F62:I62) -> 0.583 | AL62: =SUM(J62:M62) -> 0.308 | AM62: =SUM(N62:Q62) -> 0.27866667 | AN62: =SUM(R62:U62) -> 0.27866667 | AO62: =SUM(V62:Y62) -> 0.27866667
A63: 400G | B63: 0.1 | C63: 0.1 | D63: 0.2 | E63: 0.3495 | F63: 0.15 | G63: 0.15 | H63: 0.2 | I63: 0.2 | J63: 0.4 | K63: 0.68 | L63: 0.8 | M63: 0.8 | N63: 0.8 | O63: 0.6 | P63: 0.4 | Q63: 0.2 | R63: 0.2 | S63: 0.2 | T63: 0.1 | U63: 0.1 | V63: 0.1 | W63: 0.1 | X63: 0.1 | Y63: 0.1 | AF63: 0 | AG63: 0 | AH63: 0.05 | AI63: 0.276 | AJ63: =SUM(B63:E63) -> 0.7495 | AK63: =SUM(F63:I63) -> 0.7 | AL63: =SUM(J63:M63) -> 2.68 | AM63: =SUM(N63:Q63) -> 2 | AN63: =SUM(R63:U63) -> 0.6 | AO63: =SUM(V63:Y63) -> 0.4
A64: 800G single mode (EML) | B64: 0 | C64: 0 | D64: 0 | E64: 0 | F64: 0 | G64: 0.05 | H64: 0.18 | I64: 0.25 | J64: 0.3 | K64: 0.6 | L64: 0.72 | M64: 0.75 | N64: 0.75 | O64: 0.75 | P64: 0.8 | Q64: 0.9 | R64: 1 | S64: 1 | T64: 1 | U64: 1 | V64: 1 | W64: 0.9 | X64: 0.7 | Y64: 0.5 | AF64: 0 | AG64: 0 | AH64: 0 | AI64: 0 | AJ64: =SUM(B64:E64) -> 0 | AK64: =SUM(F64:I64) -> 0.48 | AL64: =SUM(J64:M64) -> 2.37 | AM64: =SUM(N64:Q64) -> 3.2 | AN64: =SUM(R64:U64) -> 4 | AO64: =SUM(V64:Y64) -> 3.1
A65: 800G single mode (SiPh) | F65: 0 | G65: 0 | H65: 0 | I65: 0 | J65: 0 | K65: 0 | L65: 0 | M65: 0 | N65: 0.11 | O65: 0.9 | P65: 1 | Q65: 1.05 | R65: 1.1 | S65: 1.3 | T65: 1.6 | U65: 1.8 | V65: 1.4 | W65: 1 | X65: 0.8 | Y65: 0.6 | AL65: =SUM(J65:M65) -> 0 | AM65: =SUM(N65:Q65) -> 3.06 | AN65: =SUM(R65:U65) -> 5.8 | AO65: =SUM(V65:Y65) -> 3.8
A66: 800G multi mode | F66: 0 | G66: 0.05 | H66: 0.15 | I66: 0.2 | J66: 0.4 | K66: 0.4 | L66: 0.4 | M66: 0.28 | N66: 0.25 | O66: 0.12 | P66: 0.1 | Q66: 0.1 | R66: 0.05 | S66: 0.05 | T66: 0.05 | U66: 0.05 | V66: 0.025 | W66: 0.025 | X66: 0.025 | Y66: 0.025 | AK66: =SUM(F66:I66) -> 0.4 | AL66: =SUM(J66:M66) -> 1.48 | AM66: =SUM(N66:Q66) -> 0.57 | AN66: =SUM(R66:U66) -> 0.2 | AO66: =SUM(V66:Y66) -> 0.1
A67: 1.6T long-range | B67: 0 | C67: 0 | D67: 0 | E67: 0 | F67: 0 | G67: 0 | H67: 0 | I67: 0 | J67: 0 | K67: 0 | L67: 0 | M67: 0 | N67: 0 | O67: 0 | P67: 0 | Q67: 0 | R67: 0 | S67: 0.1 | T67: 0.1 | U67: 0.1 | V67: 0.2 | W67: 0.4 | X67: 0.6 | Y67: 0.7 | AF67: 0 | AG67: 0 | AH67: 0 | AI67: 0 | AJ67: =SUM(B67:E67) -> 0 | AK67: =SUM(F67:I67) -> 0 | AL67: =SUM(J67:M67) -> 0 | AM67: =SUM(N67:Q67) -> 0 | AN67: =SUM(R67:U67) -> 0.3 | AO67: =SUM(V67:Y67) -> 1.9
A68: 1.6T short-range SiPh | B68: 0 | C68: 0 | D68: 0 | E68: 0 | F68: 0 | G68: 0 | H68: 0 | I68: 0 | J68: 0 | K68: 0 | L68: 0 | M68: 0.045 | N68: 0.05 | O68: 0.05 | P68: 0.25 | Q68: 0.4 | R68: 0.45 | S68: 0.6 | T68: 0.7 | U68: 0.8 | V68: 0.85 | W68: 1.4 | X68: 1.4 | Y68: 1.45 | AF68: 0 | AG68: 0 | AH68: 0 | AI68: 0 | AJ68: =SUM(B68:E68) -> 0 | AK68: =SUM(F68:I68) -> 0 | AL68: =SUM(J68:M68) -> 0.045 | AM68: =SUM(N68:Q68) -> 0.75 | AN68: =SUM(R68:U68) -> 2.55 | AO68: =SUM(V68:Y68) -> 5.1
A69: 3.2T | X69: 0.05 | Y69: 0.1 | AO69: =SUM(V69:Y69) -> 0.15
AM70: =+AM64+AM65+AM66 -> 6.83 | AN70: =+AN64+AN65+AN66 -> 10 | AO70: =+AO64+AO65+AO66 -> 7
A71: ASP (US$)(no tariff impact) | AM71: =+AM67+AM68 -> 0.75 | AN71: =+AN67+AN68 -> 2.85 | AO71: =+AO67+AO68 -> 7
A72: 10G/40G | B72: =+$AJ72 -> 27.746458 | C72: =+$AJ72 -> 27.746458 | D72: =+$AJ72 -> 27.746458 | E72: =+$AJ72 -> 27.746458 | F72: =+$AK72 -> 30.589041 | G72: =+$AK72 -> 30.589041 | H72: =+$AK72 -> 30.589041 | I72: =+$AK72 -> 30.589041 | J72: =+$AL72 -> 33.647945 | K72: =+$AL72 -> 33.647945 | L72: =+$AL72 -> 33.647945 | M72: =+$AL72 -> 33.647945 | N72: =+$AM72 -> 33.647945 | O72: =+$AM72 -> 33.647945 | P72: =+$AM72 -> 33.647945 | Q72: =+$AM72 -> 33.647945 | R72: =+$AN72 -> 33.647945 | S72: =+$AN72 -> 33.647945 | T72: =+$AN72 -> 33.647945 | U72: =+$AN72 -> 33.647945 | V72: =+$AO72 -> 33.647945 | W72: =+$AO72 -> 33.647945 | X72: =+$AO72 -> 33.647945 | Y72: =+$AO72 -> 33.647945 | AF72: =+AF106/7.3 -> 15.342466 | AG72: =+AG106/7.3 -> 15.342466 | AH72: =+AH106/7.3 -> 15.342466 | AI72: =+AI106/7.3 -> 21.780822 | AJ72: =+AJ106/7.3 -> 27.746458 | AK72: =+AK106/7.3 -> 30.589041 | AL72: =+AL106/7.3 -> 33.647945 | AM72: =+AM106/7.3 -> 33.647945 | ... AO72: =+AO106/7.3 -> 33.647945
A73: 100G | B73: 115 | C73: 115 | D73: 115 | E73: 115 | F73: 67 | G73: 67 | H73: 67 | I73: 67 | J73: 64 | K73: 64 | L73: 64 | M73: 64 | N73: 61 | O73: 61 | P73: 61 | Q73: 61 | R73: 58 | S73: 58 | T73: 58 | U73: 58 | V73: 55 | W73: 55 | X73: 55 | Y73: 55 | AF73: 350 | AG73: 300 | AH73: 255 | AI73: 216.75 | AJ73: =+AJ107/AJ103 -> 115 | AK73: =+AK107/7.3 -> 67 | AL73: =+AL107/7.3 -> 62.684932 | AM73: =+AM107/7.3 -> 60.895548 | AN73: =+AN107/7.3 -> 58 | AO73: =+AO107/7.3 -> 55
A74: 200G | B74: 210.9589 | C74: 210.9589 | D74: 210.9589 | E74: 210.9589 | F74: 180 | G74: 180 | H74: 180 | I74: 180 | J74: 162 | K74: 162 | L74: 162 | M74: 162 | N74: 145.8 | O74: 145.8 | P74: 145.8 | Q74: 145.8 | R74: 138.51 | S74: 138.51 | T74: 138.51 | U74: 138.51 | V74: 131.5845 | W74: 131.5845 | X74: 131.5845 | Y74: 131.5845 | AF74: 0 | AG74: 0 | AH74: 300 | AI74: 250 | AJ74: =+AJ108/AJ103 -> 210.9589 | AK74: =+AK108/AK103 -> 180 | AL74: =+AL108/AL103 -> 158.19569 | AM74: =+AM108/AM103 -> 145.55034 | AN74: =+AN108/AN103 -> 138.51 | AO74: =+AO108/AO103 -> 131.5845
A75: 400G | B75: =+$AJ75 -> 520 | C75: =+$AJ75 -> 520 | D75: =+$AJ75 -> 520 | E75: =+$AJ75 -> 520 | F75: =+$AK75 -> 420 | G75: =+$AK75 -> 420 | H75: =+$AK75 -> 420 | I75: =+$AK75 -> 420 | J75: =+$AL75 -> 306 | K75: =+$AL75 -> 306 | L75: =+$AL75 -> 306 | M75: =+$AL75 -> 306 | N75: =+$AM75 -> 275.4 | O75: =+$AM75 -> 275.4 | P75: =+$AM75 -> 275.4 | Q75: =+$AM75 -> 275.4 | R75: =+$AN75 -> 247.86 | S75: =+$AN75 -> 247.86 | T75: =+$AN75 -> 247.86 | U75: =+$AN75 -> 247.86 | V75: =+$AO75 -> 223.074 | W75: =+$AO75 -> 223.074 | X75: =+$AO75 -> 223.074 | Y75: =+$AO75 -> 223.074 | AF75: 0 | AG75: 0 | AH75: 800 | AI75: 650 | AJ75: 520 | AK75: 420 | AL75: 306 | AM75: 275.4 | AN75: 247.86 | AO75: 223.074
A76: 800G single mode (EML) | B76: =+$AJ76 -> 0 | C76: =+$AJ76 -> 0 | D76: =+$AJ76 -> 0 | E76: =+$AJ76 -> 0 | F76: =+$AK76 -> 880 | G76: =+$AK76 -> 880 | H76: =+$AK76 -> 880 | I76: =+$AK76 -> 880 | J76: 807 | K76: =+$AL76 -> 600 | L76: =+$AL76 -> 600 | M76: =+$AL76 -> 600 | N76: =+M76*0.95 -> 570 | O76: =+$AM76 -> 510 | P76: =+$AM76 -> 510 | Q76: =+$AM76 -> 510 | R76: =+Q76*0.97 -> 494.7 | S76: =+$AN76 -> 433.5 | T76: =+$AN76 -> 433.5 | U76: =+$AN76 -> 433.5 | V76: =+U76*0.98 -> 424.83 | W76: =+$AO76 -> 368.475 | X76: =+$AO76 -> 368.475 | Y76: =+$AO76 -> 368.475 | AF76: 0 | AG76: 0 | AH76: 0 | AI76: 0 | AJ76: 0 | AK76: 880 | AL76: 600 | AM76: =+AL76*0.85 -> 510 | AN76: =+AM76*0.85 -> 433.5 | AO76: =+AN76*0.85 -> 368.475
A77: 800G single mode (SiPh) | F77: 0 | G77: 0 | H77: 0 | I77: 0 | J77: 0 | K77: 0 | L77: 500 | M77: 500 | N77: =+M77*0.95 -> 475 | O77: =+$AM$77 -> 450 | P77: =+$AM$77 -> 450 | Q77: =+$AM$77 -> 450 | R77: =+Q77*0.95 -> 427.5 | S77: =+$AN$77 -> 382.5 | T77: =+$AN$77 -> 382.5 | U77: =+$AN$77 -> 382.5 | V77: =+U77*0.95 -> 363.375 | W77: =+$AO$77 -> 325.125 | X77: =+$AO$77 -> 325.125 | Y77: =+$AO$77 -> 325.125 | AK77: 0 | AL77: 500 | AM77: 450 | AN77: =+AM77*0.85 -> 382.5 | AO77: =+AN77*0.85 -> 325.125
A78: 800G multi mode | F78: =+$AK78 -> 630 | G78: =+$AK78 -> 630 | H78: =+$AK78 -> 630 | I78: =+$AK78 -> 630 | J78: 578 | K78: =+$AL78 -> 450 | L78: =+$AL78 -> 450 | M78: =+$AL78 -> 450 | N78: =+M78*0.95 -> 427.5 | O78: =+$AM78 -> 382.5 | P78: =+$AM78 -> 382.5 | Q78: =+$AM78 -> 382.5 | R78: =+Q78*0.97 -> 371.025 | S78: =+$AN78 -> 325.125 | T78: =+$AN78 -> 325.125 | U78: =+$AN78 -> 325.125 | V78: =+U78*0.98 -> 318.6225 | W78: =+$AO78 -> 276.35625 | X78: =+$AO78 -> 276.35625 | Y78: =+$AO78 -> 276.35625 | AF78: 0 | AG78: 0 | AH78: 0 | AI78: 0 | AJ78: 0 | AK78: 630 | AL78: 450 | AM78: =+AL78*0.85 -> 382.5 | AN78: =+AM78*0.85 -> 325.125 | AO78: =+AN78*0.85 -> 276.35625
A79: 1.6T long-range | B79: =+$AJ79 -> 0 | C79: =+$AJ79 -> 0 | D79: =+$AJ79 -> 0 | E79: =+$AJ79 -> 0 | F79: =+$AK79 -> 0 | G79: =+$AK79 -> 0 | H79: =+$AK79 -> 0 | I79: =+$AK79 -> 0 | J79: =+$AL79 -> 0 | K79: =+$AL79 -> 0 | L79: =+$AL79 -> 0 | M79: 1280 | N79: 1280 | O79: 1280 | P79: 1280 | Q79: 1280 | R79: =+Q79*0.9 -> 1152 | S79: =+$AN79 -> 1088 | T79: =+$AN79 -> 1088 | U79: =+$AN79 -> 1088 | V79: =+U79*0.9 -> 979.2 | W79: =+$AO79 -> 924.8 | X79: =+$AO79 -> 924.8 | Y79: =+$AO79 -> 924.8 | AF79: 0 | AG79: 0 | AH79: 0 | AI79: 0 | AJ79: 0 | AK79: 0 | AL79: 0 | AM79: 1280 | AN79: =+AM79*0.85 -> 1088 | AO79: =+AN79*0.85 -> 924.8
A80: 1.6T short-range | F80: =+$AK80 -> 0 | G80: =+$AK80 -> 0 | H80: =+$AK80 -> 0 | I80: =+$AK80 -> 0 | J80: =+$AL80 -> 0 | K80: =+$AL80 -> 0 | L80: =+$AL80 -> 0 | M80: 950 | N80: =+$AM$80 -> 950 | O80: =+$AM$80 -> 950 | P80: =+$AM$80 -> 950 | Q80: =+$AM$80 -> 950 | R80: =+Q80*0.9 -> 855 | S80: =+$AN80 -> 807.5 | T80: =+$AN80 -> 807.5 | U80: =+$AN80 -> 807.5 | V80: =+U80*0.9 -> 726.75 | W80: =+$AO80 -> 686.375 | X80: =+$AO80 -> 686.375 | Y80: =+$AO80 -> 686.375 | AF80: 0 | AG80: 0 | AH80: 0 | AI80: 0 | AJ80: 0 | AK80: 0 | AL80: 0 | AM80: 950 | AN80: =+AM80*0.85 -> 807.5 | AO80: =+AN80*0.85 -> 686.375
A81: 3.2T | X81: 1920 | Y81: 1920 | AO81: 1920
AM82: =+SUM(AM49:AM51)/AM70/7.3 -> 480.52811 | AN82: =+SUM(AN49:AN51)/AN70/7.3 -> 413.052 | AO82: =+SUM(AO49:AO51)/AO70/7.3 -> 359.47783
A83: Price per G (US$) | AM83: =+SUM(AM52:AM53)/AM71/7.3 -> 949.56621 | AN83: =+SUM(AN52:AN53)/AN71/7.3 -> 844.52632 | AO83: =+SUM(AO52:AO53)/AO71/7.3 -> 757.54732
A84: 40G | B84: =+B72/40 -> 0.69366144 | C84: =+C72/40 -> 0.69366144 | D84: =+D72/40 -> 0.69366144 | E84: =+E72/40 -> 0.69366144 | F84: =+F72/40 -> 0.76472603 | G84: =+G72/40 -> 0.76472603 | H84: =+H72/40 -> 0.76472603 | I84: =+I72/40 -> 0.76472603 | ... Y84: =+Y72/40 -> 0.84119863 | AF84: =+AF72/40 -> 0.38356164 | AG84: =+AG72/40 -> 0.38356164 | AH84: =+AH72/40 -> 0.38356164 | AI84: =+AI72/40 -> 0.54452055 | AJ84: =+AJ72/40 -> 0.69366144 | AK84: =+AK72/40 -> 0.76472603 | AL84: =+AL72/40 -> 0.84119863 | AM84: =+AM72/40 -> 0.84119863 | ... AO84: =+AO72/40 -> 0.84119863
A85: 100G | B85: =+B73/100 -> 1.15 | C85: =+C73/100 -> 1.15 | D85: =+D73/100 -> 1.15 | E85: =+E73/100 -> 1.15 | F85: =+F73/100 -> 0.67 | G85: =+G73/100 -> 0.67 | H85: =+H73/100 -> 0.67 | I85: =+I73/100 -> 0.67 | ... Y85: =+Y73/100 -> 0.55 | AF85: =+AF73/100 -> 3.5 | AG85: =+AG73/100 -> 3 | AH85: =+AH73/100 -> 2.55 | AI85: =+AI73/100 -> 2.1675 | AJ85: =+AJ73/100 -> 1.15 | AK85: =+AK73/100 -> 0.67 | AL85: =+AL73/100 -> 0.62684932 | AM85: =+AM73/100 -> 0.60895548 | ... AO85: =+AO73/100 -> 0.55
A86: 200G | B86: =+B74/200 -> 1.0547945 | C86: =+C74/200 -> 1.0547945 | D86: =+D74/200 -> 1.0547945 | E86: =+E74/200 -> 1.0547945 | F86: =+F74/200 -> 0.9 | G86: =+G74/200 -> 0.9 | H86: =+H74/200 -> 0.9 | I86: =+I74/200 -> 0.9 | ... Y86: =+Y74/200 -> 0.6579225 | AF86: =+AF74/200 -> 0 | AG86: =+AG74/200 -> 0 | AH86: =+AH74/200 -> 1.5 | AI86: =+AI74/200 -> 1.25 | AJ86: =+AJ74/200 -> 1.0547945 | AK86: =+AK74/200 -> 0.9 | AL86: =+AL74/200 -> 0.79097847 | AM86: =+AM74/200 -> 0.72775171 | ... AO86: =+AO74/200 -> 0.6579225
A87: 400G | B87: =+B75/400 -> 1.3 | C87: =+C75/400 -> 1.3 | D87: =+D75/400 -> 1.3 | E87: =+E75/400 -> 1.3 | F87: =+F75/400 -> 1.05 | G87: =+G75/400 -> 1.05 | H87: =+H75/400 -> 1.05 | I87: =+I75/400 -> 1.05 | ... Y87: =+Y75/400 -> 0.557685 | AF87: =+AF75/400 -> 0 | AG87: =+AG75/400 -> 0 | AH87: =+AH75/400 -> 2 | AI87: =+AI75/400 -> 1.625 | AJ87: =+AJ75/400 -> 1.3 | AK87: =+AK75/400 -> 1.05 | AL87: =+AL75/400 -> 0.765 | AM87: =+AM75/400 -> 0.6885 | ... AO87: =+AO75/400 -> 0.557685
A88: 800G | B88: =+B76/800 -> 0 | C88: =+C76/800 -> 0 | D88: =+D76/800 -> 0 | E88: =+E76/800 -> 0 | F88: =+F76/800 -> 1.1 | G88: =+G76/800 -> 1.1 | H88: =+H76/800 -> 1.1 | I88: =+I76/800 -> 1.1 | ... Y88: =+Y76/800 -> 0.46059375 | AF88: =+AF76/800 -> 0 | AG88: =+AG76/800 -> 0 | AH88: =+AH76/800 -> 0 | AI88: =+AI76/800 -> 0 | AJ88: =+AJ76/800 -> 0 | AK88: =+AK76/800 -> 1.1 | AL88: =+AL76/800 -> 0.75 | AM88: =+AM76/800 -> 0.6375 | ... AO88: =+AO76/800 -> 0.46059375
A89: 1.6T | B89: =+B79/1600 -> 0 | C89: =+C79/1600 -> 0 | D89: =+D79/1600 -> 0 | E89: =+E79/1600 -> 0 | F89: =+F79/1600 -> 0 | G89: =+G79/1600 -> 0 | H89: =+H79/1600 -> 0 | I89: =+I79/1600 -> 0 | ... Y89: =+Y79/1600 -> 0.578 | AF89: =+AF79/1600 -> 0 | AG89: =+AG79/1600 -> 0 | AH89: =+AH79/1600 -> 0 | AI89: =+AI79/1600 -> 0 | AJ89: =+AJ79/1600 -> 0 | AK89: =+AK79/1600 -> 0 | AL89: =+AL79/1600 -> 0 | AM89: =+AM79/1600 -> 0.8 | ... AO89: =+AO79/1600 -> 0.578
A91: ASP YoY
A92: 10G/40G | F92: =+F84/B84-1 -> 0.10244851 | G92: =+G84/C84-1 -> 0.10244851 | H92: =+H84/D84-1 -> 0.10244851 | I92: =+I84/E84-1 -> 0.10244851 | J92: =+J84/F84-1 -> 0.1 | K92: =+K84/G84-1 -> 0.1 | L92: =+L84/H84-1 -> 0.1 | M92: =+M84/I84-1 -> 0.1 | ... Y92: =+Y84/U84-1 -> 0 | AG92: =+AG72/AF72-1 -> 0 | AH92: =+AH72/AG72-1 -> 0 | AI92: =+AI72/AH72-1 -> 0.41964286 | AJ92: =+AJ72/AI72-1 -> 0.27389397 | AK92: =+AK72/AJ72-1 -> 0.10244851 | AL92: =+AL72/AK72-1 -> 0.1 | AM92: =+AM72/AL72-1 -> 0 | AN92: =+AN72/AM72-1 -> 0 | AO92: =+AO72/AN72-1 -> 0
A93: 100G | F93: =+F85/B85-1 -> -0.4173913 | G93: =+G85/C85-1 -> -0.4173913 | H93: =+H85/D85-1 -> -0.4173913 | I93: =+I85/E85-1 -> -0.4173913 | J93: =+J85/F85-1 -> -0.044776119 | K93: =+K85/G85-1 -> -0.044776119 | L93: =+L85/H85-1 -> -0.044776119 | M93: =+M85/I85-1 -> -0.044776119 | ... Y93: =+Y85/U85-1 -> -0.051724138 | AG93: =+AG73/AF73-1 -> -0.14285714 | AH93: =+AH73/AG73-1 -> -0.15 | AI93: =+AI73/AH73-1 -> -0.15 | AJ93: =+AJ73/AI73-1 -> -0.46943483 | AK93: =+AK73/AJ73-1 -> -0.4173913 | AL93: =+AL73/AK73-1 -> -0.064404007 | AM93: =+AM73/AL73-1 -> -0.028545673 | AN93: =+AN73/AM73-1 -> -0.047549419 | AO93: =+AO73/AN73-1 -> -0.051724138
A94: 200G | F94: =+F86/B86-1 -> -0.14675325 | G94: =+G86/C86-1 -> -0.14675325 | H94: =+H86/D86-1 -> -0.14675325 | I94: =+I86/E86-1 -> -0.14675325 | J94: =+J86/F86-1 -> -0.1 | K94: =+K86/G86-1 -> -0.1 | L94: =+L86/H86-1 -> -0.1 | M94: =+M86/I86-1 -> -0.1 | ... Y94: =+Y86/U86-1 -> -0.05 | AI94: =+AI74/AH74-1 -> -0.16666667 | AJ94: =+AJ74/AI74-1 -> -0.15616438 | AK94: =+AK74/AJ74-1 -> -0.14675325 | AL94: =+AL74/AK74-1 -> -0.12113503 | AM94: =+AM74/AL74-1 -> -0.07993487 | AN94: =+AN74/AM74-1 -> -0.048370497 | AO94: =+AO74/AN74-1 -> -0.05
A95: 400G | F95: =+F87/B87-1 -> -0.19230769 | G95: =+G87/C87-1 -> -0.19230769 | H95: =+H87/D87-1 -> -0.19230769 | I95: =+I87/E87-1 -> -0.19230769 | J95: =+J87/F87-1 -> -0.27142857 | K95: =+K87/G87-1 -> -0.27142857 | L95: =+L87/H87-1 -> -0.27142857 | M95: =+M87/I87-1 -> -0.27142857 | ... Y95: =+Y87/U87-1 -> -0.1 | AI95: =+AI75/AH75-1 -> -0.1875 | AJ95: =+AJ75/AI75-1 -> -0.2 | AK95: =+AK75/AJ75-1 -> -0.19230769 | AL95: =+AL75/AK75-1 -> -0.27142857 | AM95: =+AM75/AL75-1 -> -0.1 | AN95: =+AN75/AM75-1 -> -0.1 | AO95: =+AO75/AN75-1 -> -0.1
A96: 800G single mode (EML) | J96: =+J76/F76-1 -> -0.082954545 | K96: =+K76/G76-1 -> -0.31818182 | L96: =+L76/H76-1 -> -0.31818182 | M96: =+M76/I76-1 -> -0.31818182 | N96: =+N76/J76-1 -> -0.2936803 | O96: =+O76/K76-1 -> -0.15 | P96: =+P76/L76-1 -> -0.15 | Q96: =+Q76/M76-1 -> -0.15 | ... Y96: =+Y76/U76-1 -> -0.15 | AL96: =+AL76/AK76-1 -> -0.31818182 | AM96: =+AM76/AL76-1 -> -0.15 | AN96: =+AN76/AM76-1 -> -0.15 | AO96: =+AO76/AN76-1 -> -0.15
A97: 800G single mode (SiPh) | J97: 0 | K97: 0 | L97: 0 | M97: 0 | N97: 0 | O97: 0 | P97: =+P77/L77-1 -> -0.1 | Q97: =+Q77/M77-1 -> -0.1 | R97: =+R77/N77-1 -> -0.1 | S97: =+S77/O77-1 -> -0.15 | T97: =+T77/P77-1 -> -0.15 | U97: =+U77/Q77-1 -> -0.15 | V97: =+V77/R77-1 -> -0.15 | W97: =+W77/S77-1 -> -0.15 | ... Y97: =+Y77/U77-1 -> -0.15 | AL97: =+AL77/AK77-1 -> #DIV/0! | AM97: =+AM77/AL77-1 -> -0.1 | AN97: =+AN77/AM77-1 -> -0.15 | AO97: =+AO77/AN77-1 -> -0.15
A98: 800G multi mode | J98: =+J78/F78-1 -> -0.082539683 | K98: =+K78/G78-1 -> -0.28571429 | L98: =+L78/H78-1 -> -0.28571429 | M98: =+M78/I78-1 -> -0.28571429 | N98: =+N78/J78-1 -> -0.26038062 | O98: =+O78/K78-1 -> -0.15 | P98: =+P78/L78-1 -> -0.15 | Q98: =+Q78/M78-1 -> -0.15 | ... Y98: =+Y78/U78-1 -> -0.15 | AL98: =+AL78/AK78-1 -> -0.28571429 | AM98: =+AM78/AL78-1 -> -0.15 | AN98: =+AN78/AM78-1 -> -0.15 | AO98: =+AO78/AN78-1 -> -0.15
A99: 1.6T single mode | Q99: =+Q79/M79-1 -> 0 | R99: =+R79/N79-1 -> -0.1 | S99: =+S79/O79-1 -> -0.15 | T99: =+T79/P79-1 -> -0.15 | U99: =+U79/Q79-1 -> -0.15 | V99: =+V79/R79-1 -> -0.15 | W99: =+W79/S79-1 -> -0.15 | X99: =+X79/T79-1 -> -0.15 | Y99: =+Y79/U79-1 -> -0.15 | AN99: =+AN79/AM79-1 -> -0.15 | AO99: =+AO79/AN79-1 -> -0.15
A100: 1.6T multi mode | Q100: =+Q80/M80-1 -> 0 | R100: =+R80/N80-1 -> -0.1 | S100: =+S80/O80-1 -> -0.15 | T100: =+T80/P80-1 -> -0.15 | U100: =+U80/Q80-1 -> -0.15 | V100: =+V80/R80-1 -> -0.15 | W100: =+W80/S80-1 -> -0.15 | X100: =+X80/T80-1 -> -0.15 | Y100: =+Y80/U80-1 -> -0.15 | AN100: =+AN80/AM80-1 -> -0.15 | AO100: =+AO80/AN80-1 -> -0.15
A101: 3.2T
A103: USD-CNY exchange rate | B103: 7 | C103: 7 | D103: 7 | E103: 7 | F103: 7.3 | G103: 7.3 | H103: 7.3 | I103: 7.3 | J103: 7.3 | K103: 7.3 | L103: 7 | M103: 7 | N103: 7.25 | O103: 7.3 | P103: 7.3 | Q103: 7.3 | R103: 7.3 | S103: 7.3 | T103: 7.3 | U103: 7.3 | V103: 7.3 | W103: 7.3 | X103: 7.3 | Y103: 7.3 | AF103: 6.6 | AG103: 6.8 | AH103: 6.8 | AI103: 6.8 | AJ103: 7 | AK103: 7.3 | AL103: 7.3 | AM103: 7.3 | AN103: 7.3 | AO103: 7.3
A105: ASP (Rmb)
A106: 10G/40G | B106: 203 | C106: 203 | D106: 203 | E106: 203 | F106: 223.3 | G106: 223.3 | H106: 223.3 | I106: 223.3 | J106: 245.63 | K106: 245.63 | L106: 245.63 | M106: 245.63 | N106: 245.63 | O106: 245.63 | P106: 245.63 | Q106: 245.63 | R106: 245.63 | S106: 245.63 | T106: 245.63 | U106: 245.63 | V106: 245.63 | W106: 245.63 | X106: 245.63 | Y106: 245.63 | AF106: 112 | AG106: 112 | AH106: 112 | AI106: 159 | AJ106: =+AJ45/AJ60 -> 202.54914 | AK106: =+AK45/AK60 -> 223.3 | AL106: =+AL45/AL60 -> 245.63 | AM106: =+AM45/AM60 -> 245.63 | AN106: =+AN45/AN60 -> 245.63 | AO106: =+AO45/AO60 -> 245.63
A107: 100G | B107: =+B$103*B73 -> 805 | C107: =+C$103*C73 -> 805 | D107: =+D$103*D73 -> 805 | E107: =+E$103*E73 -> 805 | F107: =+F$103*F73 -> 489.1 | G107: =+G$103*G73 -> 489.1 | H107: =+H$103*H73 -> 489.1 | I107: =+I$103*I73 -> 489.1 | ... Y107: =+Y$103*Y73 -> 401.5 | AF107: =+AF$103*AF73 -> 2310 | AG107: =+AG$103*AG73 -> 2040 | AH107: =+AH$103*AH73 -> 1734 | AI107: =+AI$103*AI73 -> 1473.9 | AJ107: =+AJ46/AJ61 -> 805 | AK107: =+AK46/AK61 -> 489.1 | AL107: =+AL46/AL61 -> 457.6 | AM107: =+AM46/AM61 -> 444.5375 | AN107: =+AN46/AN61 -> 423.4 | AO107: =+AO46/AO61 -> 401.5
A108: 200G | B108: =+B$103*B74 -> 1476.7123 | C108: =+C$103*C74 -> 1476.7123 | D108: =+D$103*D74 -> 1476.7123 | E108: =+E$103*E74 -> 1476.7123 | F108: =+F$103*F74 -> 1314 | G108: =+G$103*G74 -> 1314 | H108: =+H$103*H74 -> 1314 | I108: =+I$103*I74 -> 1314 | ... Y108: =+Y$103*Y74 -> 960.56685 | AF108: =+AF$103*AF74 -> 0 | AG108: =+AG$103*AG74 -> 0 | AH108: =+AH$103*AH74 -> 2040 | AI108: =+AI$103*AI74 -> 1700 | AJ108: =+AJ47/AJ62 -> 1476.7123 | AK108: =+AK47/AK62 -> 1314 | AL108: =+AL47/AL62 -> 1154.8286 | AM108: =+AM47/AM62 -> 1062.5175 | AN108: =+AN47/AN62 -> 1011.123 | AO108: =+AO47/AO62 -> 960.56685
A109: 400G | B109: =+B$103*B75 -> 3640 | C109: =+C$103*C75 -> 3640 | D109: =+D$103*D75 -> 3640 | E109: =+E$103*E75 -> 3640 | F109: =+F$103*F75 -> 3066 | G109: =+G$103*G75 -> 3066 | H109: =+H$103*H75 -> 3066 | I109: =+I$103*I75 -> 3066 | ... Y109: =+Y$103*Y75 -> 1628.4402 | AF109: =+AF$103*AF75 -> 0 | AG109: =+AG$103*AG75 -> 0 | AH109: =+AH$103*AH75 -> 5440 | AI109: =+AI$103*AI75 -> 4420 | AJ109: =+AJ$103*AJ75 -> 3640 | AK109: =+AK$103*AK75 -> 3066 | AL109: =+AL$103*AL75 -> 2233.8 | AM109: =+AM$103*AM75 -> 2010.42 | ... AO109: =+AO$103*AO75 -> 1628.4402
A110: 800G single mode (EML) | B110: =+B$103*B76 -> 0 | C110: =+C$103*C76 -> 0 | D110: =+D$103*D76 -> 0 | E110: =+E$103*E76 -> 0 | F110: =+F$103*F76 -> 6424 | G110: =+G$103*G76 -> 6424 | H110: =+H$103*H76 -> 6424 | I110: =+I$103*I76 -> 6424 | ... Y110: =+Y$103*Y76 -> 2689.8675 | AF110: =+AF$103*AF76 -> 0 | AG110: =+AG$103*AG76 -> 0 | AH110: =+AH$103*AH76 -> 0 | AI110: =+AI$103*AI76 -> 0 | AJ110: =+AJ$103*AJ76 -> 0 | AK110: =+AK$103*AK76 -> 6424 | AL110: =+AL$103*AL76 -> 4380 | AM110: =+AM$103*AM76 -> 3723 | ... AO110: =+AO$103*AO76 -> 2689.8675
...
